Workbook

Sheet dinamica
A2: CHOFER | B2: PATENTE | C2: FECHA | D2: AUTOPISTA | E2: SUM of TARIFA | F2: SUM of BONIFICACION
A3: 0 | E3: 86740.56 | F3: 0
A4: Agustin Santino Kuyznierewicz | B4: AH252TW | E4: 115757.06 | F4: 0
A5: Total Agustin Santino Kuyznierewicz | E5: 115757.06 | F5: 0
A6: Amado German Fernandez | B6: Ah087VY | E6: 137817.67 | F6: 0
A7: Total Amado German Fernandez | E7: 137817.67 | F7: 0
A8: Amilcar Alejandro Tellechea | B8: AH252SM | E8: 76576.45 | F8: 0
A9: Total Amilcar Alejandro Tellechea | E9: 76576.45 | F9: 0
A10: Ariel Angel Grismado | B10: AH645XC | E10: 83312.42 | F10: 0
A11: Total Ariel Angel Grismado | E11: 83312.42 | F11: 0
A12: Arturo Omar Kunin Flash & Go | B12: AI325BR | C12: 46261 | D12: Autopistas Urbanas | E12: 1921.05
C13: 46262 | D13: Acceso Norte | E13: 1192.99 | F13: 0
A14: Total Arturo Omar Kunin Flash & Go | E14: 3114.04 | F14: 0
A15: Atilio Miguel Quaini Flash & Go | B15: AI288DX | C15: 46248 | D15: RUTAS SUR ATLANTICO S.A. | E15: 3097.64
C16: 46250 | D16: Aubasa | E16: 2395.04 | F16: 0
C17: 46251 | D17: Aubasa | E17: 6466.59 | F17: 0
D18: Autopista Del Oeste | E18: 1988.3 | F18: 0
C19: 46252 | D19: Aubasa | E19: 4071.55 | F19: 2395.04
C20: 46253 | D20: Aubasa | E20: 10777.65 | F20: 0
C21: 46255 | D21: Aubasa | E21: 8382.61 | F21: 0
D22: Autopista Del Oeste | E22: 1988.3 | F22: 0
C23: 46256 | D23: Aubasa | E23: 9580.16 | F23: 0
C24: 46257 | D24: Aubasa | E24: 4071.55 | F24: 0
D25: Autopista Del Oeste | E25: 2187.14 | F25: 0
C26: 46258 | D26: Aubasa | E26: 8562.25 | F26: 0
D27: Autopistas Urbanas | E27: 2716.64
C28: 46259 | D28: Aubasa | E28: 6765.97 | F28: 0
D29: Autopistas Urbanas | E29: 13069.04
D30: RUTAS SUR ATLANTICO S.A. | E30: 3574.2
C31: 46260 | D31: Aubasa | E31: 10777.65 | F31: 0
C32: 46261 | D32: Aubasa | E32: 9161.01 | F32: 0
D33: Autopista Del Oeste | E33: 1988.3 | F33: 0
D34: Autopistas Urbanas | E34: 16911.14
D35: RUTAS SUR ATLANTICO S.A. | E35: 5361.3
C36: 46262 | D36: Aubasa | E36: 2395.04 | F36: 0
D37: Autopista Del Oeste | E37: 2187.14 | F37: 0
C38: 46263 | D38: Aubasa | E38: 4071.55 | F38: 2395.04
C39: 46264 | D39: Aubasa | E39: 6466.59 | F39: 0
C40: 46265 | D40: Aubasa | E40: 9161.01 | F40: 0
A41: Total Atilio Miguel Quaini Flash & Go | E41: 158175.36 | F41: 4790.08
A42: Calixto Jose Laureano | B42: AI325BF | C42: 46252 | D42: Acceso Norte | E42: 2385.98 | F42: 0
C43: 46254 | D43: Acceso Norte | E43: 2385.98 | F43: 0
C44: 46256 | D44: RUTAS SUR ATLANTICO S.A. | E44: 3335.92
C45: 46258 | D45: Acceso Norte | E45: 994.15 | F45: 0
D46: Autopistas Urbanas | E46: 4637.69
C47: 46259 | D47: Autopistas Urbanas | E47: 11145.5
D48: RUTAS SUR ATLANTICO S.A. | E48: 3335.92
C49: 46260 | D49: Autopistas Urbanas | E49: 9221.96
D50: RUTAS SUR ATLANTICO S.A. | E50: 3097.64
C51: 46261 | D51: Autopistas Urbanas | E51: 1921.05
C52: 46265 | D52: Acceso Norte | E52: 1988.3 | F52: 0
A53: Total Calixto Jose Laureano | E53: 44450.09 | F53: 0
A54: Carlos Enrique Huama Felipe | B54: AH252SV | E54: 54562.64 | F54: 0
A55: Total Carlos Enrique Huama Felipe | E55: 54562.64 | F55: 0
A56: Carlos Fernando Viviani Flash & Go | B56: AI325BZ | C56: 46249 | D56: RUTAS SUR ATLANTICO S.A. | E56: 6910.12
C57: 46250 | D57: Acceso Norte | E57: 2584.79 | F57: 0
D58: Autopista Del Oeste | E58: 1192.99 | F58: 0
C59: 46251 | D59: Acceso Norte | E59: 4771.96 | F59: 0
D60: Autopista Del Oeste | E60: 4175.44 | F60: 0
D61: Ceamse | E61: 3000
C62: 46252 | D62: Acceso Norte | E62: 4771.96 | F62: 0
D63: Ceamse | E63: 3000
C64: 46253 | D64: Acceso Norte | E64: 6561.42 | F64: 0
D65: Autopista Del Oeste | E65: 994.15 | F65: 0
D66: Ceamse | E66: 6000
C67: 46254 | D67: Acceso Norte | E67: 2187.14 | F67: 0
C68: 46255 | D68: Acceso Norte | E68: 2385.98 | F68: 0
D69: Autopista Del Oeste | E69: 2187.14 | F69: 0
D70: RUTAS SUR ATLANTICO S.A. | E70: 1548.82
C71: 46256 | D71: Acceso Norte | E71: 3181.29 | F71: 0
D72: Autopista Del Oeste | E72: 994.15 | F72: 0
C73: 46257 | D73: Acceso Norte | E73: 3181.29 | F73: 0
D74: Autopista Del Oeste | E74: 994.15 | F74: 0
D75: RUTAS SUR ATLANTICO S.A. | E75: 3335.92
C76: 46258 | D76: Acceso Norte | E76: 4374.28 | F76: 0
D77: Autopistas Urbanas | E77: 10070.97
C78: 46259 | D78: Acceso Norte | E78: 4374.28 | F78: 0
D79: Autopistas Urbanas | E79: 1921.05
D80: Ceamse | E80: 3000
C81: 46260 | D81: Acceso Norte | E81: 2187.14 | F81: 0
D82: Autopista Del Oeste | E82: 994.15 | F82: 0
D83: Autopistas Urbanas | E83: 17680.02
D84: Ceamse | E84: 3000
D85: RUTAS SUR ATLANTICO S.A. | E85: 4884.74
C86: 46261 | D86: Acceso Norte | E86: 2187.14 | F86: 0
D87: Autopistas Urbanas | E87: 3842.1
C88: 46262 | D88: Acceso Norte | E88: 994.15 | F88: 0
D89: Ceamse | E89: 3000
C90: 46263 | D90: Acceso Norte | E90: 994.15 | F90: 0
D91: Ceamse | E91: 6000
C92: 46264 | D92: Acceso Norte | E92: 2187.14 | F92: 0
D93: Autopista Del Oeste | E93: 994.15 | F93: 0
D94: Ceamse | E94: 6000
C95: 46265 | D95: Acceso Norte | E95: 994.15 | F95: 0
A96: Total Carlos Fernando Viviani Flash & Go | E96: 143638.32 | F96: 0
A97: Carlos Gustavo Zabala | B97: AI325BC | C97: 46248 | D97: RUTAS SUR ATLANTICO S.A. | E97: 1787.1
C98: 46250 | D98: Aubasa | E98: 4790.08 | F98: 0
D99: RUTAS SUR ATLANTICO S.A. | E99: 4884.74
C100: 46251 | D100: Aubasa | E100: 7185.12 | F100: 0
D101: RUTAS SUR ATLANTICO S.A. | E101: 3097.64
...

Sheet con patente
A2: CHOFER | B2: PATENTE | C2: FECHA | D2: AUTOPISTA | E2: SUM of TARIFA | F2: SUM of BONIFICACION
A3: 0 | B3: AH191LS | C3: 46262 | D3: Autopista Del Oeste | E3: 2385.98 | F3: 0
C4: 46265 | D4: Aubasa | E4: 5089.44 | F4: 0
B5: AH205QG | C5: 46254 | D5: RUTAS SUR ATLANTICO S.A. | E5: 1787.1
B6: AH252SQ | E6: 13069.04
B7: AH252TJ | C7: 46259 | D7: Acceso Norte | E7: 2385.98 | F7: 0
D8: Autopistas Urbanas | E8: 2716.64
B9: AH502KF | C9: 46265 | D9: Acceso Norte | E9: 994.15 | F9: 0
D10: Autopista Del Oeste | E10: 1192.99 | F10: 0
D11: Ceamse | E11: 6000
B12: AI210DK | C12: 46256 | D12: Acceso Norte | E12: 2385.98 | F12: 0
D13: Autopistas Urbanas | E13: 2716.64
B14: AI210DL | C14: 46255 | D14: Autopistas Urbanas | E14: 4610.98
C15: 46256 | D15: Autopista Del Oeste | E15: 994.15 | F15: 0
C16: 46257 | D16: Autopista Del Oeste | E16: 1988.3 | F16: 0
D17: Autopistas Urbanas | E17: 4610.98
C18: 46258 | D18: Autopista Del Oeste | E18: 2385.98 | F18: 0
D19: Autopistas Urbanas | E19: 6534.52
C20: 46259 | D20: Autopista Del Oeste | E20: 2187.14 | F20: 0
C21: 46260 | D21: Autopista Del Oeste | E21: 2187.14 | F21: 0
D22: Autopistas Urbanas | E22: 4610.98
C23: 46261 | D23: Autopista Del Oeste | E23: 2385.98 | F23: 0
C24: 46262 | D24: Autopista Del Oeste | E24: 3380.13 | F24: 0
C25: 46263 | D25: Autopista Del Oeste | E25: 2982.45 | F25: 0
C26: 46264 | D26: Autopista Del Oeste | E26: 3976.6 | F26: 0
C27: 46265 | D27: Autopista Del Oeste | E27: 3181.29 | F27: 0
A28: Total 0 | E28: 86740.56 | F28: 0
A29: Agustin Santino Kuyznierewicz | B29: AH252TW | E29: 115757.06 | F29: 0
A30: Total Agustin Santino Kuyznierewicz | E30: 115757.06 | F30: 0
A31: Amado German Fernandez | B31: Ah087VY | E31: 137817.67 | F31: 0
A32: Total Amado German Fernandez | E32: 137817.67 | F32: 0
A33: Amilcar Alejandro Tellechea | B33: AH252SM | E33: 76576.45 | F33: 0
A34: Total Amilcar Alejandro Tellechea | E34: 76576.45 | F34: 0
A35: Ariel Angel Grismado | B35: AH645XC | C35: 46252 | D35: Acceso Norte | E35: 2187.14 | F35: 0
D36: Autopista Del Oeste | E36: 2385.98 | F36: 0
D37: Ceamse | E37: 6000
C38: 46253 | D38: Acceso Norte | E38: 994.15 | F38: 0
D39: Autopista Del Oeste | E39: 3380.13 | F39: 0
D40: Ceamse | E40: 6000
C41: 46254 | D41: Acceso Norte | E41: 1192.99 | F41: 0
D42: Autopista Del Oeste | E42: 1192.99 | F42: 0
D43: Ceamse | E43: 3000
C44: 46255 | D44: Autopista Del Oeste | E44: 2385.98 | F44: 0
C45: 46258 | D45: Acceso Norte | E45: 4573.12 | F45: 0
D46: Autopista Del Oeste | E46: 994.15 | F46: 0
D47: Ceamse | E47: 6000
C48: 46259 | D48: Acceso Norte | E48: 994.15 | F48: 0
D49: Autopista Del Oeste | E49: 2385.98 | F49: 0
D50: Autopistas Urbanas | E50: 6534.52
C51: 46260 | D51: Acceso Norte | E51: 2385.98 | F51: 0
D52: Autopista Del Oeste | E52: 1988.3 | F52: 0
D53: Ceamse | E53: 6000
C54: 46261 | D54: Acceso Norte | E54: 994.15 | F54: 0
D55: Autopista Del Oeste | E55: 2187.14 | F55: 0
D56: Ceamse | E56: 6000
C57: 46262 | D57: Autopista Del Oeste | E57: 3181.29 | F57: 0
D58: Ceamse | E58: 3000
C59: 46264 | D59: Acceso Norte | E59: 1988.3 | F59: 0
D60: Ceamse | E60: 3000
C61: 46265 | D61: Autopista Del Oeste | E61: 2385.98 | F61: 0
A62: Total Ariel Angel Grismado | E62: 83312.42 | F62: 0
A63: Arturo Omar Kunin Flash & Go | B63: AI325BR | C63: 46261 | D63: Autopistas Urbanas | E63: 1921.05 | G63: NOTIF
C64: 46262 | D64: Acceso Norte | E64: 1192.99 | F64: 0
A65: Total Arturo Omar Kunin Flash & Go | E65: 3114.04 | F65: 0
A66: Atilio Miguel Quaini Flash & Go | B66: AI288DX | C66: 46248 | D66: RUTAS SUR ATLANTICO S.A. | E66: 3097.64
C67: 46250 | D67: Aubasa | E67: 2395.04 | F67: 0
C68: 46251 | D68: Aubasa | E68: 6466.59 | F68: 0
D69: Autopista Del Oeste | E69: 1988.3 | F69: 0
C70: 46252 | D70: Aubasa | E70: 4071.55 | F70: 2395.04
C71: 46253 | D71: Aubasa | E71: 10777.65 | F71: 0
C72: 46255 | D72: Aubasa | E72: 8382.61 | F72: 0
D73: Autopista Del Oeste | E73: 1988.3 | F73: 0
C74: 46256 | D74: Aubasa | E74: 9580.16 | F74: 0
C75: 46257 | D75: Aubasa | E75: 4071.55 | F75: 0
D76: Autopista Del Oeste | E76: 2187.14 | F76: 0
C77: 46258 | D77: Aubasa | E77: 8562.25 | F77: 0
D78: Autopistas Urbanas | E78: 2716.64
C79: 46259 | D79: Aubasa | E79: 6765.97 | F79: 0
D80: Autopistas Urbanas | E80: 13069.04
D81: RUTAS SUR ATLANTICO S.A. | E81: 3574.2
C82: 46260 | D82: Aubasa | E82: 10777.65 | F82: 0
C83: 46261 | D83: Aubasa | E83: 9161.01 | F83: 0
D84: Autopista Del Oeste | E84: 1988.3 | F84: 0
D85: Autopistas Urbanas | E85: 16911.14
D86: RUTAS SUR ATLANTICO S.A. | E86: 5361.3
C87: 46262 | D87: Aubasa | E87: 2395.04 | F87: 0
D88: Autopista Del Oeste | E88: 2187.14 | F88: 0
C89: 46263 | D89: Aubasa | E89: 4071.55 | F89: 2395.04
C90: 46264 | D90: Aubasa | E90: 6466.59 | F90: 0
C91: 46265 | D91: Aubasa | E91: 9161.01 | F91: 0
A92: Total Atilio Miguel Quaini Flash & Go | E92: 158175.36 | F92: 4790.08
A93: Calixto Jose Laureano | B93: AI325BF | C93: 46252 | D93: Acceso Norte | E93: 2385.98 | F93: 0
C94: 46254 | D94: Acceso Norte | E94: 2385.98 | F94: 0
C95: 46256 | D95: RUTAS SUR ATLANTICO S.A. | E95: 3335.92
C96: 46258 | D96: Acceso Norte | E96: 994.15 | F96: 0
D97: Autopistas Urbanas | E97: 4637.69
C98: 46259 | D98: Autopistas Urbanas | E98: 11145.5
D99: RUTAS SUR ATLANTICO S.A. | E99: 3335.92
C100: 46260 | D100: Autopistas Urbanas | E100: 9221.96 | G100: NOTIF
D101: RUTAS SUR ATLANTICO S.A. | E101: 3097.64
...

Sheet PASADAS
A1: FECHA | B1: PATENTE | C1: CHOFER | D1: AUTOPISTA | E1: HORA | F1: ESTACION | G1: VIA | H1: DISPOSITIVO | I1: CATEGORIA | J1: TARIFA | K1: BONIFICACION | L1: TIPO_DE_DOCUMENTO | M1: DOCUMENTO_LEGAL | N1: DOCUMENTO_SA | O1: CLIENTE__WEB | P1: CLIENTE_RED | Q1: SUB_CUENTA | R1: COBROS
A2: 46261 | B2: AI325BV | C2: {=INDEX(CHOFERES!$1:$1001,MATCH(A2,CHOFERES!$A:$A,0),MATCH(B2,CHOFERES!$1:$1,0))} -> Rodrigo Roberto Cussi Rueda | D2: Autopistas Urbanas | E2: 0.58258102 | F2: VAR | G2: 02P | H2: 61024087 | I2: 2 | J2: 4610.98
A3: 46257 | B3: AI288CT | C3: {=INDEX(CHOFERES!$1:$1001,MATCH(A3,CHOFERES!$A:$A,0),MATCH(B3,CHOFERES!$1:$1,0))} -> Hugo Mario Pereyra | D3: Autopistas Urbanas | E3: 0.65666667 | F3: PB1 | G3: 02N | H3: 61024058 | I3: 2 | J3: 10202.36
A4: 46260 | B4: AH387LH | C4: {=INDEX(CHOFERES!$1:$1001,MATCH(A4,CHOFERES!$A:$A,0),MATCH(B4,CHOFERES!$1:$1,0))} -> Victor Hugo Liendro | D4: Autopistas Urbanas | E4: 0.17736111 | F4: VAR | G4: 04P | H4: 60618256 | I4: 2 | J4: 4610.98
A5: 46261 | B5: AH448UA | C5: {=INDEX(CHOFERES!$1:$1001,MATCH(A5,CHOFERES!$A:$A,0),MATCH(B5,CHOFERES!$1:$1,0))} -> Mariano Martin Carello | D5: Autopistas Urbanas | E5: 0.95064815 | F5: VAR | G5: 05P | H5: 60618244 | I5: 2 | J5: 4610.98
A6: 46259 | B6: AH191LX | C6: {=INDEX(CHOFERES!$1:$1001,MATCH(A6,CHOFERES!$A:$A,0),MATCH(B6,CHOFERES!$1:$1,0))} -> Daniel Oscar Aguirre | D6: Autopistas Urbanas | E6: 0.71561343 | F6: VAR | G6: 03P | H6: 67199775 | I6: 2 | J6: 6534.52
A7: 46259 | B7: AH502KG | C7: {=INDEX(CHOFERES!$1:$1001,MATCH(A7,CHOFERES!$A:$A,0),MATCH(B7,CHOFERES!$1:$1,0))} -> Javier Lucio Aldea Medrano | D7: Autopistas Urbanas | E7: 0.40787037 | F7: VAR | G7: 05P | H7: 67339635 | I7: 2 | J7: 6534.52
A8: 46260 | B8: AI325BQ | C8: {=INDEX(CHOFERES!$1:$1001,MATCH(A8,CHOFERES!$A:$A,0),MATCH(B8,CHOFERES!$1:$1,0))} -> Ruben Enrique Perez Matamoros Flash & Go | D8: Autopistas Urbanas | E8: 0.4628588 | F8: REM | G8: 04C | H8: 61024084 | I8: 2 | J8: 4610.98
A9: 46260 | B9: AI325CC | C9: {=INDEX(CHOFERES!$1:$1001,MATCH(A9,CHOFERES!$A:$A,0),MATCH(B9,CHOFERES!$1:$1,0))} -> Damian Oscar Gordillo Flash & Go | D9: Autopistas Urbanas | E9: 0.6891088 | F9: VAR | G9: 04P | H9: 61024046 | I9: 2 | J9: 6534.52
A10: 46258 | B10: AH252ST | C10: {=INDEX(CHOFERES!$1:$1001,MATCH(A10,CHOFERES!$A:$A,0),MATCH(B10,CHOFERES!$1:$1,0))} -> Lucas Gabriel Lema | D10: Autopistas Urbanas | E10: 0.70695602 | F10: KDT | G10: 05P | H10: 60613512 | I10: 2 | J10: 2716.64
A11: 46259 | B11: AI288DU | C11: {=INDEX(CHOFERES!$1:$1001,MATCH(A11,CHOFERES!$A:$A,0),MATCH(B11,CHOFERES!$1:$1,0))} -> Daniel Esteban Godoy | D11: Autopistas Urbanas | E11: 0.8847338 | F11: KDT | G11: 05P | H11: 61024063 | I11: 2 | J11: 1921.05
A12: 46261 | B12: AI325CA | C12: {=INDEX(CHOFERES!$1:$1001,MATCH(A12,CHOFERES!$A:$A,0),MATCH(B12,CHOFERES!$1:$1,0))} -> Mario Ezequiel Garcia | D12: Autopistas Urbanas | E12: 0.78128472 | F12: ALB | G12: 04B | H12: 61024056 | I12: 2 | J12: 1844.24
A13: 46260 | B13: AH252TT | C13: {=INDEX(CHOFERES!$1:$1001,MATCH(A13,CHOFERES!$A:$A,0),MATCH(B13,CHOFERES!$1:$1,0))} -> Sandro Facundo Portal | D13: Autopistas Urbanas | E13: 0.18233796 | F13: VAR | G13: 04P | H13: 60615287 | I13: 2 | J13: 4610.98
... A545: 46261 | B545: AH387LG | C545: {=INDEX(CHOFERES!$1:$1001,MATCH(A545,CHOFERES!$A:$A,0),MATCH(B545,CHOFERES!$1:$1,0))} -> Rafael Miguel Paucara | D545: Autopistas Urbanas | E545: 0.35449074 | F545: KDT | G545: 05C | H545: 60618249 | I545: 2 | J545: 2716.64
A546: 46248 | B546: AH087VY | C546: {=INDEX(CHOFERES!$1:$1001,MATCH(A546,CHOFERES!$A:$A,0),MATCH(B546,CHOFERES!$1:$1,0))} -> Amado German Fernandez | D546: AEROPUERTOS ARGENTINA 2000 SA | E546: 19:53:39 | F546: EZEIZA - PARKING AEROPUERTO EZEIZA | G546: VIA 11 | H546: 67199955 | J546: 9000
A547: 46247 | B547: AH252TL | C547: {=INDEX(CHOFERES!$1:$1001,MATCH(A547,CHOFERES!$A:$A,0),MATCH(B547,CHOFERES!$1:$1,0))} -> Claudio Matias Minuet | D547: AEROPUERTOS ARGENTINA 2000 SA | E547: 14:04:09 | F547: EZEIZA - PARKING AEROPUERTO EZEIZA | G547: VIA 09 | H547: 60615293 | J547: 13500
A548: 46261 | B548: AH252TN | C548: {=INDEX(CHOFERES!$1:$1001,MATCH(A548,CHOFERES!$A:$A,0),MATCH(B548,CHOFERES!$1:$1,0))} -> Juan Manuel Suarez | D548: AEROPUERTOS ARGENTINA 2000 SA | E548: 14:33:45 | F548: EZEIZA - PARKING AEROPUERTO EZEIZA | G548: VIA 11 | H548: 60615295 | J548: 9000
A549: 46249 | B549: AH387LM | C549: {=INDEX(CHOFERES!$1:$1001,MATCH(A549,CHOFERES!$A:$A,0),MATCH(B549,CHOFERES!$1:$1,0))} -> Walter Lujan Testori | D549: AEROPUERTOS ARGENTINA 2000 SA | E549: 13:06:38 | F549: EZEIZA - PARKING AEROPUERTO EZEIZA | G549: VIA 12 | H549: 60618236 | J549: 9000
A550: 46259 | B550: AI274QT | C550: {=INDEX(CHOFERES!$1:$1001,MATCH(A550,CHOFERES!$A:$A,0),MATCH(B550,CHOFERES!$1:$1,0))} -> USO RB | D550: ARGENTINA COMMERCIAL PROPERTIES S.A. | E550: 16:05:37 | F550: PARKING - SAN MARTIN 1225, CABA | G550: SALIDA SAN MARTIN | H550: 61024004 | J550: 39200
A551: 46257 | B551: AI288DV | C551: {=INDEX(CHOFERES!$1:$1001,MATCH(A551,CHOFERES!$A:$A,0),MATCH(B551,CHOFERES!$1:$1,0))} -> Jose Ignacio Tombetta | D551: AEROPUERTOS ARGENTINA 2000 SA | E551: 17:15:16 | F551: EZEIZA - PARKING AEROPUERTO EZEIZA | G551: VIA 10 | H551: 61024064 | J551: 9000
A552: 46259 | B552: AI288DV | C552: {=INDEX(CHOFERES!$1:$1001,MATCH(A552,CHOFERES!$A:$A,0),MATCH(B552,CHOFERES!$1:$1,0))} -> Jose Ignacio Tombetta | D552: AEROPUERTOS ARGENTINA 2000 SA | E552: 13:04:01 | F552: EZEIZA - PARKING AEROPUERTO EZEIZA | G552: VIA 13 | H552: 61024064 | J552: 9000
A553: 46260 | B553: AI288DV | C553: {=INDEX(CHOFERES!$1:$1001,MATCH(A553,CHOFERES!$A:$A,0),MATCH(B553,CHOFERES!$1:$1,0))} -> Jose Ignacio Tombetta | D553: AEROPUERTOS ARGENTINA 2000 SA | E553: 11:04:08 | F553: EZEIZA - PARKING AEROPUERTO EZEIZA | G553: VIA 13 | H553: 61024064 | J553: 9000
A554: 46260 | B554: AI288DV | C554: {=INDEX(CHOFERES!$1:$1001,MATCH(A554,CHOFERES!$A:$A,0),MATCH(B554,CHOFERES!$1:$1,0))} -> Jose Ignacio Tombetta | D554: AEROPUERTOS ARGENTINA 2000 SA | E554: 17:05:41 | F554: EZEIZA - PARKING AEROPUERTO EZEIZA | G554: VIA 12 | H554: 61024064 | J554: 9000
A555: 46256 | B555: AI288DZ | C555: {=INDEX(CHOFERES!$1:$1001,MATCH(A555,CHOFERES!$A:$A,0),MATCH(B555,CHOFERES!$1:$1,0))} -> Mario Daniel Lanzilotti | D555: AEROPUERTOS ARGENTINA 2000 SA | E555: 15:13:24 | F555: EZEIZA - PARKING AEROPUERTO EZEIZA | G555: VIA 13 | H555: 61024060 | J555: 9000
A556: 46257 | B556: AI325BB | C556: {=INDEX(CHOFERES!$1:$1001,MATCH(A556,CHOFERES!$A:$A,0),MATCH(B556,CHOFERES!$1:$1,0))} -> Leopoldo Lucas Matias Peralta | D556: AEROPUERTOS ARGENTINA 2000 SA | E556: 17:19:10 | F556: EZEIZA - PARKING AEROPUERTO EZEIZA | G556: VIA 12 | H556: 61024059 | J556: 9000
A557: 46258 | B557: AI325BB | C557: {=INDEX(CHOFERES!$1:$1001,MATCH(A557,CHOFERES!$A:$A,0),MATCH(B557,CHOFERES!$1:$1,0))} -> Leopoldo Lucas Matias Peralta | D557: AEROPUERTOS ARGENTINA 2000 SA | E557: 13:45:24 | F557: EZEIZA - PARKING AEROPUERTO EZEIZA | G557: VIA 11 | H557: 61024059 | J557: 13500
... A1373: 46261 | B1373: AI325CC | C1373: {=INDEX(CHOFERES!$1:$1001,MATCH(A1373,CHOFERES!$A:$A,0),MATCH(B1373,CHOFERES!$1:$1,0))} -> Damian Oscar Gordillo Flash & Go | D1373: RUTAS SUR ATLANTICO S.A. | E1373: 18:47:35 | F1373: AGÜERO - AU.RICCHIERI KM 15,80 | G1373: VIA 16 | H1373: 61024046 | J1373: 1787.1
A1374: 46250 | B1374: AI325BI | C1374: {=INDEX(CHOFERES!$1:$1001,MATCH(A1374,CHOFERES!$A:$A,0),MATCH(B1374,CHOFERES!$1:$1,0))} -> Diego Rafel Minuet | D1374: Autopista Del Oeste | E1374: 0.015277778 | F1374: SANTA ROSA | G1374: 3 | H1374: 61024039 | J1374: 994.15 | K1374: 0
A1375: 46250 | B1375: AH252TT | C1375: {=INDEX(CHOFERES!$1:$1001,MATCH(A1375,CHOFERES!$A:$A,0),MATCH(B1375,CHOFERES!$1:$1,0))} -> Sandro Facundo Portal | D1375: Autopista Del Oeste | E1375: 0.073634259 | F1375: VERGARA | G1375: 7 | H1375: 60615287 | J1375: 994.15 | K1375: 0
A1376: 46250 | B1376: AH252TW | C1376: {=INDEX(CHOFERES!$1:$1001,MATCH(A1376,CHOFERES!$A:$A,0),MATCH(B1376,CHOFERES!$1:$1,0))} -> Agustin Santino Kuyznierewicz | D1376: Autopista Del Oeste | E1376: 0.09630787 | F1376: VERGARA | G1376: 8 | H1376: 60613531 | J1376: 994.15 | K1376: 0
A1377: 46250 | B1377: AH387LD | C1377: {=INDEX(CHOFERES!$1:$1001,MATCH(A1377,CHOFERES!$A:$A,0),MATCH(B1377,CHOFERES!$1:$1,0))} -> Marcelo Fabian Sindaco | D1377: Autopista Del Oeste | E1377: 0.11115741 | F1377: MARTIN FIERRO | G1377: 2 | H1377: 60618241 | J1377: 994.15 | K1377: 0
A1378: 46250 | B1378: AH387LD | C1378: {=INDEX(CHOFERES!$1:$1001,MATCH(A1378,CHOFERES!$A:$A,0),MATCH(B1378,CHOFERES!$1:$1,0))} -> Marcelo Fabian Sindaco | D1378: Autopista Del Oeste | E1378: 0.14618056 | F1378: MARTIN FIERRO | G1378: 4 | H1378: 60618241 | J1378: 994.15 | K1378: 0
A1379: 46250 | B1379: AH252TK | C1379: {=INDEX(CHOFERES!$1:$1001,MATCH(A1379,CHOFERES!$A:$A,0),MATCH(B1379,CHOFERES!$1:$1,0))} -> Rolando Antonio Bustos Cavieres | D1379: Autopista Del Oeste | E1379: 0.15346065 | F1379: VERGARA | G1379: 2 | H1379: 60615286 | J1379: 994.15 | K1379: 0
A1380: 46250 | B1380: AH252TW | C1380: {=INDEX(CHOFERES!$1:$1001,MATCH(A1380,CHOFERES!$A:$A,0),MATCH(B1380,CHOFERES!$1:$1,0))} -> Agustin Santino Kuyznierewicz | D1380: Autopista Del Oeste | E1380: 0.15748843 | F1380: POSADAS | G1380: 2 | H1380: 60613531 | J1380: 994.15 | K1380: 0
A1381: 46250 | B1381: AH252TW | C1381: {=INDEX(CHOFERES!$1:$1001,MATCH(A1381,CHOFERES!$A:$A,0),MATCH(B1381,CHOFERES!$1:$1,0))} -> Agustin Santino Kuyznierewicz | D1381: Autopista Del Oeste | E1381: 0.1640162 | F1381: SANTA ROSA | G1381: 3 | H1381: 60613531 | J1381: 994.15 | K1381: 0
A1382: 46250 | B1382: AH387LD | C1382: {=INDEX(CHOFERES!$1:$1001,MATCH(A1382,CHOFERES!$A:$A,0),MATCH(B1382,CHOFERES!$1:$1,0))} -> Marcelo Fabian Sindaco | D1382: Autopista Del Oeste | E1382: 0.17097222 | F1382: ITUZAINGO | G1382: 11 | H1382: 60618241 | J1382: 994.15 | K1382: 0
A1383: 46250 | B1383: AI325BA | C1383: {=INDEX(CHOFERES!$1:$1001,MATCH(A1383,CHOFERES!$A:$A,0),MATCH(B1383,CHOFERES!$1:$1,0))} -> Patricio Joel Vergniaud | D1383: Autopista Del Oeste | E1383: 0.18251157 | F1383: ITUZAINGO | G1383: 12 | H1383: 61024054 | J1383: 994.15 | K1383: 0
A1384: 46250 | B1384: AH252TT | C1384: {=INDEX(CHOFERES!$1:$1001,MATCH(A1384,CHOFERES!$A:$A,0),MATCH(B1384,CHOFERES!$1:$1,0))} -> Sandro Facundo Portal | D1384: Autopista Del Oeste | E1384: 0.1853125 | F1384: ITUZAINGO | G1384: 11 | H1384: 60615287 | J1384: 994.15 | K1384: 0
A1385: 46250 | B1385: AH252TK | C1385: {=INDEX(CHOFERES!$1:$1001,MATCH(A1385,CHOFERES!$A:$A,0),MATCH(B1385,CHOFERES!$1:$1,0))} -> Rolando Antonio Bustos Cavieres | D1385: Autopista Del Oeste | E1385: 0.19337963 | F1385: BARCALA | G1385: 5 | H1385: 60615286 | J1385: 994.15 | K1385: 0
... A2952: 46265 | B2952: AI210DQ | C2952: {=INDEX(CHOFERES!$1:$1001,MATCH(A2952,CHOFERES!$A:$A,0),MATCH(B2952,CHOFERES!$1:$1,0))} -> Vanina Leonor Lezcano | D2952: Acceso Norte | E2952: 0.98172454 | F2952: RUTA 197 DESCENDENTE | G2952: 5 | H2952: 61024088 | J2952: 994.15 | K2952: 0
A2953: 46265 | B2953: AH502KG | C2953: {=INDEX(CHOFERES!$1:$1001,MATCH(A2953,CHOFERES!$A:$A,0),MATCH(B2953,CHOFERES!$1:$1,0))} -> Javier Lucio Aldea Medrano | D2953: Aubasa | E2953: 85015 | F2953: 1 | G2953: 01M | H2953: 67339635 | J2953: 2993.8 | K2953: 0
A2954: 46264 | B2954: AH191LK | C2954: {=INDEX(CHOFERES!$1:$1001,MATCH(A2954,CHOFERES!$A:$A,0),MATCH(B2954,CHOFERES!$1:$1,0))} -> Yesica Andrea Garcia | D2954: Aubasa | E2954: 150521 | F2954: 1 | G2954: 01M | H2954: 67199780 | J2954: 2395.04 | K2954: 0
A2955: 46256 | B2955: AI325BC | C2955: {=INDEX(CHOFERES!$1:$1001,MATCH(A2955,CHOFERES!$A:$A,0),MATCH(B2955,CHOFERES!$1:$1,0))} -> Carlos Gustavo Zabala | D2955: Aubasa | E2955: 104720 | F2955: 1 | G2955: 01M | H2955: 61024061 | J2955: 2395.04 | K2955: 0
A2956: 46252 | B2956: AH252TP | C2956: {=INDEX(CHOFERES!$1:$1001,MATCH(A2956,CHOFERES!$A:$A,0),MATCH(B2956,CHOFERES!$1:$1,0))} -> Sergio Daniel Siñani Calle | D2956: Aubasa | E2956: 185708 | F2956: 1 | G2956: 02M | H2956: 60613532 | J2956: 2993.8 | K2956: 0
A2957: 46252 | B2957: AH645XD | C2957: {=INDEX(CHOFERES!$1:$1001,MATCH(A2957,CHOFERES!$A:$A,0),MATCH(B2957,CHOFERES!$1:$1,0))} -> Hugo Cesar Fernandez Britez | D2957: Aubasa | E2957: 34859 | F2957: 1 | G2957: 02M | H2957: 67339634 | J2957: 2395.04 | K2957: 0
A2958: 46251 | B2958: AI325BV | C2958: {=INDEX(CHOFERES!$1:$1001,MATCH(A2958,CHOFERES!$A:$A,0),MATCH(B2958,CHOFERES!$1:$1,0))} -> Rodrigo Roberto Cussi Rueda | D2958: Aubasa | E2958: 200848 | F2958: 1 | G2958: 02M | H2958: 61024087 | J2958: 2395.04 | K2958: 0
A2959: 46251 | B2959: AH645XD | C2959: {=INDEX(CHOFERES!$1:$1001,MATCH(A2959,CHOFERES!$A:$A,0),MATCH(B2959,CHOFERES!$1:$1,0))} -> Hugo Cesar Fernandez Britez | D2959: Aubasa | E2959: 191638 | F2959: 1 | G2959: 02M | H2959: 67339634 | J2959: 2395.04 | K2959: 0
A2960: 46251 | B2960: AI325BV | C2960: {=INDEX(CHOFERES!$1:$1001,MATCH(A2960,CHOFERES!$A:$A,0),MATCH(B2960,CHOFERES!$1:$1,0))} -> Rodrigo Roberto Cussi Rueda | D2960: Aubasa | E2960: 161700 | F2960: 1 | G2960: 02M | H2960: 61024087 | J2960: 2395.04 | K2960: 0
A2961: 46251 | B2961: AI325BC | C2961: {=INDEX(CHOFERES!$1:$1001,MATCH(A2961,CHOFERES!$A:$A,0),MATCH(B2961,CHOFERES!$1:$1,0))} -> Carlos Gustavo Zabala | D2961: Aubasa | E2961: 75247 | F2961: 1 | G2961: 02M | H2961: 61024061 | J2961: 2395.04 | K2961: 0
A2962: 46250 | B2962: AH645XD | C2962: {=INDEX(CHOFERES!$1:$1001,MATCH(A2962,CHOFERES!$A:$A,0),MATCH(B2962,CHOFERES!$1:$1,0))} -> Hugo Cesar Fernandez Britez | D2962: Aubasa | E2962: 185817 | F2962: 1 | G2962: 02M | H2962: 67339634 | J2962: 2395.04 | K2962: 0
A2963: 46250 | B2963: AH502KG | C2963: {=INDEX(CHOFERES!$1:$1001,MATCH(A2963,CHOFERES!$A:$A,0),MATCH(B2963,CHOFERES!$1:$1,0))} -> Javier Lucio Aldea Medrano | D2963: Aubasa | E2963: 92818 | F2963: 1 | G2963: 02M | H2963: 67339635 | J2963: 2395.04 | K2963: 0
A2964: 46263 | B2964: AI325CC | C2964: {=INDEX(CHOFERES!$1:$1001,MATCH(A2964,CHOFERES!$A:$A,0),MATCH(B2964,CHOFERES!$1:$1,0))} -> Damian Oscar Gordillo Flash & Go | D2964: Aubasa | E2964: 150904 | F2964: 1 | G2964: 01M | H2964: 61024046 | J2964: 2395.04 | K2964: 0
... A3766: 46265 | B3766: AI288DB | C3766: {=INDEX(CHOFERES!$1:$1001,MATCH(A3766,CHOFERES!$A:$A,0),MATCH(B3766,CHOFERES!$1:$1,0))} -> Nahuel Tobias Campos Flash & Go | D3766: Aubasa | E3766: 155233 | F3766: 5 | G3766: 53M | H3766: 61024077 | J3766: 1676.53 | K3766: 0
A3767: 46250 | B3767: AH252SM | C3767: {=INDEX(CHOFERES!$1:$1001,MATCH(A3767,CHOFERES!$A:$A,0),MATCH(B3767,CHOFERES!$1:$1,0))} -> Amilcar Alejandro Tellechea | D3767: Ceamse | E3767: 0.84947917 | F3767: 0002 - 2-CABECERA OESTE | G3767: 35 | I3767: 2 | J3767: 3000
A3768: 46255 | B3768: AH252SM | C3768: {=INDEX(CHOFERES!$1:$1001,MATCH(A3768,CHOFERES!$A:$A,0),MATCH(B3768,CHOFERES!$1:$1,0))} -> Amilcar Alejandro Tellechea | D3768: Ceamse | E3768: 0.67861111 | F3768: 0012 - 12-PUENTE COPAN | G3768: 12 | I3768: 2 | J3768: 3000
A3769: 46260 | B3769: AH252SM | C3769: {=INDEX(CHOFERES!$1:$1001,MATCH(A3769,CHOFERES!$A:$A,0),MATCH(B3769,CHOFERES!$1:$1,0))} -> Amilcar Alejandro Tellechea | D3769: Ceamse | E3769: 0.32237269 | F3769: 0002 - 2-CABECERA OESTE | G3769: 34 | I3769: 2 | J3769: 3000
A3770: 46263 | B3770: AH252SM | C3770: {=INDEX(CHOFERES!$1:$1001,MATCH(A3770,CHOFERES!$A:$A,0),MATCH(B3770,CHOFERES!$1:$1,0))} -> Amilcar Alejandro Tellechea | D3770: Ceamse | E3770: 0.64944444 | F3770: 0002 - 2-CABECERA OESTE | G3770: 35 | I3770: 2 | J3770: 3000
A3771: 46264 | B3771: AH252SM | C3771: {=INDEX(CHOFERES!$1:$1001,MATCH(A3771,CHOFERES!$A:$A,0),MATCH(B3771,CHOFERES!$1:$1,0))} -> Amilcar Alejandro Tellechea | D3771: Ceamse | E3771: 0.80834491 | F3771: 0002 - 2-CABECERA OESTE | G3771: 36 | I3771: 2 | J3771: 3000
A3772: 46264 | B3772: AH252SM | C3772: {=INDEX(CHOFERES!$1:$1001,MATCH(A3772,CHOFERES!$A:$A,0),MATCH(B3772,CHOFERES!$1:$1,0))} -> Amilcar Alejandro Tellechea | D3772: Ceamse | E3772: 0.85171296 | F3772: 0008 - 8-RUTA 201 ASCENDENTE | G3772: 19 | I3772: 2 | J3772: 3000
A3773: 46264 | B3773: AH252SM | C3773: {=INDEX(CHOFERES!$1:$1001,MATCH(A3773,CHOFERES!$A:$A,0),MATCH(B3773,CHOFERES!$1:$1,0))} -> Amilcar Alejandro Tellechea | D3773: Ceamse | E3773: 0.88516204 | F3773: 0002 - 2-CABECERA OESTE | G3773: 35 | I3773: 2 | J3773: 3000
A3774: 46252 | B3774: AH252TX | C3774: {=INDEX(CHOFERES!$1:$1001,MATCH(A3774,CHOFERES!$A:$A,0),MATCH(B3774,CHOFERES!$1:$1,0))} -> Ernesto PoqueChoque Muruchi | D3774: Ceamse | E3774: 0.77680556 | F3774: 0009 - 9-RUTA 201 DESCENDENTE | G3774: 20 | I3774: 2 | J3774: 3000
A3775: 46256 | B3775: AH252ST | C3775: {=INDEX(CHOFERES!$1:$1001,MATCH(A3775,CHOFERES!$A:$A,0),MATCH(B3775,CHOFERES!$1:$1,0))} -> Lucas Gabriel Lema | D3775: Ceamse | E3775: 0.67664352 | F3775: 0002 - 2-CABECERA OESTE | G3775: 26 | I3775: 2 | J3775: 3000
A3776: 46256 | B3776: AH252ST | C3776: {=INDEX(CHOFERES!$1:$1001,MATCH(A3776,CHOFERES!$A:$A,0),MATCH(B3776,CHOFERES!$1:$1,0))} -> Lucas Gabriel Lema | D3776: Ceamse | E3776: 0.74513889 | F3776: 0001 - 1-CABECERA NORTE | G3776: 9 | I3776: 2 | J3776: 3000
A3777: 46259 | B3777: AH252ST | C3777: {=INDEX(CHOFERES!$1:$1001,MATCH(A3777,CHOFERES!$A:$A,0),MATCH(B3777,CHOFERES!$1:$1,0))} -> Lucas Gabriel Lema | D3777: Ceamse | E3777: 0.77377315 | F3777: 0002 - 2-CABECERA OESTE | G3777: 29 | I3777: 2 | J3777: 3000
A3778: 46263 | B3778: AH252ST | C3778: {=INDEX(CHOFERES!$1:$1001,MATCH(A3778,CHOFERES!$A:$A,0),MATCH(B3778,CHOFERES!$1:$1,0))} -> Lucas Gabriel Lema | D3778: Ceamse | E3778: 0.65959491 | F3778: 0002 - 2-CABECERA OESTE | G3778: 27 | I3778: 2 | J3778: 3000
... A3956: 46265 | B3956: AH087VS | C3956: {=INDEX(CHOFERES!$1:$1001,MATCH(A3956,CHOFERES!$A:$A,0),MATCH(B3956,CHOFERES!$1:$1,0))} -> Nestor Gustavo Gimenez | D3956: Ceamse | E3956: 0.52996528 | F3956: 0002 - 2-CABECERA OESTE | G3956: 29 | I3956: 2 | J3956: 3000

Sheet Hoja3
B1: FECHA | C1: PATENTE | D1: CHOFER | E1: AUTOPISTA | F1: HORA | G1: ESTACION
B2: 46243 | C2: AI210DO | D2: 0 | E2: Autopistas Urbanas | F2: 0.17428241 | G2: KDT
B3: 46243 | C3: AI210DO | D3: 0 | E3: Autopistas Urbanas | F3: 0.31136574 | G3: KDT
B4: 46247 | C4: AI210DO | D4: 0 | E4: Autopistas Urbanas | F4: 0.77512731 | G4: KDT
B5: 46246 | C5: AI210DO | D5: 0 | E5: Autopistas Urbanas | F5: 0.75335648 | G5: KDT
B6: 46247 | C6: AI210DO | D6: 0 | E6: Autopistas Urbanas | F6: 0.69563657 | G6: KDT
B7: 46241 | C7: AI210DO | D7: 0 | E7: Autopistas Urbanas | F7: 0.69572917 | G7: VAR
B8: 46241 | C8: AI210DO | D8: 0 | E8: Autopistas Urbanas | F8: 0.76384259 | G8: KDT
B9: 46244 | C9: AI210DO | D9: 0 | E9: Autopistas Urbanas | F9: 0.76635417 | G9: KDT
B10: 46248 | C10: AI210DO | D10: 0 | E10: Autopistas Urbanas | F10: 0.76024306 | G10: KDT
B11: 46244 | C11: AI210DO | D11: 0 | E11: Autopistas Urbanas | F11: 0.46708333 | G11: REM
B12: 46246 | C12: AI210DO | D12: 0 | E12: Autopistas Urbanas | F12: 0.62884259 | G12: VAR
B13: 46254 | C13: AI210DO | D13: 0 | E13: Autopistas Urbanas | F13: 0.77408565 | G13: KDT
... B38: 46248 | C38: AI210DO | D38: 0 | E38: Acceso Norte | F38: 0.45741898 | G38: BELGRANO DESCENDENTE
B39: 46246 | C39: AI210DO | D39: 0 | E39: Aubasa | F39: 154825 | G39: 1
B40: 46240 | C40: AH205QU | D40: 0 | E40: Aubasa | F40: 120604 | G40: 1
B41: 46241 | C41: AI210DO | D41: 0 | E41: Aubasa | F41: 0.7877662 | G41: 1
B42: 46240 | C42: AI210DO | D42: 0 | E42: Aubasa | F42: 0.77021991 | G42: 1
B43: 46246 | C43: AI210DO | D43: 0 | E43: Aubasa | F43: 151736 | G43: 1
B44: 46247 | C44: AI210DO | D44: 0 | E44: Aubasa | F44: 191647 | G44: 1
B45: 46246 | C45: AI210DO | D45: 0 | E45: Aubasa | F45: 1638 | G45: 1
B46: 46244 | C46: AI210DO | D46: 0 | E46: Aubasa | F46: 112700 | G46: 1
B47: 46246 | C47: AI210DO | D47: 0 | E47: Aubasa | F47: 184515 | G47: 1
B48: 46248 | C48: AI210DO | D48: 0 | E48: Aubasa | F48: 132900 | G48: 1
B49: 46243 | C49: AI210DO | D49: 0 | E49: Aubasa | F49: 73908 | G49: 1
B50: 46244 | C50: AI210DO | D50: 0 | E50: Aubasa | F50: 192355 | G50: 1
... B57: 46244 | C57: AI210DO | D57: 0 | E57: Aubasa | F57: 113411 | G57: 5
B58: 46241 | C58: AH205QU | D58: 0 | E58: CORREDORES VIALES SA | F58: 0.61320602 | G58: ZARATE - RUTA 9 KM. 95
B59: 46241 | C59: AH205QU | D59: 0 | E59: CORREDORES VIALES SA | F59: 0.70002315 | G59: LAGOS - RUTA 9 KM. 272
B60: 46241 | C60: AH205QU | D60: 0 | E60: CORREDORES VIALES SA | F60: 0.73341435 | G60: CARCARAÑA - AUTOVIA ROSARIO - CORDOBA KM. 356
B61: 46241 | C61: AH205QU | D61: 0 | E61: CORREDORES VIALES SA | F61: 0.85106481 | G61: JAMES CRAIK - AUTOVIA ROSARIO - CORDOBA KM. 595
B62: 46245 | C62: AH252TD | D62: 0 | E62: RUTAS SUR ATLANTICO S.A. | F62: 0.41679398 | G62: AGÜERO - AU.RICCHIERI KM 15,80
B63: 46233 | C63: AH252TQ | D63: 0 | E63: CORREDORES VIALES SA | F63: 0.5762963 | G63: V. TUERTO (RN8) - RUTA 8 KM 381
B64: 46241 | C64: AI210DO | D64: 0 | E64: RUTAS SUR ATLANTICO S.A. | F64: 0.65925926 | G64: AGÜERO - AU.RICCHIERI KM 15,80
B65: 46241 | C65: AI210DO | D65: 0 | E65: RUTAS SUR ATLANTICO S.A. | F65: 0.68997685 | G65: AGÜERO - AU.RICCHIERI KM 15,80
B66: 46243 | C66: AI210DO | D66: 0 | E66: RUTAS SUR ATLANTICO S.A. | F66: 0.25987269 | G66: AGÜERO - AU.RICCHIERI KM 15,80
B67: 46243 | C67: AI210DO | D67: 0 | E67: RUTAS SUR ATLANTICO S.A. | F67: 0.27825231 | G67: AGÜERO - AU.RICCHIERI KM 15,80
B68: 46245 | C68: AI210DO | D68: 0 | E68: RUTAS SUR ATLANTICO S.A. | F68: 0.95337963 | G68: AGÜERO - AU.RICCHIERI KM 15,80
B69: 46246 | C69: AI210DO | D69: 0 | E69: RUTAS SUR ATLANTICO S.A. | F69: 0.58763889 | G69: AGÜERO - AU.RICCHIERI KM 15,80
... B73: 46245 | C73: AH191LP | D73: 0 | E73: Ceamse | F73: 0.0011226852 | G73: 0005 - 5-DEBENEDETTI

Sheet Hoja2
D1: =SUM(D2:D10) -> 9135856.6
D2: 3004291.8 | E2: urbanas
D3: 2153589.3 | E3: urbanas
D4: 16800 | E4: Rsio-Sta fe
D5: 4707.32 | E5: Mercosur
D6: 811825.82 | E6: del Oeste
D7: 703761.4 | E7: Norte
D8: 2055899 | E8: Aubasa
D9: 471000 | E9: Ceamse
D10: -86018.07 | E10: bonif

Sheet Hoja1
F2: 14991900 | G2: 46119
F3: 3650473.2 | G3: 46132
F4: 14658659 | G4: 46146
F5: =SUM(F2:F4) -> 33301033

Sheet CHOFERES
B1: AH087VQ | C1: AH087VS | D1: AH087VT | E1: AH087VU | F1: AH087VV | G1: AH087VW | H1: AH087VX | I1: AH087VY | J1: AH087VZ | K1: AH120EA | L1: AH191LH | M1: AH191LI | N1: AH191LJ | O1: AH191LK | P1: AH191LL | Q1: AH191LM | R1: AH191LN | S1: AH191LO | T1: AH191LP | U1: AH191LQ | V1: AH191LR | W1: AH191LS | X1: AH191LT | Y1: AH191LU | Z1: AH191LV | AA1: AH191LW | AB1: AH191LX | AC1: AH191LY | AD1: AH191LZ | AE1: AH205QB | AF1: AH205QC | AG1: AH205QD | AH1: AH205QE | AI1: AH205QF | AJ1: AH205QG | AK1: AH205QH | AL1: AH205QI | AM1: AH205QJ | AN1: AH205QK | AO1: AH205QL | AP1: AH205QN | AQ1: AH205QM | AR1: AH205QO | AS1: AH205QP | AT1: AH205QQ | AU1: AH205QR | AV1: AH205QS | AW1: AH205QT | AX1: AH205QU | AY1: AH205QV | AZ1: AH252SH | BA1: AH252SI | BB1: AH252SK | BC1: AH252SL | BD1: AH252SM | BE1: AH252SN | BF1: AH252SO | BG1: AH252SP | BH1: AH252SQ | BI1: AH252SR | BJ1: AH252SS | BK1: AH252ST | BL1: AH252SU | BM1: AH252SV | BN1: AH252SW | BO1: AH252SX | BP1: AH252SY | BQ1: AH252SZ | BR1: AH252TA | BS1: AH252TB | BT1: AH252TC | BU1: AH252TD | BV1: AH252TE | BW1: AH252TF | BX1: AH252TG | BY1: AH252TH | BZ1: AH252TI | CA1: AH252TJ | CB1: AH252TK | CC1: AH252TL | CD1: AH252TM | CE1: AH252TN | CF1: AH252TO | CG1: AH252TP | CH1: AH252TQ | CI1: AH252TR | CJ1: AH252TS | CK1: AH252TT | CL1: AH252TU | CM1: AH252TV | CN1: AH252TW | CO1: AH252TX | CP1: AH252TY | CQ1: AH252TZ | CR1: AH276CA | CS1: AH276CB | CT1: AH276CC | CU1: AH276CD | CV1: AH276CE | CW1: AH276CF | CX1: AH387KY | CY1: AH387KZ | CZ1: AH387LA | DA1: AH387LB | DB1: AH387LC | DC1: AH387LD | DD1: AH387LE | DE1: AH387LF | DF1: AH387LG | DG1: AH387LH | DH1: AH387LI | DI1: AH387LJ | DJ1: AH387LK | DK1: AH387LL | DL1: AH387LM | DM1: AH448TP | DN1: AH448TQ | DO1: AH448TR | DP1: AH448TS | DQ1: AH448TT | DR1: AH448TX | DS1: AH448TY | DT1: AH448TZ | DU1: AH448UA | DV1: AH448UC | DW1: AH448UG | DX1: AH448UH | DY1: AH448UI | DZ1: AH448UJ | EA1: AH448UK | EB1: AH502KB | EC1: AH502KC | ED1: AH502KD | EE1: AH502KF | EF1: AH502KG | EG1: AH645XB | EH1: AH645XC | EI1: AH645XD | EJ1: AH645XE | EK1: AH688UW | EL1: AH991GB | EM1: AI085VR | EN1: AI199YR | EO1: AI210DK | EP1: AI210DL | EQ1: AI210DO | ER1: AI210DP | ES1: AI210DQ | ET1: AI210DR | EU1: AI210DS | EV1: AI274QF | EW1: AI274QG | EX1: AI274QH | EY1: AI274QI | EZ1: AI274QJ | FA1: AI274QK | FB1: AI274QL | FC1: AI274QP | FD1: AI274QT | FE1: AI288CR | FF1: AI288CS | FG1: AI288CT | FH1: AI288CU | FI1: AI288CV | FJ1: AI288CW | FK1: AI288CX | FL1: AI288CY | FM1: AI288CZ | FN1: AI288DA | FO1: AI288DB | FP1: AI288DC | FQ1: AI288DD | FR1: AI288DE | FS1: AI288DF | FT1: AI288DU | FU1: AI288DV | FV1: AI288DX | FW1: AI288DY | FX1: AI288DZ | FY1: AI325BA | FZ1: AI325BB | GA1: AI325BC | GB1: AI325BD | GC1: AI325BE | GD1: AI325BF | GE1: AI325BG | GF1: AI325BH | GG1: AI325BI | GH1: AI325BJ | GI1: AI325BK | GJ1: AI325BL | GK1: AI325BM | GL1: AI325BO | GM1: AI325BQ | GN1: AI325BR | GO1: AI325BS | GP1: AI325BT | GQ1: AI325BU | GR1: AI325BV | GS1: AI325BW | GT1: AI325BX | GU1: AI325BY | GV1: AI325BZ | GW1: AI325CA | GX1: AI325CB | GY1: AI325CC | GZ1: AI325CD | HA1: AI325CE
A2: 45702 | D2: Yeferson Angel Gay
A3: 45705 | D3: Yeferson Angel Gay | H3: Angel Ricardo Novoa | I3: Carlos Gustavo Zabala | K3: Ezequiel Alberto Porciel
A4: 45706 | D4: Yeferson Angel Gay | F4: Lucas Fabrizio Acosta | H4: Angel Ricardo Novoa | I4: Carlos Gustavo Zabala | K4: Ezequiel Alberto Porciel
A5: 45707 | C5: Alexis Jose Brito Vizcaino | D5: Yeferson Angel Gay | E5: Cristian Joel Moreno | F5: Lucas Fabrizio Acosta | H5: Angel Ricardo Novoa | I5: Carlos Gustavo Zabala | K5: Ezequiel Alberto Porciel | DI5: Alexis Jose Brito Vizcaino
A6: 45708 | B6: Juan Carlos Lezcano | C6: Alexis Jose Brito Vizcaino | D6: Yeferson Angel Gay | E6: Cristian Joel Moreno | F6: Lucas Fabrizio Acosta | G6: Gaston Maximiliano Villalba | H6: Angel Ricardo Novoa | I6: Carlos Gustavo Zabala | J6: Vanina Leonor Lezcano | K6: Ezequiel Alberto Porciel | DI6: Alexis Jose Brito Vizcaino
A7: 45709 | B7: Juan Carlos Lezcano | C7: Alexis Jose Brito Vizcaino | D7: Yeferson Angel Gay | E7: Cristian Joel Moreno | F7: Lucas Fabrizio Acosta | G7: Gaston Maximiliano Villalba | H7: William Enrique Suarez Williams | I7: Carlos Gustavo Zabala | J7: Vanina Leonor Lezcano | K7: Ezequiel Alberto Porciel | DI7: Alexis Jose Brito Vizcaino
A8: 45710 | B8: Juan Carlos Lezcano | C8: Alexis Jose Brito Vizcaino | D8: Yeferson Angel Gay | E8: Cristian Joel Moreno | F8: Lucas Fabrizio Acosta | G8: Gaston Maximiliano Villalba | H8: William Enrique Suarez Williams | I8: Carlos Gustavo Zabala | J8: Vanina Leonor Lezcano | K8: Ezequiel Alberto Porciel | DI8: Alexis Jose Brito Vizcaino
A9: 45711 | B9: Juan Carlos Lezcano | C9: Alexis Jose Brito Vizcaino | D9: Yeferson Angel Gay | E9: Cristian Joel Moreno | F9: Lucas Fabrizio Acosta | G9: Gaston Maximiliano Villalba | H9: William Enrique Suarez Williams | I9: Carlos Gustavo Zabala | J9: Vanina Leonor Lezcano | K9: Ezequiel Alberto Porciel | DI9: Alexis Jose Brito Vizcaino
A10: 45712 | B10: Juan Carlos Lezcano | C10: Alexis Jose Brito Vizcaino | D10: Yeferson Angel Gay | E10: Cristian Joel Moreno | F10: Lucas Fabrizio Acosta | G10: Gaston Maximiliano Villalba | H10: William Enrique Suarez Williams | I10: Carlos Gustavo Zabala | J10: Vanina Leonor Lezcano | K10: Ezequiel Alberto Porciel | DI10: Alexis Jose Brito Vizcaino
A11: 45713 | B11: Juan Carlos Lezcano | C11: Alexis Jose Brito Vizcaino | D11: Yeferson Angel Gay | E11: Cristian Joel Moreno | F11: Lucas Fabrizio Acosta | G11: Gaston Maximiliano Villalba | H11: William Enrique Suarez Williams | I11: Carlos Gustavo Zabala | J11: Vanina Leonor Lezcano | K11: Ezequiel Alberto Porciel | DI11: Alexis Jose Brito Vizcaino
A12: 45714 | B12: Juan Carlos Lezcano | C12: Alexis Jose Brito Vizcaino | D12: Yeferson Angel Gay | E12: Cristian Joel Moreno | F12: Lucas Fabrizio Acosta | G12: Gaston Maximiliano Villalba | H12: William Enrique Suarez Williams | I12: Carlos Gustavo Zabala | J12: Vanina Leonor Lezcano | K12: Ezequiel Alberto Porciel | DI12: Alexis Jose Brito Vizcaino
A13: 45715 | B13: Juan Carlos Lezcano | C13: Alexis Jose Brito Vizcaino | D13: Yeferson Angel Gay | E13: Cristian Joel Moreno | F13: Lucas Fabrizio Acosta | G13: Diego Jose Garcia Garcia | H13: William Enrique Suarez Williams | I13: Carlos Gustavo Zabala | J13: Vanina Leonor Lezcano | K13: Ezequiel Alberto Porciel | DI13: Alexis Jose Brito Vizcaino
A14: 45716 | B14: Juan Carlos Lezcano | C14: Alexis Jose Brito Vizcaino | D14: Yeferson Angel Gay | E14: Cristian Joel Moreno | F14: Lucas Fabrizio Acosta | G14: Diego Jose Garcia Garcia | H14: William Enrique Suarez Williams | I14: Carlos Gustavo Zabala | J14: Vanina Leonor Lezcano | K14: Carlos Elias Guevara Garanton | DI14: Alexis Jose Brito Vizcaino
A15: 45717 | B15: Juan Carlos Lezcano | C15: Alexis Jose Brito Vizcaino | D15: Yeferson Angel Gay | E15: Cristian Joel Moreno | F15: Lucas Fabrizio Acosta | G15: Diego Jose Garcia Garcia | H15: William Enrique Suarez Williams | I15: Carlos Gustavo Zabala | J15: Vanina Leonor Lezcano | K15: Carlos Elias Guevara Garanton | DI15: Alexis Jose Brito Vizcaino
A16: 45718 | B16: Juan Carlos Lezcano | C16: Alexis Jose Brito Vizcaino | D16: Yeferson Angel Gay | E16: Cristian Joel Moreno | F16: Lucas Fabrizio Acosta | G16: Diego Jose Garcia Garcia | H16: William Enrique Suarez Williams | I16: Carlos Gustavo Zabala | J16: Vanina Leonor Lezcano | K16: Carlos Elias Guevara Garanton | DI16: Alexis Jose Brito Vizcaino
A17: 45719 | B17: Juan Carlos Lezcano | C17: Alexis Jose Brito Vizcaino | D17: Yeferson Angel Gay | E17: Cristian Joel Moreno | F17: Lucas Fabrizio Acosta | G17: Diego Jose Garcia Garcia | H17: William Enrique Suarez Williams | I17: Carlos Gustavo Zabala | J17: Vanina Leonor Lezcano | K17: Carlos Elias Guevara Garanton | DI17: Alexis Jose Brito Vizcaino
... A21: 45723 | B21: Juan Carlos Lezcano | C21: Alexis Jose Brito Vizcaino | D21: Yeferson Angel Gay | E21: Cristian Joel Moreno | F21: Lucas Fabrizio Acosta | G21: Diego Jose Garcia Garcia | H21: William Enrique Suarez Williams | I21: Carlos Gustavo Zabala | J21: Vanina Leonor Lezcano | K21: Carlos Elias Guevara Garanton | DI21: Alexis Jose Brito Vizcaino
A22: 45724 | B22: Juan Carlos Lezcano | C22: Alexis Jose Brito Vizcaino | D22: Yeferson Angel Gay | E22: Cristian Joel Moreno | F22: Lucas Fabrizio Acosta | G22: Diego Jose Garcia Garcia | H22: William Enrique Suarez Williams | I22: Carlos Gustavo Zabala | J22: Vanina Leonor Lezcano | K22: Carlos Elias Guevara Garanton | P22: Daniel Oscar Aguirre | AA22: Miguel Antonio Toledo Perez | AM22: Flavio Ariel Romero | AT22: Esteban Del Barco | DI22: Alexis Jose Brito Vizcaino
A23: 45725 | B23: Juan Carlos Lezcano | C23: Alexis Jose Brito Vizcaino | D23: Yeferson Angel Gay | E23: Cristian Joel Moreno | F23: Lucas Fabrizio Acosta | G23: Diego Jose Garcia Garcia | H23: William Enrique Suarez Williams | I23: Carlos Gustavo Zabala | J23: Vanina Leonor Lezcano | K23: Carlos Elias Guevara Garanton | P23: Daniel Oscar Aguirre | AA23: Miguel Antonio Toledo Perez | AM23: Flavio Ariel Romero | AT23: Esteban Del Barco | DI23: Alexis Jose Brito Vizcaino
A24: 45726 | B24: Juan Carlos Lezcano | C24: Alexis Jose Brito Vizcaino | D24: Yeferson Angel Gay | E24: Cristian Joel Moreno | F24: Lucas Fabrizio Acosta | G24: Diego Jose Garcia Garcia | H24: William Enrique Suarez Williams | I24: Carlos Gustavo Zabala | J24: Vanina Leonor Lezcano | K24: Carlos Elias Guevara Garanton | P24: Daniel Oscar Aguirre | AA24: Miguel Antonio Toledo Perez | AM24: Flavio Ariel Romero | AT24: Esteban Del Barco | DI24: Alexis Jose Brito Vizcaino
A25: 45727 | B25: Juan Carlos Lezcano | C25: Alexis Jose Brito Vizcaino | D25: Yeferson Angel Gay | E25: Cristian Joel Moreno | F25: Lucas Fabrizio Acosta | G25: Diego Jose Garcia Garcia | H25: William Enrique Suarez Williams | I25: Carlos Gustavo Zabala | J25: Vanina Leonor Lezcano | K25: Carlos Elias Guevara Garanton | P25: Daniel Oscar Aguirre | AA25: Miguel Antonio Toledo Perez | AM25: Flavio Ariel Romero | AT25: Esteban Del Barco | DI25: Alexis Jose Brito Vizcaino
A26: 45728 | B26: Juan Carlos Lezcano | C26: Alexis Jose Brito Vizcaino | D26: Yeferson Angel Gay | E26: Cristian Joel Moreno | F26: Lucas Fabrizio Acosta | G26: Diego Jose Garcia Garcia | H26: William Enrique Suarez Williams | I26: Carlos Gustavo Zabala | J26: Vanina Leonor Lezcano | K26: Carlos Elias Guevara Garanton | P26: Daniel Oscar Aguirre | X26: Diego Marcelo Diaz | AA26: Miguel Antonio Toledo Perez | AM26: Flavio Ariel Romero | AT26: Esteban Del Barco | AW26: Lautaro Ezequiel Scarpitti | DI26: Alexis Jose Brito Vizcaino
A27: 45729 | B27: Juan Carlos Lezcano | C27: Alexis Jose Brito Vizcaino | D27: Yeferson Angel Gay | E27: Cristian Joel Moreno | F27: Lucas Fabrizio Acosta | G27: Diego Jose Garcia Garcia | H27: William Enrique Suarez Williams | J27: Vanina Leonor Lezcano | K27: Carlos Elias Guevara Garanton | P27: Daniel Oscar Aguirre | X27: Diego Marcelo Diaz | AA27: Miguel Antonio Toledo Perez | AM27: Flavio Ariel Romero | AT27: Esteban Del Barco | AW27: Lautaro Ezequiel Scarpitti | DI27: Alexis Jose Brito Vizcaino
A28: 45730 | B28: Carlos Gustavo Zabala | C28: Alexis Jose Brito Vizcaino | D28: Yeferson Angel Gay | E28: Cristian Joel Moreno | F28: Lucas Fabrizio Acosta | G28: Diego Jose Garcia Garcia | H28: William Enrique Suarez Williams | J28: Vanina Leonor Lezcano | K28: Carlos Elias Guevara Garanton | P28: Daniel Oscar Aguirre | X28: Diego Marcelo Diaz | AA28: Miguel Antonio Toledo Perez | AM28: Flavio Ariel Romero | AT28: Esteban Del Barco | AW28: Lautaro Ezequiel Scarpitti | DI28: Alexis Jose Brito Vizcaino
A29: 45731 | B29: Carlos Gustavo Zabala | C29: Alexis Jose Brito Vizcaino | D29: Yeferson Angel Gay | E29: Cristian Joel Moreno | F29: Lucas Fabrizio Acosta | G29: Diego Jose Garcia Garcia | H29: William Enrique Suarez Williams | J29: Vanina Leonor Lezcano | K29: Carlos Elias Guevara Garanton | P29: Daniel Oscar Aguirre | S29: Sebastian Leandro Toconas | X29: Diego Marcelo Diaz | AA29: Miguel Antonio Toledo Perez | AM29: Flavio Ariel Romero | AT29: Esteban Del Barco | AW29: Lautaro Ezequiel Scarpitti | DI29: Alexis Jose Brito Vizcaino
A30: 45732 | B30: Carlos Gustavo Zabala | C30: Alexis Jose Brito Vizcaino | D30: Yeferson Angel Gay | E30: Cristian Joel Moreno | F30: Lucas Fabrizio Acosta | G30: Diego Jose Garcia Garcia | H30: William Enrique Suarez Williams | J30: Vanina Leonor Lezcano | K30: Carlos Elias Guevara Garanton | P30: Daniel Oscar Aguirre | S30: Sebastian Leandro Toconas | X30: Diego Marcelo Diaz | AA30: Miguel Antonio Toledo Perez | AM30: Flavio Ariel Romero | AT30: Esteban Del Barco | AW30: Lautaro Ezequiel Scarpitti | DI30: Alexis Jose Brito Vizcaino
A31: 45733 | B31: Carlos Gustavo Zabala | C31: Alexis Jose Brito Vizcaino | D31: Yeferson Angel Gay | E31: Cristian Joel Moreno | F31: Lucas Fabrizio Acosta | G31: Diego Jose Garcia Garcia | H31: William Enrique Suarez Williams | J31: Vanina Leonor Lezcano | K31: Carlos Elias Guevara Garanton | M31: Carlos Villanueva | P31: Daniel Oscar Aguirre | S31: Sebastian Leandro Toconas | X31: Diego Marcelo Diaz | AA31: Miguel Antonio Toledo Perez | AM31: Flavio Ariel Romero | AP31: Jose Miguel Camacho Fernandez | AT31: Esteban Del Barco | AW31: Lautaro Ezequiel Scarpitti | DI31: Alexis Jose Brito Vizcaino
A32: 45734 | B32: Carlos Gustavo Zabala | C32: Alexis Jose Brito Vizcaino | D32: Yeferson Angel Gay | E32: Cristian Joel Moreno | F32: Lucas Fabrizio Acosta | G32: Diego Jose Garcia Garcia | H32: William Enrique Suarez Williams | J32: Vanina Leonor Lezcano | K32: Carlos Elias Guevara Garanton | M32: Carlos Villanueva | P32: Daniel Oscar Aguirre | S32: Sebastian Leandro Toconas | X32: Diego Marcelo Diaz | AA32: Miguel Antonio Toledo Perez | AM32: Flavio Ariel Romero | AP32: Jose Miguel Camacho Fernandez | AT32: Esteban Del Barco | AW32: Lautaro Ezequiel Scarpitti | DI32: Alexis Jose Brito Vizcaino
A33: 45735 | B33: Carlos Gustavo Zabala | C33: Alexis Jose Brito Vizcaino | D33: Yeferson Angel Gay | E33: Cristian Joel Moreno | F33: Lucas Fabrizio Acosta | G33: Diego Jose Garcia Garcia | H33: William Enrique Suarez Williams | J33: Vanina Leonor Lezcano | K33: Carlos Elias Guevara Garanton | M33: Carlos Villanueva | P33: Daniel Oscar Aguirre | S33: Sebastian Leandro Toconas | X33: Diego Marcelo Diaz | AA33: Miguel Antonio Toledo Perez | AM33: Flavio Ariel Romero | AP33: Jose Miguel Camacho Fernandez | AT33: Esteban Del Barco | AW33: Lautaro Ezequiel Scarpitti | DI33: Alexis Jose Brito Vizcaino
A34: 45736 | B34: Carlos Gustavo Zabala | C34: Alexis Jose Brito Vizcaino | D34: Yeferson Angel Gay | E34: Cristian Joel Moreno | F34: Lucas Fabrizio Acosta | G34: Diego Jose Garcia Garcia | H34: William Enrique Suarez Williams | J34: Vanina Leonor Lezcano | K34: Carlos Elias Guevara Garanton | M34: Carlos Villanueva | P34: Daniel Oscar Aguirre | S34: Sebastian Leandro Toconas | X34: Diego Marcelo Diaz | AA34: Miguel Antonio Toledo Perez | AF34: Sebastian Alexis Lopez | AM34: Flavio Ariel Romero | AP34: Jose Miguel Camacho Fernandez | AT34: Esteban Del Barco | AW34: Lautaro Ezequiel Scarpitti | DI34: Alexis Jose Brito Vizcaino
A35: 45737 | B35: Carlos Gustavo Zabala | C35: Alexis Jose Brito Vizcaino | D35: Yeferson Angel Gay | E35: Cristian Joel Moreno | F35: Lucas Fabrizio Acosta | G35: Diego Jose Garcia Garcia | H35: William Enrique Suarez Williams | J35: Vanina Leonor Lezcano | K35: Carlos Elias Guevara Garanton | M35: Carlos Villanueva | P35: Daniel Oscar Aguirre | R35: Claudio Omar Cobas | S35: Sebastian Leandro Toconas | X35: Diego Marcelo Diaz | Z35: Haylonn Mathias Do Carmo | AA35: Miguel Antonio Toledo Perez | AF35: Sebastian Alexis Lopez | AM35: Flavio Ariel Romero | AP35: Jose Miguel Camacho Fernandez | AT35: Esteban Del Barco | AW35: Lautaro Ezequiel Scarpitti | DI35: Alexis Jose Brito Vizcaino
A36: 45738 | B36: Carlos Gustavo Zabala | C36: Alexis Jose Brito Vizcaino | D36: Yeferson Angel Gay | E36: Cristian Joel Moreno | F36: Lucas Fabrizio Acosta | G36: Diego Jose Garcia Garcia | H36: William Enrique Suarez Williams | J36: Vanina Leonor Lezcano | K36: Carlos Elias Guevara Garanton | M36: Carlos Villanueva | P36: Daniel Oscar Aguirre | R36: Claudio Omar Cobas | S36: Sebastian Leandro Toconas | X36: Diego Marcelo Diaz | Z36: Haylonn Mathias Do Carmo | AA36: Miguel Antonio Toledo Perez | AF36: Sebastian Alexis Lopez | AM36: Flavio Ariel Romero | AP36: Jose Miguel Camacho Fernandez | AT36: Esteban Del Barco | AW36: Lautaro Ezequiel Scarpitti | DI36: Alexis Jose Brito Vizcaino
A37: 45739 | B37: Carlos Gustavo Zabala | C37: Alexis Jose Brito Vizcaino | D37: Yeferson Angel Gay | E37: Cristian Joel Moreno | F37: Lucas Fabrizio Acosta | G37: Diego Jose Garcia Garcia | H37: William Enrique Suarez Williams | J37: Vanina Leonor Lezcano | K37: Carlos Elias Guevara Garanton | M37: Carlos Villanueva | P37: Daniel Oscar Aguirre | R37: Claudio Omar Cobas | S37: Sebastian Leandro Toconas | X37: Diego Marcelo Diaz | Z37: Haylonn Mathias Do Carmo | AA37: Miguel Antonio Toledo Perez | AF37: Sebastian Alexis Lopez | AM37: Flavio Ariel Romero | AP37: Jose Miguel Camacho Fernandez | AT37: Esteban Del Barco | AW37: Lautaro Ezequiel Scarpitti | DI37: Alexis Jose Brito Vizcaino
A38: 45740 | B38: Carlos Gustavo Zabala | C38: Alexis Jose Brito Vizcaino | D38: Yeferson Angel Gay | E38: Cristian Joel Moreno | F38: Lucas Fabrizio Acosta | G38: Diego Jose Garcia Garcia | H38: William Enrique Suarez Williams | J38: Vanina Leonor Lezcano | K38: Carlos Elias Guevara Garanton | M38: Carlos Villanueva | P38: Daniel Oscar Aguirre | R38: Claudio Omar Cobas | S38: Sebastian Leandro Toconas | X38: Diego Marcelo Diaz | Z38: Haylonn Mathias Do Carmo | AA38: Miguel Antonio Toledo Perez | AF38: Sebastian Alexis Lopez | AM38: Flavio Ariel Romero | AP38: Jose Miguel Camacho Fernandez | AT38: Esteban Del Barco | AW38: Lautaro Ezequiel Scarpitti | DI38: Alexis Jose Brito Vizcaino
A39: 45741 | B39: Carlos Gustavo Zabala | C39: Alexis Jose Brito Vizcaino | D39: Yeferson Angel Gay | E39: Cristian Joel Moreno | F39: Lucas Fabrizio Acosta | G39: Diego Jose Garcia Garcia | H39: William Enrique Suarez Williams | J39: Vanina Leonor Lezcano | K39: Carlos Elias Guevara Garanton | M39: Carlos Villanueva | P39: Daniel Oscar Aguirre | R39: Claudio Omar Cobas | S39: Sebastian Leandro Toconas | X39: Diego Marcelo Diaz | Z39: Haylonn Mathias Do Carmo | AA39: Miguel Antonio Toledo Perez | AB39: Lucas Gabriel Galeano Tapia | AF39: Sebastian Alexis Lopez | AM39: Flavio Ariel Romero | AP39: Jose Miguel Camacho Fernandez | AT39: Esteban Del Barco | AW39: Lautaro Ezequiel Scarpitti | DI39: Alexis Jose Brito Vizcaino
A40: 45742 | B40: Carlos Gustavo Zabala | C40: Alexis Jose Brito Vizcaino | D40: Yeferson Angel Gay | E40: Cristian Joel Moreno | F40: Lucas Fabrizio Acosta | G40: Diego Jose Garcia Garcia | H40: William Enrique Suarez Williams | J40: Vanina Leonor Lezcano | K40: Carlos Elias Guevara Garanton | L40: Juan Jose Lugo | M40: Carlos Villanueva | P40: Daniel Oscar Aguirre | R40: Claudio Omar Cobas | S40: Sebastian Leandro Toconas | T40: Jorge Yefherson Martinez Hernandez | X40: Diego Marcelo Diaz | Z40: Haylonn Mathias Do Carmo | AA40: Miguel Antonio Toledo Perez | AB40: Lucas Gabriel Galeano Tapia | AF40: Sebastian Alexis Lopez | AH40: Braian Ezequiel Molina | AM40: Flavio Ariel Romero | AP40: Jose Miguel Camacho Fernandez | AT40: Esteban Del Barco | AW40: Lautaro Ezequiel Scarpitti | DI40: Alexis Jose Brito Vizcaino
A41: 45743 | B41: Carlos Gustavo Zabala | C41: Alexis Jose Brito Vizcaino | D41: Yeferson Angel Gay | E41: Cristian Joel Moreno | F41: Lucas Fabrizio Acosta | G41: Diego Jose Garcia Garcia | H41: William Enrique Suarez Williams | J41: Vanina Leonor Lezcano | K41: Carlos Elias Guevara Garanton | L41: Juan Jose Lugo | M41: Carlos Villanueva | P41: Daniel Oscar Aguirre | R41: Claudio Omar Cobas | S41: Sebastian Leandro Toconas | T41: Jorge Yefherson Martinez Hernandez | X41: Diego Marcelo Diaz | Z41: Haylonn Mathias Do Carmo | AA41: Miguel Antonio Toledo Perez | AB41: Lucas Gabriel Galeano Tapia | AE41: Derek Daniel Almeida Santander | AF41: Sebastian Alexis Lopez | AH41: Braian Ezequiel Molina | AI41: Sergio Daniel Menelli | AJ41: Luciano Ezequiel Cordoba | AK41: qh Carlos Alberto Gonzalez | AM41: Flavio Ariel Romero | AP41: Jose Miguel Camacho Fernandez | AT41: Esteban Del Barco | AW41: Lautaro Ezequiel Scarpitti | AX41: Hector Jose Suarez Uzcategui | DI41: Alexis Jose Brito Vizcaino
A42: 45744 | B42: Carlos Gustavo Zabala | C42: Alexis Jose Brito Vizcaino | D42: Yeferson Angel Gay | E42: Cristian Joel Moreno | F42: Lucas Fabrizio Acosta | G42: Diego Jose Garcia Garcia | H42: William Enrique Suarez Williams | J42: Vanina Leonor Lezcano | K42: Carlos Elias Guevara Garanton | L42: Juan Jose Lugo | M42: Carlos Villanueva | P42: Daniel Oscar Aguirre | Q42: Fabricio Sebastian Castillo | R42: Claudio Omar Cobas | S42: Sebastian Leandro Toconas | T42: Jorge Yefherson Martinez Hernandez | X42: Diego Marcelo Diaz | Z42: Haylonn Mathias Do Carmo | AA42: Miguel Antonio Toledo Perez | AB42: Lucas Gabriel Galeano Tapia | AE42: Derek Daniel Almeida Santander | AF42: Sebastian Alexis Lopez | AH42: Braian Ezequiel Molina | AI42: Sergio Daniel Menelli | AJ42: Luciano Ezequiel Cordoba | AK42: qh Carlos Alberto Gonzalez | AM42: Flavio Ariel Romero | AN42: Dionicio Ruiz Diaz | AP42: Jose Miguel Camacho Fernandez | AR42: Mauro Gabriel Allosa | AT42: Esteban Del Barco | AW42: Lautaro Ezequiel Scarpitti | AX42: Hector Jose Suarez Uzcategui | DI42: Alexis Jose Brito Vizcaino
A43: 45745 | B43: Carlos Gustavo Zabala | C43: Alexis Jose Brito Vizcaino | D43: Yeferson Angel Gay | E43: Cristian Joel Moreno | F43: Lucas Fabrizio Acosta | G43: Diego Jose Garcia Garcia | H43: William Enrique Suarez Williams | J43: Vanina Leonor Lezcano | K43: Carlos Elias Guevara Garanton | L43: Juan Jose Lugo | M43: Carlos Villanueva | P43: Daniel Oscar Aguirre | Q43: Fabricio Sebastian Castillo | R43: Claudio Omar Cobas | S43: Sebastian Leandro Toconas | T43: Jorge Yefherson Martinez Hernandez | X43: Diego Marcelo Diaz | Z43: Haylonn Mathias Do Carmo | AA43: Miguel Antonio Toledo Perez | AB43: Lucas Gabriel Galeano Tapia | AE43: Derek Daniel Almeida Santander | AF43: Sebastian Alexis Lopez | AH43: Braian Ezequiel Molina | AI43: Sergio Daniel Menelli | AJ43: Luciano Ezequiel Cordoba | AK43: qh Carlos Alberto Gonzalez | AM43: Flavio Ariel Romero | AN43: Dionicio Ruiz Diaz | AP43: Jose Miguel Camacho Fernandez | AR43: Mauro Gabriel Allosa | AT43: Esteban Del Barco | AW43: Lautaro Ezequiel Scarpitti | AX43: Hector Jose Suarez Uzcategui | DI43: Alexis Jose Brito Vizcaino
A44: 45746 | B44: Carlos Gustavo Zabala | C44: Alexis Jose Brito Vizcaino | D44: Yeferson Angel Gay | E44: Cristian Joel Moreno | F44: Lucas Fabrizio Acosta | G44: Diego Jose Garcia Garcia | H44: William Enrique Suarez Williams | J44: Vanina Leonor Lezcano | K44: Carlos Elias Guevara Garanton | L44: Juan Jose Lugo | M44: Carlos Villanueva | P44: Daniel Oscar Aguirre | Q44: Fabricio Sebastian Castillo | R44: Claudio Omar Cobas | S44: Sebastian Leandro Toconas | T44: Jorge Yefherson Martinez Hernandez | X44: Diego Marcelo Diaz | Z44: Haylonn Mathias Do Carmo | AA44: Miguel Antonio Toledo Perez | AB44: Lucas Gabriel Galeano Tapia | AE44: Derek Daniel Almeida Santander | AF44: Sebastian Alexis Lopez | AH44: Braian Ezequiel Molina | AI44: Sergio Daniel Menelli | AJ44: Luciano Ezequiel Cordoba | AK44: qh Carlos Alberto Gonzalez | AM44: Flavio Ariel Romero | AN44: Dionicio Ruiz Diaz | AP44: Jose Miguel Camacho Fernandez | AR44: Mauro Gabriel Allosa | AT44: Esteban Del Barco | AW44: Lautaro Ezequiel Scarpitti | AX44: Hector Jose Suarez Uzcategui | DI44: Alexis Jose Brito Vizcaino
A45: 45747 | B45: Carlos Gustavo Zabala | C45: Alexis Jose Brito Vizcaino | D45: Yeferson Angel Gay | E45: Cristian Joel Moreno | F45: Lucas Fabrizio Acosta | G45: Diego Jose Garcia Garcia | H45: William Enrique Suarez Williams | J45: Vanina Leonor Lezcano | K45: Carlos Elias Guevara Garanton | L45: Juan Jose Lugo | M45: Carlos Villanueva | P45: Daniel Oscar Aguirre | Q45: Fabricio Sebastian Castillo | R45: Claudio Omar Cobas | S45: Sebastian Leandro Toconas | T45: Jorge Yefherson Martinez Hernandez | X45: Diego Marcelo Diaz | Z45: Haylonn Mathias Do Carmo | AA45: Miguel Antonio Toledo Perez | AB45: Lucas Gabriel Galeano Tapia | AE45: Derek Daniel Almeida Santander | AF45: Sebastian Alexis Lopez | AG45: Julio David Muñoz Garcia | AH45: Braian Ezequiel Molina | AI45: Sergio Daniel Menelli | AJ45: Luciano Ezequiel Cordoba | AK45: qh Carlos Alberto Gonzalez | AM45: Flavio Ariel Romero | AN45: Dionicio Ruiz Diaz | AP45: Jose Miguel Camacho Fernandez | AR45: Mauro Gabriel Allosa | AT45: Esteban Del Barco | AW45: Lautaro Ezequiel Scarpitti | AX45: Hector Jose Suarez Uzcategui | DI45: Alexis Jose Brito Vizcaino
A46: 45748 | B46: Carlos Gustavo Zabala | C46: Alexis Jose Brito Vizcaino | D46: Yeferson Angel Gay | E46: Cristian Joel Moreno | F46: Lucas Fabrizio Acosta | G46: Diego Jose Garcia Garcia | H46: William Enrique Suarez Williams | J46: Vanina Leonor Lezcano | K46: Carlos Elias Guevara Garanton | L46: Juan Jose Lugo | M46: Carlos Villanueva | P46: Daniel Oscar Aguirre | Q46: Fabricio Sebastian Castillo | R46: Claudio Omar Cobas | S46: Sebastian Leandro Toconas | T46: Jorge Yefherson Martinez Hernandez | X46: Diego Marcelo Diaz | Z46: Haylonn Mathias Do Carmo | AA46: Miguel Antonio Toledo Perez | AB46: Lucas Gabriel Galeano Tapia | AE46: Derek Daniel Almeida Santander | AF46: Sebastian Alexis Lopez | AG46: Julio David Muñoz Garcia | AH46: Braian Ezequiel Molina | AI46: Sergio Daniel Menelli | AJ46: Luciano Ezequiel Cordoba | AK46: qh Carlos Alberto Gonzalez | AM46: Flavio Ariel Romero | AN46: Dionicio Ruiz Diaz | AP46: Jose Miguel Camacho Fernandez | AR46: Mauro Gabriel Allosa | AT46: Esteban Del Barco | AU46: Jackson Jose Sosa Garcia | AW46: Lautaro Ezequiel Scarpitti | AX46: Hector Jose Suarez Uzcategui | DI46: Alexis Jose Brito Vizcaino
A47: 45749 | B47: Carlos Gustavo Zabala | C47: Alexis Jose Brito Vizcaino | D47: Yeferson Angel Gay | E47: Cristian Joel Moreno | F47: Lucas Fabrizio Acosta | G47: Diego Jose Garcia Garcia | H47: William Enrique Suarez Williams | J47: Vanina Leonor Lezcano | K47: Carlos Elias Guevara Garanton | L47: Juan Jose Lugo | M47: Carlos Villanueva | P47: Daniel Oscar Aguirre | Q47: Fabricio Sebastian Castillo | R47: Claudio Omar Cobas | S47: Sebastian Leandro Toconas | T47: Jorge Yefherson Martinez Hernandez | U47: Anibal Rafael Cabrera Paredes | X47: Diego Marcelo Diaz | Z47: Haylonn Mathias Do Carmo | AB47: Lucas Gabriel Galeano Tapia | AE47: Derek Daniel Almeida Santander | AF47: Sebastian Alexis Lopez | AG47: Julio David Muñoz Garcia | AH47: Braian Ezequiel Molina | AI47: Sergio Daniel Menelli | AJ47: Luciano Ezequiel Cordoba | AK47: qh Carlos Alberto Gonzalez | AM47: Flavio Ariel Romero | AN47: Dionicio Ruiz Diaz | AP47: Jose Miguel Camacho Fernandez | AR47: Mauro Gabriel Allosa | AT47: Esteban Del Barco | AU47: Jackson Jose Sosa Garcia | AW47: Lautaro Ezequiel Scarpitti | AX47: Hector Jose Suarez Uzcategui | DI47: Alexis Jose Brito Vizcaino
A48: 45750 | B48: Carlos Gustavo Zabala | C48: Alexis Jose Brito Vizcaino | D48: Yeferson Angel Gay | E48: Cristian Joel Moreno | F48: Lucas Fabrizio Acosta | G48: Diego Jose Garcia Garcia | H48: William Enrique Suarez Williams | J48: Vanina Leonor Lezcano | K48: Carlos Elias Guevara Garanton | L48: Juan Jose Lugo | M48: Carlos Villanueva | P48: Daniel Oscar Aguirre | Q48: Fabricio Sebastian Castillo | R48: Claudio Omar Cobas | S48: Sebastian Leandro Toconas | T48: Jorge Yefherson Martinez Hernandez | U48: Anibal Rafael Cabrera Paredes | X48: Diego Marcelo Diaz | Z48: Haylonn Mathias Do Carmo | AB48: Lucas Gabriel Galeano Tapia | AE48: Derek Daniel Almeida Santander | AF48: Sebastian Alexis Lopez | AG48: Julio David Muñoz Garcia | AH48: Braian Ezequiel Molina | AI48: Sergio Daniel Menelli | AJ48: Luciano Ezequiel Cordoba | AK48: qh Carlos Alberto Gonzalez | AM48: Flavio Ariel Romero | AN48: Dionicio Ruiz Diaz | AO48: Carlos Eduardo Galarza Sanchez | AP48: Jose Miguel Camacho Fernandez | AR48: Mauro Gabriel Allosa | AT48: Esteban Del Barco | AU48: Jackson Jose Sosa Garcia | AW48: Lautaro Ezequiel Scarpitti | AX48: Hector Jose Suarez Uzcategui | DI48: Alexis Jose Brito Vizcaino
A49: 45751 | B49: Carlos Gustavo Zabala | C49: Alexis Jose Brito Vizcaino | D49: Yeferson Angel Gay | E49: Cristian Joel Moreno | F49: Lucas Fabrizio Acosta | G49: Diego Jose Garcia Garcia | H49: William Enrique Suarez Williams | J49: Vanina Leonor Lezcano | K49: Carlos Elias Guevara Garanton | L49: Juan Jose Lugo | M49: Carlos Villanueva | P49: Daniel Oscar Aguirre | Q49: Fabricio Sebastian Castillo | R49: Claudio Omar Cobas | S49: Sebastian Leandro Toconas | T49: Jorge Yefherson Martinez Hernandez | U49: Anibal Rafael Cabrera Paredes | X49: Diego Marcelo Diaz | Z49: Haylonn Mathias Do Carmo | AB49: Lucas Gabriel Galeano Tapia | AE49: Derek Daniel Almeida Santander | AF49: Sebastian Alexis Lopez | AG49: Julio David Muñoz Garcia | AH49: Braian Ezequiel Molina | AI49: Sergio Daniel Menelli | AJ49: Luciano Ezequiel Cordoba | AK49: qh Carlos Alberto Gonzalez | AL49: Victor Emanuel Piris | AN49: Dionicio Ruiz Diaz | AO49: Carlos Eduardo Galarza Sanchez | AP49: Jose Miguel Camacho Fernandez | AR49: Mauro Gabriel Allosa | AT49: Esteban Del Barco | AU49: Jackson Jose Sosa Garcia | AW49: Lautaro Ezequiel Scarpitti | AX49: Hector Jose Suarez Uzcategui | DI49: Alexis Jose Brito Vizcaino
A50: 45752 | B50: Carlos Gustavo Zabala | C50: Alexis Jose Brito Vizcaino | D50: Yeferson Angel Gay | E50: Cristian Joel Moreno | G50: Diego Jose Garcia Garcia | H50: William Enrique Suarez Williams | J50: Vanina Leonor Lezcano | K50: Carlos Elias Guevara Garanton | L50: Juan Jose Lugo | M50: Carlos Villanueva | P50: Daniel Oscar Aguirre | Q50: Fabricio Sebastian Castillo | R50: Claudio Omar Cobas | S50: Sebastian Leandro Toconas | T50: Jorge Yefherson Martinez Hernandez | U50: Anibal Rafael Cabrera Paredes | X50: Diego Marcelo Diaz | Z50: Haylonn Mathias Do Carmo | AB50: Lucas Gabriel Galeano Tapia | AE50: Derek Daniel Almeida Santander | AF50: Sebastian Alexis Lopez | AG50: Julio David Muñoz Garcia | AH50: Braian Ezequiel Molina | AI50: Sergio Daniel Menelli | AJ50: Luciano Ezequiel Cordoba | AK50: qh Carlos Alberto Gonzalez | AL50: Victor Emanuel Piris | AN50: Dionicio Ruiz Diaz | AO50: Carlos Eduardo Galarza Sanchez | AP50: Jose Miguel Camacho Fernandez | AR50: Mauro Gabriel Allosa | AT50: Esteban Del Barco | AU50: Jackson Jose Sosa Garcia | AW50: Lautaro Ezequiel Scarpitti | AX50: Hector Jose Suarez Uzcategui | DI50: Alexis Jose Brito Vizcaino
A51: 45753 | B51: Carlos Gustavo Zabala | C51: Alexis Jose Brito Vizcaino | D51: Yeferson Angel Gay | E51: Cristian Joel Moreno | G51: Diego Jose Garcia Garcia | H51: William Enrique Suarez Williams | J51: Vanina Leonor Lezcano | K51: Carlos Elias Guevara Garanton | L51: Juan Jose Lugo | M51: Carlos Villanueva | P51: Daniel Oscar Aguirre | Q51: Fabricio Sebastian Castillo | R51: Claudio Omar Cobas | S51: Sebastian Leandro Toconas | T51: Jorge Yefherson Martinez Hernandez | U51: Anibal Rafael Cabrera Paredes | X51: Diego Marcelo Diaz | Z51: Haylonn Mathias Do Carmo | AB51: Lucas Gabriel Galeano Tapia | AE51: Derek Daniel Almeida Santander | AF51: Sebastian Alexis Lopez | AG51: Julio David Muñoz Garcia | AH51: Braian Ezequiel Molina | AI51: Sergio Daniel Menelli | AJ51: Luciano Ezequiel Cordoba | AK51: qh Carlos Alberto Gonzalez | AL51: Victor Emanuel Piris | AN51: Dionicio Ruiz Diaz | AO51: Carlos Eduardo Galarza Sanchez | AP51: Jose Miguel Camacho Fernandez | AR51: Mauro Gabriel Allosa | AT51: Esteban Del Barco | AU51: Jackson Jose Sosa Garcia | AW51: Lautaro Ezequiel Scarpitti | AX51: Hector Jose Suarez Uzcategui | DI51: Alexis Jose Brito Vizcaino
A52: 45754 | B52: Carlos Gustavo Zabala | C52: Alexis Jose Brito Vizcaino | D52: Yeferson Angel Gay | E52: Cristian Joel Moreno | G52: Diego Jose Garcia Garcia | H52: William Enrique Suarez Williams | J52: Vanina Leonor Lezcano | K52: Carlos Elias Guevara Garanton | L52: Juan Jose Lugo | M52: Carlos Villanueva | P52: Daniel Oscar Aguirre | Q52: Fabricio Sebastian Castillo | R52: Claudio Omar Cobas | S52: Sebastian Leandro Toconas | T52: Jorge Yefherson Martinez Hernandez | U52: Anibal Rafael Cabrera Paredes | X52: Diego Marcelo Diaz | Z52: Haylonn Mathias Do Carmo | AB52: Lucas Gabriel Galeano Tapia | AE52: Derek Daniel Almeida Santander | AF52: Sebastian Alexis Lopez | AG52: Julio David Muñoz Garcia | AH52: Braian Ezequiel Molina | AI52: Sergio Daniel Menelli | AJ52: Luciano Ezequiel Cordoba | AK52: qh Carlos Alberto Gonzalez | AL52: Victor Emanuel Piris | AM52: Fernando Ariel Lopez | AN52: Dionicio Ruiz Diaz | AO52: Carlos Eduardo Galarza Sanchez | AP52: Jose Miguel Camacho Fernandez | AR52: Mauro Gabriel Allosa | AT52: Esteban Del Barco | AU52: Jackson Jose Sosa Garcia | AW52: Lautaro Ezequiel Scarpitti | AX52: Hector Jose Suarez Uzcategui | DI52: Alexis Jose Brito Vizcaino
A53: 45755 | B53: Carlos Gustavo Zabala | C53: Alexis Jose Brito Vizcaino | D53: Yeferson Angel Gay | E53: Cristian Joel Moreno | F53: Aquilino Romero Velazquez | G53: Diego Jose Garcia Garcia | H53: William Enrique Suarez Williams | J53: Vanina Leonor Lezcano | K53: Carlos Elias Guevara Garanton | L53: Juan Jose Lugo | M53: Carlos Villanueva | P53: Daniel Oscar Aguirre | Q53: Fabricio Sebastian Castillo | R53: Claudio Omar Cobas | S53: Sebastian Leandro Toconas | T53: Jorge Yefherson Martinez Hernandez | U53: Anibal Rafael Cabrera Paredes | X53: Diego Marcelo Diaz | Z53: Haylonn Mathias Do Carmo | AB53: Lucas Gabriel Galeano Tapia | AE53: Derek Daniel Almeida Santander | AF53: Sebastian Alexis Lopez | AG53: Julio David Muñoz Garcia | AH53: Braian Ezequiel Molina | AI53: Sergio Daniel Menelli | AJ53: Luciano Ezequiel Cordoba | AK53: qh Carlos Alberto Gonzalez | AL53: Victor Emanuel Piris | AM53: Fernando Ariel Lopez | AN53: Dionicio Ruiz Diaz | AO53: Carlos Eduardo Galarza Sanchez | AP53: Jose Miguel Camacho Fernandez | AQ53: Ezequiel Adrian Marelli | AR53: Mauro Gabriel Allosa | AS53: Luis Eduardo Anselmi | AT53: Esteban Del Barco | AU53: Jackson Jose Sosa Garcia | AW53: Lautaro Ezequiel Scarpitti | AX53: Hector Jose Suarez Uzcategui | DI53: Alexis Jose Brito Vizcaino
A54: 45756 | B54: Carlos Gustavo Zabala | C54: Alexis Jose Brito Vizcaino | D54: Yeferson Angel Gay | E54: Cristian Joel Moreno | F54: Aquilino Romero Velazquez | G54: Diego Jose Garcia Garcia | H54: William Enrique Suarez Williams | J54: Vanina Leonor Lezcano | K54: Carlos Elias Guevara Garanton | L54: Juan Jose Lugo | M54: Carlos Villanueva | N54: Miguel Antonio Akouri Samra | P54: Daniel Oscar Aguirre | Q54: Fabricio Sebastian Castillo | R54: Claudio Omar Cobas | S54: Sebastian Leandro Toconas | T54: Jorge Yefherson Martinez Hernandez | U54: Anibal Rafael Cabrera Paredes | W54: Selso Sanchez | X54: Diego Marcelo Diaz | Z54: Haylonn Mathias Do Carmo | AB54: Lucas Gabriel Galeano Tapia | AE54: Derek Daniel Almeida Santander | AF54: Sebastian Alexis Lopez | AG54: Julio David Muñoz Garcia | AH54: Braian Ezequiel Molina | AI54: Sergio Daniel Menelli | AJ54: Luciano Ezequiel Cordoba | AK54: qh Carlos Alberto Gonzalez | AL54: Victor Emanuel Piris | AM54: Fernando Ariel Lopez | AN54: Dionicio Ruiz Diaz | AO54: Carlos Eduardo Galarza Sanchez | AP54: Jose Miguel Camacho Fernandez | AQ54: Ezequiel Adrian Marelli | AR54: Mauro Gabriel Allosa | AS54: Luis Eduardo Anselmi | AT54: Esteban Del Barco | AU54: Jackson Jose Sosa Garcia | AW54: Lautaro Ezequiel Scarpitti | AX54: Hector Jose Suarez Uzcategui | AY54: Sergio Gustavo Barrios | DI54: Alexis Jose Brito Vizcaino
A55: 45757 | B55: Carlos Gustavo Zabala | C55: Alexis Jose Brito Vizcaino | D55: Yeferson Angel Gay | E55: Cristian Joel Moreno | F55: Aquilino Romero Velazquez | G55: Diego Jose Garcia Garcia | H55: William Enrique Suarez Williams | J55: Vanina Leonor Lezcano | K55: Carlos Elias Guevara Garanton | L55: Juan Jose Lugo | M55: Carlos Villanueva | N55: Miguel Antonio Akouri Samra | P55: Daniel Oscar Aguirre | Q55: Fabricio Sebastian Castillo | R55: Claudio Omar Cobas | S55: Sebastian Leandro Toconas | T55: Jorge Yefherson Martinez Hernandez | U55: Anibal Rafael Cabrera Paredes | V55: Matias Alejandro Romero | W55: Selso Sanchez | X55: Diego Marcelo Diaz | Z55: Haylonn Mathias Do Carmo | AB55: Lucas Gabriel Galeano Tapia | AE55: Derek Daniel Almeida Santander | AF55: Sebastian Alexis Lopez | AG55: Julio David Muñoz Garcia | AH55: Braian Ezequiel Molina | AI55: Sergio Daniel Menelli | AJ55: Luciano Ezequiel Cordoba | AK55: qh Carlos Alberto Gonzalez | AL55: Victor Emanuel Piris | AM55: Fernando Ariel Lopez | AN55: Dionicio Ruiz Diaz | AO55: Damian Jorge Abalo Prelat | AP55: Jose Miguel Camacho Fernandez | AQ55: Ezequiel Adrian Marelli | AR55: Mauro Gabriel Allosa | AS55: Luis Eduardo Anselmi | AT55: Esteban Del Barco | AU55: Jackson Jose Sosa Garcia | AV55: Rommer Leandro Cordero Hernandez | AW55: Lautaro Ezequiel Scarpitti | AX55: Hector Jose Suarez Uzcategui | AY55: Sergio Gustavo Barrios | DI55: Alexis Jose Brito Vizcaino
A56: 45758 | B56: Carlos Gustavo Zabala | C56: Alexis Jose Brito Vizcaino | D56: Yeferson Angel Gay | E56: Cristian Joel Moreno | F56: Aquilino Romero Velazquez | G56: Diego Jose Garcia Garcia | H56: William Enrique Suarez Williams | J56: Vanina Leonor Lezcano | K56: Carlos Elias Guevara Garanton | L56: Juan Jose Lugo | M56: Carlos Villanueva | N56: Miguel Antonio Akouri Samra | O56: Sergio Luis Prado | P56: Daniel Oscar Aguirre | Q56: Fabricio Sebastian Castillo | R56: Claudio Omar Cobas | S56: Sebastian Leandro Toconas | T56: Jorge Yefherson Martinez Hernandez | U56: Anibal Rafael Cabrera Paredes | V56: Matias Alejandro Romero | W56: Selso Sanchez | X56: Diego Marcelo Diaz | Z56: Haylonn Mathias Do Carmo | AB56: Aquilino Romero Velazquez | AC56: Yovertt Daniel Herrera Zamora | AD56: Abel Mario Martinez | AE56: Derek Daniel Almeida Santander | AF56: Sebastian Alexis Lopez | AG56: Julio David Muñoz Garcia | AH56: Braian Ezequiel Molina | AI56: Sergio Daniel Menelli | AJ56: Luciano Ezequiel Cordoba | AK56: qh Carlos Alberto Gonzalez | AL56: Victor Emanuel Piris | AM56: Fernando Ariel Lopez | AN56: Dionicio Ruiz Diaz | AO56: Damian Jorge Abalo Prelat | AP56: Jose Miguel Camacho Fernandez | AQ56: Ezequiel Adrian Marelli | AR56: Mauro Gabriel Allosa | AS56: Luis Eduardo Anselmi | AT56: Esteban Del Barco | AU56: Jackson Jose Sosa Garcia | AV56: Rommer Leandro Cordero Hernandez | AW56: Lautaro Ezequiel Scarpitti | AX56: Hector Jose Suarez Uzcategui | AY56: Sergio Gustavo Barrios | DI56: Alexis Jose Brito Vizcaino
A57: 45759 | B57: Carlos Gustavo Zabala | C57: Alexis Jose Brito Vizcaino | D57: Yeferson Angel Gay | E57: Cristian Joel Moreno | F57: Angel Daniel Castillo | G57: Diego Jose Garcia Garcia | H57: William Enrique Suarez Williams | J57: Vanina Leonor Lezcano | K57: Carlos Elias Guevara Garanton | L57: Juan Jose Lugo | M57: Carlos Villanueva | N57: Miguel Antonio Akouri Samra | O57: Sergio Luis Prado | P57: Daniel Oscar Aguirre | Q57: Fabricio Sebastian Castillo | R57: Claudio Omar Cobas | S57: Sebastian Leandro Toconas | T57: Jorge Yefherson Martinez Hernandez | U57: Anibal Rafael Cabrera Paredes | V57: Matias Alejandro Romero | W57: Selso Sanchez | X57: Diego Marcelo Diaz | Y57: Daniel Eduardo FuentesTovar | Z57: Haylonn Mathias Do Carmo | AB57: Aquilino Romero Velazquez | AC57: Yovertt Daniel Herrera Zamora | AD57: Abel Mario Martinez | AE57: Derek Daniel Almeida Santander | AF57: Sebastian Alexis Lopez | AG57: Julio David Muñoz Garcia | AH57: Braian Ezequiel Molina | AI57: Sergio Daniel Menelli | AJ57: Luciano Ezequiel Cordoba | AK57: qh Carlos Alberto Gonzalez | AL57: Victor Emanuel Piris | AM57: Fernando Ariel Lopez | AN57: Dionicio Ruiz Diaz | AO57: Damian Jorge Abalo Prelat | AP57: Jose Miguel Camacho Fernandez | AQ57: Ezequiel Adrian Marelli | AR57: Mauro Gabriel Allosa | AS57: Luis Eduardo Anselmi | AT57: Esteban Del Barco | AU57: Jackson Jose Sosa Garcia | AV57: Rommer Leandro Cordero Hernandez | AW57: Lautaro Ezequiel Scarpitti | AX57: Hector Jose Suarez Uzcategui | AY57: Sergio Gustavo Barrios | DI57: Alexis Jose Brito Vizcaino
A58: 45760 | B58: Carlos Gustavo Zabala | C58: Alexis Jose Brito Vizcaino | D58: Yeferson Angel Gay | E58: Cristian Joel Moreno | F58: Angel Daniel Castillo | G58: Diego Jose Garcia Garcia | H58: William Enrique Suarez Williams | J58: Vanina Leonor Lezcano | K58: Carlos Elias Guevara Garanton | M58: Carlos Villanueva | N58: Miguel Antonio Akouri Samra | O58: Sergio Luis Prado | P58: Daniel Oscar Aguirre | Q58: Fabricio Sebastian Castillo | R58: Claudio Omar Cobas | S58: Sebastian Leandro Toconas | T58: Jorge Yefherson Martinez Hernandez | U58: Anibal Rafael Cabrera Paredes | V58: Matias Alejandro Romero | W58: Selso Sanchez | X58: Diego Marcelo Diaz | Y58: Daniel Eduardo FuentesTovar | Z58: Haylonn Mathias Do Carmo | AB58: Aquilino Romero Velazquez | AC58: Yovertt Daniel Herrera Zamora | AD58: Abel Mario Martinez | AE58: Derek Daniel Almeida Santander | AF58: Sebastian Alexis Lopez | AG58: Julio David Muñoz Garcia | AH58: Braian Ezequiel Molina | AI58: Sergio Daniel Menelli | AJ58: Luciano Ezequiel Cordoba | AK58: qh Carlos Alberto Gonzalez | AL58: Victor Emanuel Piris | AM58: Fernando Ariel Lopez | AN58: Dionicio Ruiz Diaz | AO58: Damian Jorge Abalo Prelat | AP58: Jose Miguel Camacho Fernandez | AQ58: Ezequiel Adrian Marelli | AR58: Mauro Gabriel Allosa | AS58: Luis Eduardo Anselmi | AT58: Esteban Del Barco | AU58: Jackson Jose Sosa Garcia | AV58: Rommer Leandro Cordero Hernandez | AW58: Lautaro Ezequiel Scarpitti | AX58: Hector Jose Suarez Uzcategui | AY58: Sergio Gustavo Barrios | DI58: Alexis Jose Brito Vizcaino
A59: 45761 | B59: Carlos Gustavo Zabala | C59: Alexis Jose Brito Vizcaino | D59: Yeferson Angel Gay | E59: Cristian Joel Moreno | F59: Angel Daniel Castillo | G59: Diego Jose Garcia Garcia | H59: William Enrique Suarez Williams | J59: Vanina Leonor Lezcano | K59: Carlos Elias Guevara Garanton | L59: Diego German Rodriguez | M59: Carlos Villanueva | N59: Miguel Antonio Akouri Samra | O59: Sergio Luis Prado | P59: Daniel Oscar Aguirre | Q59: Fabricio Sebastian Castillo | R59: Claudio Omar Cobas | S59: Sebastian Leandro Toconas | T59: Jorge Yefherson Martinez Hernandez | U59: Anibal Rafael Cabrera Paredes | V59: Matias Alejandro Romero | W59: Selso Sanchez | X59: Diego Marcelo Diaz | Y59: Daniel Eduardo FuentesTovar | Z59: Haylonn Mathias Do Carmo | AB59: Aquilino Romero Velazquez | AC59: Yovertt Daniel Herrera Zamora | AD59: Abel Mario Martinez | AE59: Derek Daniel Almeida Santander | AF59: Sebastian Alexis Lopez | AG59: Julio David Muñoz Garcia | AH59: Braian Ezequiel Molina | AI59: Sergio Daniel Menelli | AJ59: Luciano Ezequiel Cordoba | AK59: qh Carlos Alberto Gonzalez | AL59: Victor Emanuel Piris | AM59: Fernando Ariel Lopez | AN59: Dionicio Ruiz Diaz | AO59: Damian Jorge Abalo Prelat | AP59: Jose Miguel Camacho Fernandez | AQ59: Ezequiel Adrian Marelli | AR59: Mauro Gabriel Allosa | AS59: Luis Eduardo Anselmi | AT59: Esteban Del Barco | AU59: Jackson Jose Sosa Garcia | AV59: Rommer Leandro Cordero Hernandez | AW59: Lautaro Ezequiel Scarpitti | AX59: Hector Jose Suarez Uzcategui | AY59: Sergio Gustavo Barrios | DI59: Alexis Jose Brito Vizcaino
A60: 45762 | B60: Carlos Gustavo Zabala | C60: Alexis Jose Brito Vizcaino | D60: Yeferson Angel Gay | E60: Cristian Joel Moreno | F60: Angel Daniel Castillo | G60: Diego Jose Garcia Garcia | H60: William Enrique Suarez Williams | J60: Vanina Leonor Lezcano | K60: Carlos Elias Guevara Garanton | L60: Diego German Rodriguez | M60: Carlos Villanueva | N60: Miguel Antonio Akouri Samra | O60: Sergio Luis Prado | P60: Daniel Oscar Aguirre | Q60: Fabricio Sebastian Castillo | R60: Claudio Omar Cobas | S60: Sebastian Leandro Toconas | T60: Jorge Yefherson Martinez Hernandez | U60: Anibal Rafael Cabrera Paredes | V60: Matias Alejandro Romero | W60: Selso Sanchez | X60: Diego Marcelo Diaz | Y60: Daniel Eduardo FuentesTovar | Z60: Haylonn Mathias Do Carmo | AB60: Aquilino Romero Velazquez | AC60: Yovertt Daniel Herrera Zamora | AD60: Abel Mario Martinez | AE60: Derek Daniel Almeida Santander | AF60: Sebastian Alexis Lopez | AG60: Julio David Muñoz Garcia | AH60: Braian Ezequiel Molina | AI60: Sergio Daniel Menelli | AJ60: Luciano Ezequiel Cordoba | AK60: qh Carlos Alberto Gonzalez | AL60: Victor Emanuel Piris | AM60: Fernando Ariel Lopez | AN60: Dionicio Ruiz Diaz | AO60: Damian Jorge Abalo Prelat | AP60: Jose Miguel Camacho Fernandez | AQ60: Ezequiel Adrian Marelli | AR60: Mauro Gabriel Allosa | AS60: Luis Eduardo Anselmi | AT60: Esteban Del Barco | AU60: Jackson Jose Sosa Garcia | AV60: Rommer Leandro Cordero Hernandez | AW60: Lautaro Ezequiel Scarpitti | AX60: Hector Jose Suarez Uzcategui | AY60: Sergio Gustavo Barrios | DI60: Alexis Jose Brito Vizcaino
A61: 45763 | B61: Carlos Gustavo Zabala | C61: Alexis Jose Brito Vizcaino | D61: Yeferson Angel Gay | E61: Cristian Joel Moreno | F61: Angel Daniel Castillo | G61: Diego Jose Garcia Garcia | H61: Luis Raul Marquez Araujo | J61: Vanina Leonor Lezcano | K61: Carlos Elias Guevara Garanton | L61: Diego German Rodriguez | M61: Carlos Villanueva | N61: Miguel Antonio Akouri Samra | O61: Sergio Luis Prado | P61: Daniel Oscar Aguirre | Q61: Fabricio Sebastian Castillo | R61: Claudio Omar Cobas | S61: Sebastian Leandro Toconas | T61: Jorge Yefherson Martinez Hernandez | U61: Anibal Rafael Cabrera Paredes | V61: Matias Alejandro Romero | W61: Selso Sanchez | X61: Diego Marcelo Diaz | Y61: Daniel Eduardo FuentesTovar | Z61: Haylonn Mathias Do Carmo | AB61: Aquilino Romero Velazquez | AC61: Yovertt Daniel Herrera Zamora | AD61: Abel Mario Martinez | AE61: Derek Daniel Almeida Santander | AF61: Sebastian Alexis Lopez | AG61: Julio David Muñoz Garcia | AH61: Braian Ezequiel Molina | AI61: Luis Miguel Prato Ceballo | AJ61: Luciano Ezequiel Cordoba | AK61: qh Carlos Alberto Gonzalez | AL61: Victor Emanuel Piris | AM61: Fernando Ariel Lopez | AN61: Dionicio Ruiz Diaz | AO61: Damian Jorge Abalo Prelat | AP61: Jose Miguel Camacho Fernandez | AQ61: Ezequiel Adrian Marelli | AR61: Mauro Gabriel Allosa | AS61: Luis Eduardo Anselmi | AT61: Esteban Del Barco | AU61: Jackson Jose Sosa Garcia | AV61: Rommer Leandro Cordero Hernandez | AW61: Lautaro Ezequiel Scarpitti | AX61: Hector Jose Suarez Uzcategui | AY61: Sergio Gustavo Barrios | DI61: Alexis Jose Brito Vizcaino
A62: 45764 | B62: Carlos Gustavo Zabala | C62: Alexis Jose Brito Vizcaino | D62: Yeferson Angel Gay | E62: Cristian Joel Moreno | F62: Angel Daniel Castillo | G62: Diego Jose Garcia Garcia | H62: Luis Raul Marquez Araujo | J62: Vanina Leonor Lezcano | K62: Carlos Elias Guevara Garanton | L62: Diego German Rodriguez | M62: Carlos Villanueva | N62: Miguel Antonio Akouri Samra | O62: Sergio Luis Prado | P62: Daniel Oscar Aguirre | Q62: Fabricio Sebastian Castillo | R62: Claudio Omar Cobas | S62: Sebastian Leandro Toconas | T62: Jorge Yefherson Martinez Hernandez | U62: Anibal Rafael Cabrera Paredes | V62: Matias Alejandro Romero | W62: Selso Sanchez | X62: Diego Marcelo Diaz | Y62: Daniel Eduardo FuentesTovar | Z62: Haylonn Mathias Do Carmo | AB62: Aquilino Romero Velazquez | AC62: Yovertt Daniel Herrera Zamora | AD62: Abel Mario Martinez | AE62: Derek Daniel Almeida Santander | AF62: Sebastian Alexis Lopez | AG62: Julio David Muñoz Garcia | AH62: Braian Ezequiel Molina | AI62: Luis Miguel Prato Ceballo | AJ62: Luciano Ezequiel Cordoba | AK62: qh Carlos Alberto Gonzalez | AL62: Victor Emanuel Piris | AM62: Fernando Ariel Lopez | AN62: Dionicio Ruiz Diaz | AO62: Damian Jorge Abalo Prelat | AP62: Jose Miguel Camacho Fernandez | AQ62: Ezequiel Adrian Marelli | AR62: Mauro Gabriel Allosa | AS62: Luis Eduardo Anselmi | AT62: Esteban Del Barco | AU62: Jackson Jose Sosa Garcia | AV62: Rommer Leandro Cordero Hernandez | AW62: Lautaro Ezequiel Scarpitti | AX62: Hector Jose Suarez Uzcategui | AY62: Sergio Gustavo Barrios | DI62: Alexis Jose Brito Vizcaino
A63: 45765 | B63: Carlos Gustavo Zabala | C63: Alexis Jose Brito Vizcaino | D63: Yeferson Angel Gay | F63: Angel Daniel Castillo | G63: Diego Jose Garcia Garcia | H63: Luis Raul Marquez Araujo | J63: Vanina Leonor Lezcano | K63: Carlos Elias Guevara Garanton | L63: Diego German Rodriguez | M63: Carlos Villanueva | N63: Miguel Antonio Akouri Samra | O63: Sergio Luis Prado | P63: Daniel Oscar Aguirre | Q63: Fabricio Sebastian Castillo | R63: Claudio Omar Cobas | S63: Sebastian Leandro Toconas | T63: Jorge Yefherson Martinez Hernandez | U63: Anibal Rafael Cabrera Paredes | V63: Matias Alejandro Romero | W63: Selso Sanchez | X63: Diego Marcelo Diaz | Y63: Daniel Eduardo FuentesTovar | Z63: Haylonn Mathias Do Carmo | AB63: Aquilino Romero Velazquez | AC63: Yovertt Daniel Herrera Zamora | AD63: Abel Mario Martinez | AE63: Derek Daniel Almeida Santander | AF63: Sebastian Alexis Lopez | AG63: Julio David Muñoz Garcia | AH63: Braian Ezequiel Molina | AI63: Luis Miguel Prato Ceballo | AJ63: Luciano Ezequiel Cordoba | AK63: qh Carlos Alberto Gonzalez | AL63: Victor Emanuel Piris | AM63: Fernando Ariel Lopez | AN63: Dionicio Ruiz Diaz | AO63: Damian Jorge Abalo Prelat | AP63: Jose Miguel Camacho Fernandez | AQ63: Ezequiel Adrian Marelli | AR63: Mauro Gabriel Allosa | AS63: Luis Eduardo Anselmi | AT63: Esteban Del Barco | AU63: Jackson Jose Sosa Garcia | AV63: Rommer Leandro Cordero Hernandez | AW63: Lautaro Ezequiel Scarpitti | AX63: Hector Jose Suarez Uzcategui | AY63: Sergio Gustavo Barrios | DI63: Alexis Jose Brito Vizcaino
A64: 45766 | B64: Carlos Gustavo Zabala | C64: Alexis Jose Brito Vizcaino | D64: Yeferson Angel Gay | E64: Cesar Nixon Velasco Zerpa | F64: Angel Daniel Castillo | G64: Diego Jose Garcia Garcia | H64: Luis Raul Marquez Araujo | J64: Vanina Leonor Lezcano | K64: Carlos Elias Guevara Garanton | L64: Diego German Rodriguez | M64: Carlos Villanueva | N64: Miguel Antonio Akouri Samra | O64: Sergio Luis Prado | P64: Daniel Oscar Aguirre | Q64: Fabricio Sebastian Castillo | R64: Claudio Omar Cobas | S64: Sebastian Leandro Toconas | T64: Jorge Yefherson Martinez Hernandez | U64: Anibal Rafael Cabrera Paredes | V64: Matias Alejandro Romero | W64: Selso Sanchez | X64: Diego Marcelo Diaz | Y64: Daniel Eduardo FuentesTovar | Z64: Haylonn Mathias Do Carmo | AB64: Aquilino Romero Velazquez | AC64: Yovertt Daniel Herrera Zamora | AD64: Abel Mario Martinez | AE64: Derek Daniel Almeida Santander | AF64: Sebastian Alexis Lopez | AG64: Julio David Muñoz Garcia | AH64: Braian Ezequiel Molina | AI64: Luis Miguel Prato Ceballo | AJ64: Luciano Ezequiel Cordoba | AK64: qh Carlos Alberto Gonzalez | AL64: Victor Emanuel Piris | AM64: Fernando Ariel Lopez | AN64: Dionicio Ruiz Diaz | AO64: Damian Jorge Abalo Prelat | AP64: Jose Miguel Camacho Fernandez | AQ64: Ezequiel Adrian Marelli | AR64: Mauro Gabriel Allosa | AS64: Luis Eduardo Anselmi | AT64: Esteban Del Barco | AU64: Jackson Jose Sosa Garcia | AV64: Rommer Leandro Cordero Hernandez | AW64: Lautaro Ezequiel Scarpitti | AX64: Hector Jose Suarez Uzcategui | AY64: Sergio Gustavo Barrios | DI64: Alexis Jose Brito Vizcaino
A65: 45767 | B65: Carlos Gustavo Zabala | C65: Alexis Jose Brito Vizcaino | D65: Yeferson Angel Gay | E65: Cesar Nixon Velasco Zerpa | F65: Angel Daniel Castillo | G65: Diego Jose Garcia Garcia | H65: Luis Raul Marquez Araujo | J65: Vanina Leonor Lezcano | K65: Carlos Elias Guevara Garanton | L65: Diego German Rodriguez | M65: Carlos Villanueva | N65: Miguel Antonio Akouri Samra | O65: Sergio Luis Prado | P65: Daniel Oscar Aguirre | Q65: Fabricio Sebastian Castillo | R65: Claudio Omar Cobas | S65: Sebastian Leandro Toconas | T65: Jorge Yefherson Martinez Hernandez | U65: Anibal Rafael Cabrera Paredes | V65: Matias Alejandro Romero | W65: Selso Sanchez | X65: Diego Marcelo Diaz | Y65: Daniel Eduardo FuentesTovar | Z65: Haylonn Mathias Do Carmo | AB65: Aquilino Romero Velazquez | AC65: Yovertt Daniel Herrera Zamora | AD65: Abel Mario Martinez | AE65: Derek Daniel Almeida Santander | AF65: Sebastian Alexis Lopez | AG65: Julio David Muñoz Garcia | AH65: Braian Ezequiel Molina | AI65: Luis Miguel Prato Ceballo | AJ65: Luciano Ezequiel Cordoba | AK65: qh Carlos Alberto Gonzalez | AL65: Victor Emanuel Piris | AM65: Fernando Ariel Lopez | AN65: Dionicio Ruiz Diaz | AO65: Damian Jorge Abalo Prelat | AP65: Jose Miguel Camacho Fernandez | AQ65: Ezequiel Adrian Marelli | AR65: Mauro Gabriel Allosa | AS65: Luis Eduardo Anselmi | AT65: Esteban Del Barco | AU65: Jackson Jose Sosa Garcia | AV65: Rommer Leandro Cordero Hernandez | AW65: Lautaro Ezequiel Scarpitti | AX65: Hector Jose Suarez Uzcategui | AY65: Sergio Gustavo Barrios | DI65: Alexis Jose Brito Vizcaino
A66: 45768 | B66: Carlos Gustavo Zabala | C66: Alexis Jose Brito Vizcaino | D66: Yeferson Angel Gay | E66: Cesar Nixon Velasco Zerpa | F66: Angel Daniel Castillo | G66: Diego Jose Garcia Garcia | H66: Luis Raul Marquez Araujo | J66: Vanina Leonor Lezcano | K66: Carlos Elias Guevara Garanton | L66: Diego German Rodriguez | M66: Carlos Villanueva | N66: Miguel Antonio Akouri Samra | O66: Sergio Luis Prado | P66: Daniel Oscar Aguirre | Q66: Fabricio Sebastian Castillo | R66: Claudio Omar Cobas | S66: Sebastian Leandro Toconas | T66: Jorge Yefherson Martinez Hernandez | U66: Anibal Rafael Cabrera Paredes | V66: Matias Alejandro Romero | W66: Selso Sanchez | X66: Diego Marcelo Diaz | Y66: Daniel Eduardo FuentesTovar | Z66: Haylonn Mathias Do Carmo | AA66: Gilberto Miguel Federico Aguirre Viloria | AB66: Aquilino Romero Velazquez | AC66: Yovertt Daniel Herrera Zamora | AD66: Abel Mario Martinez | AE66: Derek Daniel Almeida Santander | AF66: Sebastian Alexis Lopez | AG66: Julio David Muñoz Garcia | AH66: Braian Ezequiel Molina | AI66: Luis Miguel Prato Ceballo | AJ66: Luciano Ezequiel Cordoba | AK66: qh Carlos Alberto Gonzalez | AL66: Victor Emanuel Piris | AM66: Fernando Ariel Lopez | AN66: Dionicio Ruiz Diaz | AO66: Damian Jorge Abalo Prelat | AP66: Jose Miguel Camacho Fernandez | AQ66: Ezequiel Adrian Marelli | AR66: Mauro Gabriel Allosa | AS66: Luis Eduardo Anselmi | AT66: Esteban Del Barco | AU66: Jackson Jose Sosa Garcia | AV66: Rommer Leandro Cordero Hernandez | AW66: Lautaro Ezequiel Scarpitti | AX66: Hector Jose Suarez Uzcategui | AY66: Sergio Gustavo Barrios | DI66: Alexis Jose Brito Vizcaino
A67: 45769 | B67: Carlos Gustavo Zabala | C67: Alexis Jose Brito Vizcaino | D67: Yeferson Angel Gay | E67: Cesar Nixon Velasco Zerpa | F67: Angel Daniel Castillo | G67: Diego Jose Garcia Garcia | H67: Luis Raul Marquez Araujo | J67: Vanina Leonor Lezcano | K67: Carlos Elias Guevara Garanton | L67: Diego German Rodriguez | M67: Carlos Villanueva | N67: Miguel Antonio Akouri Samra | O67: Sergio Luis Prado | P67: Daniel Oscar Aguirre | Q67: Fabricio Sebastian Castillo | R67: Claudio Omar Cobas | S67: Sebastian Leandro Toconas | T67: Jorge Yefherson Martinez Hernandez | U67: Anibal Rafael Cabrera Paredes | V67: Matias Alejandro Romero | W67: Selso Sanchez | X67: Diego Marcelo Diaz | Y67: Daniel Eduardo FuentesTovar | Z67: Haylonn Mathias Do Carmo | AA67: Gilberto Miguel Federico Aguirre Viloria | AB67: Aquilino Romero Velazquez | AC67: Yovertt Daniel Herrera Zamora | AD67: Abel Mario Martinez | AE67: Derek Daniel Almeida Santander | AF67: Henry Alexander Robles Molina | AG67: Julio David Muñoz Garcia | AH67: Braian Ezequiel Molina | AI67: Luis Miguel Prato Ceballo | AJ67: Luciano Ezequiel Cordoba | AK67: qh Carlos Alberto Gonzalez | AL67: Victor Emanuel Piris | AM67: Fernando Ariel Lopez | AN67: Dionicio Ruiz Diaz | AO67: Damian Jorge Abalo Prelat | AP67: Jose Miguel Camacho Fernandez | AQ67: Ezequiel Adrian Marelli | AR67: Mauro Gabriel Allosa | AS67: Luis Eduardo Anselmi | AT67: Esteban Del Barco | AU67: Jackson Jose Sosa Garcia | AV67: Rommer Leandro Cordero Hernandez | AW67: Lautaro Ezequiel Scarpitti | AX67: Hector Jose Suarez Uzcategui | AY67: Sergio Gustavo Barrios | DI67: Alexis Jose Brito Vizcaino
A68: 45770 | B68: Carlos Gustavo Zabala | C68: Alexis Jose Brito Vizcaino | D68: Yeferson Angel Gay | E68: Cesar Nixon Velasco Zerpa | F68: Angel Daniel Castillo | G68: Diego Jose Garcia Garcia | H68: Luis Raul Marquez Araujo | J68: Vanina Leonor Lezcano | K68: Carlos Elias Guevara Garanton | L68: Diego German Rodriguez | M68: Carlos Villanueva | N68: Miguel Antonio Akouri Samra | O68: Sergio Luis Prado | P68: Daniel Oscar Aguirre | Q68: Fabricio Sebastian Castillo | R68: Claudio Omar Cobas | S68: Sebastian Leandro Toconas | T68: Jorge Yefherson Martinez Hernandez | U68: Anibal Rafael Cabrera Paredes | V68: Matias Alejandro Romero | W68: Selso Sanchez | X68: Diego Marcelo Diaz | Y68: Daniel Eduardo FuentesTovar | AA68: Gilberto Miguel Federico Aguirre Viloria | AB68: Aquilino Romero Velazquez | AC68: Yovertt Daniel Herrera Zamora | AD68: Abel Mario Martinez | AE68: Derek Daniel Almeida Santander | AF68: Henry Alexander Robles Molina | AG68: Julio David Muñoz Garcia | AH68: Braian Ezequiel Molina | AI68: Luis Miguel Prato Ceballo | AJ68: Luciano Ezequiel Cordoba | AK68: qh Carlos Alberto Gonzalez | AL68: Victor Emanuel Piris | AM68: Fernando Ariel Lopez | AN68: Dionicio Ruiz Diaz | AO68: Damian Jorge Abalo Prelat | AP68: Jose Miguel Camacho Fernandez | AQ68: Ezequiel Adrian Marelli | AR68: Mauro Gabriel Allosa | AS68: Luis Eduardo Anselmi | AT68: Esteban Del Barco | AU68: Jackson Jose Sosa Garcia | AV68: Rommer Leandro Cordero Hernandez | AW68: Lautaro Ezequiel Scarpitti | AX68: Hector Jose Suarez Uzcategui | AY68: Sergio Gustavo Barrios | DI68: Alexis Jose Brito Vizcaino
A69: 45771 | B69: Carlos Gustavo Zabala | C69: Alexis Jose Brito Vizcaino | D69: Yeferson Angel Gay | E69: Cesar Nixon Velasco Zerpa | F69: Angel Daniel Castillo | G69: Diego Jose Garcia Garcia | H69: Luis Raul Marquez Araujo | J69: Vanina Leonor Lezcano | K69: Carlos Elias Guevara Garanton | L69: Diego German Rodriguez | M69: Carlos Villanueva | N69: Miguel Antonio Akouri Samra | O69: Sergio Luis Prado | P69: Daniel Oscar Aguirre | Q69: Fabricio Sebastian Castillo | R69: Claudio Omar Cobas | S69: Sebastian Leandro Toconas | T69: Jorge Yefherson Martinez Hernandez | U69: Anibal Rafael Cabrera Paredes | V69: Matias Alejandro Romero | W69: Selso Sanchez | X69: Diego Marcelo Diaz | Y69: Daniel Eduardo FuentesTovar | Z69: Pablo Ceferino Gonzalez | AA69: Gilberto Miguel Federico Aguirre Viloria | AB69: Aquilino Romero Velazquez | AC69: Yovertt Daniel Herrera Zamora | AD69: Abel Mario Martinez | AE69: Derek Daniel Almeida Santander | AF69: Henry Alexander Robles Molina | AG69: Julio David Muñoz Garcia | AI69: Luis Miguel Prato Ceballo | AK69: qh Carlos Alberto Gonzalez | AL69: Victor Emanuel Piris | AM69: Fernando Ariel Lopez | AN69: Dionicio Ruiz Diaz | AO69: Damian Jorge Abalo Prelat | AP69: Jose Miguel Camacho Fernandez | AQ69: Ezequiel Adrian Marelli | AR69: Mauro Gabriel Allosa | AS69: Luis Eduardo Anselmi | AT69: Esteban Del Barco | AU69: Jackson Jose Sosa Garcia | AV69: Rommer Leandro Cordero Hernandez | AW69: Lautaro Ezequiel Scarpitti | AX69: Hector Jose Suarez Uzcategui | AY69: Sergio Gustavo Barrios | DI69: Alexis Jose Brito Vizcaino
A70: 45772 | B70: Carlos Gustavo Zabala | C70: Alexis Jose Brito Vizcaino | D70: Yeferson Angel Gay | E70: Cesar Nixon Velasco Zerpa | F70: Angel Daniel Castillo | G70: Diego Jose Garcia Garcia | H70: Luis Raul Marquez Araujo | J70: Vanina Leonor Lezcano | K70: Carlos Elias Guevara Garanton | L70: Diego German Rodriguez | M70: Carlos Villanueva | N70: Miguel Antonio Akouri Samra | O70: Sergio Luis Prado | P70: Daniel Oscar Aguirre | Q70: Fabricio Sebastian Castillo | R70: Claudio Omar Cobas | S70: Sebastian Leandro Toconas | T70: Jorge Yefherson Martinez Hernandez | U70: Anibal Rafael Cabrera Paredes | V70: Matias Alejandro Romero | W70: Selso Sanchez | X70: Diego Marcelo Diaz | Y70: Daniel Eduardo FuentesTovar | Z70: Pablo Ceferino Gonzalez | AA70: Gilberto Miguel Federico Aguirre Viloria | AB70: Aquilino Romero Velazquez | AC70: Yovertt Daniel Herrera Zamora | AD70: Abel Mario Martinez | AE70: Derek Daniel Almeida Santander | AF70: Henry Alexander Robles Molina | AG70: Julio David Muñoz Garcia | AI70: Luis Miguel Prato Ceballo | AK70: qh Carlos Alberto Gonzalez | AL70: Victor Emanuel Piris | AM70: Fernando Ariel Lopez | AN70: Dionicio Ruiz Diaz | AO70: Damian Jorge Abalo Prelat | AP70: Jose Miguel Camacho Fernandez | AQ70: Ezequiel Adrian Marelli | AR70: Mauro Gabriel Allosa | AS70: Luis Eduardo Anselmi | AT70: Esteban Del Barco | AU70: Jackson Jose Sosa Garcia | AV70: Rommer Leandro Cordero Hernandez | AW70: Lautaro Ezequiel Scarpitti | AX70: Hector Jose Suarez Uzcategui | AY70: Sergio Gustavo Barrios | DI70: Alexis Jose Brito Vizcaino
A71: 45773 | B71: Carlos Gustavo Zabala | C71: Alexis Jose Brito Vizcaino | D71: Yeferson Angel Gay | E71: Cesar Nixon Velasco Zerpa | F71: Angel Daniel Castillo | G71: Diego Jose Garcia Garcia | H71: Luis Raul Marquez Araujo | J71: Vanina Leonor Lezcano | K71: Carlos Elias Guevara Garanton | L71: Diego German Rodriguez | M71: Carlos Villanueva | N71: Miguel Antonio Akouri Samra | O71: Sergio Luis Prado | P71: Daniel Oscar Aguirre | Q71: Fabricio Sebastian Castillo | R71: Claudio Omar Cobas | S71: Sebastian Leandro Toconas | T71: Jorge Yefherson Martinez Hernandez | U71: Anibal Rafael Cabrera Paredes | V71: Matias Alejandro Romero | W71: Selso Sanchez | X71: Diego Marcelo Diaz | Y71: Daniel Eduardo FuentesTovar | Z71: Pablo Ceferino Gonzalez | AA71: Gilberto Miguel Federico Aguirre Viloria | AB71: Aquilino Romero Velazquez | AC71: Yovertt Daniel Herrera Zamora | AD71: Abel Mario Martinez | AE71: Derek Daniel Almeida Santander | AF71: Henry Alexander Robles Molina | AG71: Julio David Muñoz Garcia | AH71: Fernando Di Pietro | AI71: Luis Miguel Prato Ceballo | AK71: qh Carlos Alberto Gonzalez | AL71: Victor Emanuel Piris | AM71: Fernando Ariel Lopez | AN71: Dionicio Ruiz Diaz | AO71: Damian Jorge Abalo Prelat | AP71: Jose Miguel Camacho Fernandez | AQ71: Ezequiel Adrian Marelli | AR71: Mauro Gabriel Allosa | AS71: Luis Eduardo Anselmi | AT71: Esteban Del Barco | AU71: Jackson Jose Sosa Garcia | AV71: Rommer Leandro Cordero Hernandez | AW71: Lautaro Ezequiel Scarpitti | AX71: Hector Jose Suarez Uzcategui | AY71: Sergio Gustavo Barrios | BS71: Hernan Martin D'Avanzo | DI71: Alexis Jose Brito Vizcaino
A72: 45774 | B72: Carlos Gustavo Zabala | C72: Alexis Jose Brito Vizcaino | D72: Yeferson Angel Gay | E72: Cesar Nixon Velasco Zerpa | F72: Angel Daniel Castillo | G72: Diego Jose Garcia Garcia | H72: Luis Raul Marquez Araujo | J72: Vanina Leonor Lezcano | K72: Carlos Elias Guevara Garanton | L72: Diego German Rodriguez | M72: Carlos Villanueva | N72: Miguel Antonio Akouri Samra | O72: Sergio Luis Prado | P72: Daniel Oscar Aguirre | Q72: Fabricio Sebastian Castillo | R72: Claudio Omar Cobas | S72: Sebastian Leandro Toconas | T72: Jorge Yefherson Martinez Hernandez | U72: Anibal Rafael Cabrera Paredes | V72: Matias Alejandro Romero | W72: Selso Sanchez | X72: Diego Marcelo Diaz | Y72: Daniel Eduardo FuentesTovar | Z72: Pablo Ceferino Gonzalez | AA72: Gilberto Miguel Federico Aguirre Viloria | AB72: Aquilino Romero Velazquez | AC72: Yovertt Daniel Herrera Zamora | AD72: Abel Mario Martinez | AE72: Derek Daniel Almeida Santander | AF72: Henry Alexander Robles Molina | AG72: Julio David Muñoz Garcia | AH72: Fernando Di Pietro | AI72: Luis Miguel Prato Ceballo | AJ72: Esteban Del Barco | AK72: qh Carlos Alberto Gonzalez | AL72: Victor Emanuel Piris | AM72: Fernando Ariel Lopez | AN72: Dionicio Ruiz Diaz | AO72: Damian Jorge Abalo Prelat | AP72: Jose Miguel Camacho Fernandez | AQ72: Ezequiel Adrian Marelli | AR72: Mauro Gabriel Allosa | AS72: Luis Eduardo Anselmi | AU72: Jackson Jose Sosa Garcia | AV72: Rommer Leandro Cordero Hernandez | AW72: Lautaro Ezequiel Scarpitti | AX72: Hector Jose Suarez Uzcategui | AY72: Sergio Gustavo Barrios | BS72: Hernan Martin D'Avanzo | DI72: Alexis Jose Brito Vizcaino
A73: 45775 | B73: Carlos Gustavo Zabala | C73: Alexis Jose Brito Vizcaino | D73: Yeferson Angel Gay | E73: Cesar Nixon Velasco Zerpa | F73: Angel Daniel Castillo | G73: Diego Jose Garcia Garcia | H73: Luis Raul Marquez Araujo | J73: Vanina Leonor Lezcano | K73: Carlos Elias Guevara Garanton | L73: Diego German Rodriguez | M73: Carlos Villanueva | N73: Miguel Antonio Akouri Samra | O73: Sergio Luis Prado | P73: Daniel Oscar Aguirre | Q73: Fabricio Sebastian Castillo | R73: Claudio Omar Cobas | S73: Sebastian Leandro Toconas | T73: Jorge Yefherson Martinez Hernandez | U73: Anibal Rafael Cabrera Paredes | V73: Matias Alejandro Romero | W73: Selso Sanchez | X73: Diego Marcelo Diaz | Y73: Daniel Eduardo FuentesTovar | Z73: Pablo Ceferino Gonzalez | AA73: Gilberto Miguel Federico Aguirre Viloria | AB73: Aquilino Romero Velazquez | AC73: Yovertt Daniel Herrera Zamora | AD73: Abel Mario Martinez | AE73: Derek Daniel Almeida Santander | AF73: Henry Alexander Robles Molina | AG73: Julio David Muñoz Garcia | AH73: Fernando Di Pietro | AI73: Luis Miguel Prato Ceballo | AJ73: Esteban Del Barco | AK73: qh Carlos Alberto Gonzalez | AL73: Victor Emanuel Piris | AM73: Fernando Ariel Lopez | AN73: Dionicio Ruiz Diaz | AO73: Damian Jorge Abalo Prelat | AP73: Jose Miguel Camacho Fernandez | AQ73: Ezequiel Adrian Marelli | AR73: Mauro Gabriel Allosa | AS73: Luis Eduardo Anselmi | AU73: Jackson Jose Sosa Garcia | AV73: Rommer Leandro Cordero Hernandez | AW73: Lautaro Ezequiel Scarpitti | AX73: Hector Jose Suarez Uzcategui | AY73: Sergio Gustavo Barrios | BG73: Emiliano Rodrigo Perez | BS73: Hernan Martin D'Avanzo | BZ73: Juan Carlos Gimenez | DI73: Alexis Jose Brito Vizcaino
A74: 45776 | B74: Carlos Gustavo Zabala | C74: Alexis Jose Brito Vizcaino | D74: Yeferson Angel Gay | E74: Cesar Nixon Velasco Zerpa | F74: Angel Daniel Castillo | G74: Diego Jose Garcia Garcia | H74: Luis Raul Marquez Araujo | J74: Vanina Leonor Lezcano | K74: Carlos Elias Guevara Garanton | L74: Diego German Rodriguez | M74: Carlos Villanueva | N74: Miguel Antonio Akouri Samra | O74: Sergio Luis Prado | P74: Daniel Oscar Aguirre | Q74: Fabricio Sebastian Castillo | R74: Claudio Omar Cobas | S74: Sebastian Leandro Toconas | T74: Jorge Yefherson Martinez Hernandez | U74: Anibal Rafael Cabrera Paredes | V74: Matias Alejandro Romero | W74: Selso Sanchez | X74: Diego Marcelo Diaz | Y74: Daniel Eduardo FuentesTovar | Z74: Pablo Ceferino Gonzalez | AA74: Gilberto Miguel Federico Aguirre Viloria | AB74: Aquilino Romero Velazquez | AC74: Yovertt Daniel Herrera Zamora | AD74: Abel Mario Martinez | AE74: Derek Daniel Almeida Santander | AF74: Henry Alexander Robles Molina | AG74: Julio David Muñoz Garcia | AH74: Fernando Di Pietro | AI74: Luis Miguel Prato Ceballo | AJ74: Esteban Del Barco | AK74: qh Carlos Alberto Gonzalez | AL74: Victor Emanuel Piris | AM74: Fernando Ariel Lopez | AN74: Dionicio Ruiz Diaz | AO74: Damian Jorge Abalo Prelat | AP74: Jose Miguel Camacho Fernandez | AQ74: Ezequiel Adrian Marelli | AR74: Mauro Gabriel Allosa | AS74: Luis Eduardo Anselmi | AT74: GIAMA | AU74: Jackson Jose Sosa Garcia | AV74: Rommer Leandro Cordero Hernandez | AW74: Lautaro Ezequiel Scarpitti | AX74: Hector Jose Suarez Uzcategui | AY74: Sergio Gustavo Barrios | BG74: Emiliano Rodrigo Perez | BP74: Alberto Fausto Cillo | BS74: Hernan Martin D'Avanzo | BU74: Fabricio Damian Fernandez Lattianzi | BZ74: Juan Carlos Gimenez | DI74: Alexis Jose Brito Vizcaino
A75: 45777 | B75: Carlos Gustavo Zabala | C75: Alexis Jose Brito Vizcaino | D75: Yeferson Angel Gay | E75: Cesar Nixon Velasco Zerpa | F75: Angel Daniel Castillo | G75: Diego Jose Garcia Garcia | H75: Luis Raul Marquez Araujo | J75: Vanina Leonor Lezcano | K75: Carlos Elias Guevara Garanton | L75: Diego German Rodriguez | M75: Carlos Villanueva | N75: Miguel Antonio Akouri Samra | O75: Sergio Luis Prado | P75: Daniel Oscar Aguirre | Q75: Fabricio Sebastian Castillo | R75: Claudio Omar Cobas | S75: Sebastian Leandro Toconas | T75: Jorge Yefherson Martinez Hernandez | U75: Anibal Rafael Cabrera Paredes | V75: Matias Alejandro Romero | W75: Selso Sanchez | X75: Diego Marcelo Diaz | Y75: Daniel Eduardo FuentesTovar | Z75: Pablo Ceferino Gonzalez | AA75: Gilberto Miguel Federico Aguirre Viloria | AB75: Aquilino Romero Velazquez | AC75: Yovertt Daniel Herrera Zamora | AD75: Abel Mario Martinez | AE75: Derek Daniel Almeida Santander | AF75: Henry Alexander Robles Molina | AG75: Julio David Muñoz Garcia | AH75: Fernando Di Pietro | AI75: Luis Miguel Prato Ceballo | AJ75: Esteban Del Barco | AK75: qh Carlos Alberto Gonzalez | AL75: Victor Emanuel Piris | AM75: Fernando Ariel Lopez | AN75: Dionicio Ruiz Diaz | AO75: Damian Jorge Abalo Prelat | AP75: Jose Miguel Camacho Fernandez | AQ75: Ezequiel Adrian Marelli | AR75: Mauro Gabriel Allosa | AS75: Luis Eduardo Anselmi | AU75: Jackson Jose Sosa Garcia | AV75: Rommer Leandro Cordero Hernandez | AW75: Lautaro Ezequiel Scarpitti | AX75: Hector Jose Suarez Uzcategui | AY75: Sergio Gustavo Barrios | BG75: Emiliano Rodrigo Perez | BP75: Alberto Fausto Cillo | BS75: Hernan Martin D'Avanzo | BU75: Fabricio Damian Fernandez Lattianzi | BW75: Cristian Jorge Miranda | BZ75: Juan Carlos Gimenez | DI75: Alexis Jose Brito Vizcaino
A76: 45778 | B76: Carlos Gustavo Zabala | C76: Alexis Jose Brito Vizcaino | D76: Yeferson Angel Gay | E76: Cesar Nixon Velasco Zerpa | F76: Angel Daniel Castillo | G76: Diego Jose Garcia Garcia | H76: Luis Raul Marquez Araujo | J76: Vanina Leonor Lezcano | K76: Carlos Elias Guevara Garanton | L76: Diego German Rodriguez | M76: Carlos Villanueva | N76: Miguel Antonio Akouri Samra | O76: Sergio Luis Prado | P76: Daniel Oscar Aguirre | Q76: Fabricio Sebastian Castillo | R76: Claudio Omar Cobas | S76: Sebastian Leandro Toconas | U76: Anibal Rafael Cabrera Paredes | V76: Matias Alejandro Romero | W76: Selso Sanchez | X76: Diego Marcelo Diaz | Y76: Daniel Eduardo FuentesTovar | Z76: Pablo Ceferino Gonzalez | AA76: Gilberto Miguel Federico Aguirre Viloria | AB76: Aquilino Romero Velazquez | AC76: Yovertt Daniel Herrera Zamora | AD76: Abel Mario Martinez | AE76: Derek Daniel Almeida Santander | AF76: Henry Alexander Robles Molina | AG76: Julio David Muñoz Garcia | AH76: Fernando Di Pietro | AI76: Luis Miguel Prato Ceballo | AJ76: Esteban Del Barco | AK76: qh Carlos Alberto Gonzalez | AL76: Victor Emanuel Piris | AM76: Fernando Ariel Lopez | AN76: Dionicio Ruiz Diaz | AO76: Damian Jorge Abalo Prelat | AP76: Jose Miguel Camacho Fernandez | AQ76: Ezequiel Adrian Marelli | AR76: Mauro Gabriel Allosa | AS76: Luis Eduardo Anselmi | AU76: Jackson Jose Sosa Garcia | AV76: Rommer Leandro Cordero Hernandez | AW76: Lautaro Ezequiel Scarpitti | AY76: Sergio Gustavo Barrios | BG76: Emiliano Rodrigo Perez | BP76: Alberto Fausto Cillo | BS76: Hernan Martin D'Avanzo | BU76: Fabricio Damian Fernandez Lattianzi | BW76: Cristian Jorge Miranda | BZ76: Juan Carlos Gimenez | DI76: Alexis Jose Brito Vizcaino
A77: 45779 | B77: Carlos Gustavo Zabala | C77: Alexis Jose Brito Vizcaino | D77: Yeferson Angel Gay | E77: Cesar Nixon Velasco Zerpa | F77: Angel Daniel Castillo | G77: Diego Jose Garcia Garcia | H77: Luis Raul Marquez Araujo | J77: Vanina Leonor Lezcano | K77: Carlos Elias Guevara Garanton | L77: Diego German Rodriguez | M77: Carlos Villanueva | N77: Miguel Antonio Akouri Samra | O77: Sergio Luis Prado | P77: Daniel Oscar Aguirre | Q77: Fabricio Sebastian Castillo | R77: Claudio Omar Cobas | S77: Sebastian Leandro Toconas | T77: Eduardo Gabriel Olea | U77: Anibal Rafael Cabrera Paredes | V77: Matias Alejandro Romero | W77: Selso Sanchez | X77: Diego Marcelo Diaz | Y77: Daniel Eduardo FuentesTovar | Z77: Pablo Ceferino Gonzalez | AA77: Gilberto Miguel Federico Aguirre Viloria | AB77: Aquilino Romero Velazquez | AC77: Yovertt Daniel Herrera Zamora | AD77: Abel Mario Martinez | AE77: Derek Daniel Almeida Santander | AF77: Henry Alexander Robles Molina | AG77: Julio David Muñoz Garcia | AH77: Fernando Di Pietro | AI77: Luis Miguel Prato Ceballo | AJ77: Esteban Del Barco | AK77: qh Carlos Alberto Gonzalez | AL77: Victor Emanuel Piris | AM77: Fernando Ariel Lopez | AN77: Dionicio Ruiz Diaz | AO77: Damian Jorge Abalo Prelat | AP77: Jose Miguel Camacho Fernandez | AQ77: Ezequiel Adrian Marelli | AR77: Mauro Gabriel Allosa | AS77: Luis Eduardo Anselmi | AU77: Jackson Jose Sosa Garcia | AV77: Rommer Leandro Cordero Hernandez | AW77: Lautaro Ezequiel Scarpitti | AY77: Sergio Gustavo Barrios | BG77: Emiliano Rodrigo Perez | BP77: Alberto Fausto Cillo | BS77: Hernan Martin D'Avanzo | BU77: Fabricio Damian Fernandez Lattianzi | BW77: Cristian Jorge Miranda | BZ77: Juan Carlos Gimenez | CH77: Hector Daniel Techeira | DI77: Alexis Jose Brito Vizcaino
A78: 45780 | B78: Carlos Gustavo Zabala | C78: Alexis Jose Brito Vizcaino | D78: Yeferson Angel Gay | E78: Cesar Nixon Velasco Zerpa | F78: Angel Daniel Castillo | G78: Diego Jose Garcia Garcia | H78: Luis Raul Marquez Araujo | J78: Vanina Leonor Lezcano | K78: Carlos Elias Guevara Garanton | L78: Diego German Rodriguez | M78: Carlos Villanueva | N78: Miguel Antonio Akouri Samra | O78: Sergio Luis Prado | P78: Daniel Oscar Aguirre | Q78: Fabricio Sebastian Castillo | R78: Claudio Omar Cobas | S78: Sebastian Leandro Toconas | T78: Eduardo Gabriel Olea | U78: Anibal Rafael Cabrera Paredes | V78: Matias Alejandro Romero | W78: Selso Sanchez | X78: Diego Marcelo Diaz | Y78: Daniel Eduardo FuentesTovar | Z78: Pablo Ceferino Gonzalez | AA78: Gilberto Miguel Federico Aguirre Viloria | AB78: Aquilino Romero Velazquez | AC78: Yovertt Daniel Herrera Zamora | AD78: Abel Mario Martinez | AE78: Derek Daniel Almeida Santander | AF78: Henry Alexander Robles Molina | AG78: Julio David Muñoz Garcia | AH78: Fernando Di Pietro | AI78: Luis Miguel Prato Ceballo | AJ78: Esteban Del Barco | AK78: qh Carlos Alberto Gonzalez | AL78: Victor Emanuel Piris | AM78: Fernando Ariel Lopez | AN78: Dionicio Ruiz Diaz | AO78: Damian Jorge Abalo Prelat | AP78: Jose Miguel Camacho Fernandez | AQ78: Ezequiel Adrian Marelli | AR78: Mauro Gabriel Allosa | AS78: Luis Eduardo Anselmi | AU78: Jackson Jose Sosa Garcia | AV78: Rommer Leandro Cordero Hernandez | AW78: Lautaro Ezequiel Scarpitti | AY78: Sergio Gustavo Barrios | BG78: Emiliano Rodrigo Perez | BP78: Alberto Fausto Cillo | BS78: Hernan Martin D'Avanzo | BU78: Fabricio Damian Fernandez Lattianzi | BW78: Cristian Jorge Miranda | BZ78: Juan Carlos Gimenez | CH78: Hector Daniel Techeira | DI78: Alexis Jose Brito Vizcaino
A79: 45781 | B79: Carlos Gustavo Zabala | C79: Alexis Jose Brito Vizcaino | D79: Yeferson Angel Gay | E79: Cesar Nixon Velasco Zerpa | F79: Angel Daniel Castillo | G79: Diego Jose Garcia Garcia | H79: Luis Raul Marquez Araujo | J79: Vanina Leonor Lezcano | K79: Carlos Elias Guevara Garanton | L79: Diego German Rodriguez | M79: Carlos Villanueva | N79: Miguel Antonio Akouri Samra | O79: Sergio Luis Prado | P79: Daniel Oscar Aguirre | Q79: Fabricio Sebastian Castillo | R79: Claudio Omar Cobas | S79: Sebastian Leandro Toconas | T79: Eduardo Gabriel Olea | U79: Anibal Rafael Cabrera Paredes | V79: Matias Alejandro Romero | W79: Selso Sanchez | X79: Diego Marcelo Diaz | Y79: Daniel Eduardo FuentesTovar | Z79: Pablo Ceferino Gonzalez | AA79: Gilberto Miguel Federico Aguirre Viloria | AB79: Aquilino Romero Velazquez | AC79: Yovertt Daniel Herrera Zamora | AD79: Abel Mario Martinez | AE79: Derek Daniel Almeida Santander | AF79: Henry Alexander Robles Molina | AG79: Julio David Muñoz Garcia | AH79: Fernando Di Pietro | AI79: Luis Miguel Prato Ceballo | AJ79: Esteban Del Barco | AK79: qh Carlos Alberto Gonzalez | AL79: Victor Emanuel Piris | AM79: Fernando Ariel Lopez | AN79: Dionicio Ruiz Diaz | AO79: Damian Jorge Abalo Prelat | AP79: Jose Miguel Camacho Fernandez | AQ79: Ezequiel Adrian Marelli | AR79: Mauro Gabriel Allosa | AS79: Luis Eduardo Anselmi | AU79: Jackson Jose Sosa Garcia | AV79: Rommer Leandro Cordero Hernandez | AW79: Lautaro Ezequiel Scarpitti | AY79: Sergio Gustavo Barrios | BG79: Emiliano Rodrigo Perez | BP79: Alberto Fausto Cillo | BS79: Hernan Martin D'Avanzo | BU79: Fabricio Damian Fernandez Lattianzi | BW79: Cristian Jorge Miranda | BZ79: Juan Carlos Gimenez | CH79: Hector Daniel Techeira | DI79: Alexis Jose Brito Vizcaino
A80: 45782 | B80: Carlos Gustavo Zabala | C80: Alexis Jose Brito Vizcaino | D80: Yeferson Angel Gay | E80: Cesar Nixon Velasco Zerpa | F80: Angel Daniel Castillo | G80: Diego Jose Garcia Garcia | H80: Luis Raul Marquez Araujo | J80: Vanina Leonor Lezcano | K80: Carlos Elias Guevara Garanton | L80: Diego German Rodriguez | M80: Carlos Villanueva | N80: Miguel Antonio Akouri Samra | O80: Sergio Luis Prado | P80: Daniel Oscar Aguirre | Q80: Fabricio Sebastian Castillo | R80: Claudio Omar Cobas | S80: Sebastian Leandro Toconas | T80: Eduardo Gabriel Olea | U80: Anibal Rafael Cabrera Paredes | V80: Matias Alejandro Romero | W80: Selso Sanchez | X80: Diego Marcelo Diaz | Y80: Daniel Eduardo FuentesTovar | Z80: Pablo Ceferino Gonzalez | AA80: Gilberto Miguel Federico Aguirre Viloria | AB80: Aquilino Romero Velazquez | AC80: Yovertt Daniel Herrera Zamora | AD80: Abel Mario Martinez | AE80: Derek Daniel Almeida Santander | AF80: Henry Alexander Robles Molina | AG80: Julio David Muñoz Garcia | AH80: Fernando Di Pietro | AI80: Luis Miguel Prato Ceballo | AJ80: Esteban Del Barco | AK80: qh Carlos Alberto Gonzalez | AL80: Victor Emanuel Piris | AM80: Fernando Ariel Lopez | AN80: Dionicio Ruiz Diaz | AO80: Damian Jorge Abalo Prelat | AP80: Jose Miguel Camacho Fernandez | AQ80: Ezequiel Adrian Marelli | AR80: Mauro Gabriel Allosa | AS80: Luis Eduardo Anselmi | AU80: Jackson Jose Sosa Garcia | AV80: Rommer Leandro Cordero Hernandez | AW80: Lautaro Ezequiel Scarpitti | AY80: Sergio Gustavo Barrios | BG80: Emiliano Rodrigo Perez | BN80: Carlos Maximiliano Lopez Nuñez | BP80: Alberto Fausto Cillo | BS80: Hernan Martin D'Avanzo | BU80: Fabricio Damian Fernandez Lattianzi | BW80: Cristian Jorge Miranda | BZ80: Juan Carlos Gimenez | CH80: Hector Daniel Techeira | CN80: Patricia Lorena Correa | CO80: Gonzalo Matias Enrique Ruiz | CP80: Carla Lorena Coll | DI80: Alexis Jose Brito Vizcaino
A81: 45783 | B81: Carlos Gustavo Zabala | C81: Alexis Jose Brito Vizcaino | D81: Yeferson Angel Gay | E81: Cesar Nixon Velasco Zerpa | F81: Angel Daniel Castillo | G81: Diego Jose Garcia Garcia | H81: Luis Raul Marquez Araujo | J81: Vanina Leonor Lezcano | K81: Carlos Elias Guevara Garanton | L81: Diego German Rodriguez | M81: Carlos Villanueva | N81: Miguel Antonio Akouri Samra | O81: Sergio Luis Prado | P81: Daniel Oscar Aguirre | Q81: Fabricio Sebastian Castillo | R81: Claudio Omar Cobas | S81: Sebastian Leandro Toconas | T81: Eduardo Gabriel Olea | U81: Anibal Rafael Cabrera Paredes | V81: Matias Alejandro Romero | W81: Selso Sanchez | X81: Diego Marcelo Diaz | Y81: Daniel Eduardo FuentesTovar | AA81: Gilberto Miguel Federico Aguirre Viloria | AB81: Aquilino Romero Velazquez | AC81: Yovertt Daniel Herrera Zamora | AD81: Abel Mario Martinez | AE81: Derek Daniel Almeida Santander | AF81: Henry Alexander Robles Molina | AG81: Julio David Muñoz Garcia | AH81: Fernando Di Pietro | AI81: Luis Miguel Prato Ceballo | AJ81: Esteban Del Barco | AK81: qh Carlos Alberto Gonzalez | AL81: Victor Emanuel Piris | AM81: Fernando Ariel Lopez | AN81: Dionicio Ruiz Diaz | AO81: Damian Jorge Abalo Prelat | AP81: Jose Miguel Camacho Fernandez | AQ81: Ezequiel Adrian Marelli | AR81: Mauro Gabriel Allosa | AS81: Luis Eduardo Anselmi | AU81: Jackson Jose Sosa Garcia | AV81: Rommer Leandro Cordero Hernandez | AW81: Lautaro Ezequiel Scarpitti | AY81: Sergio Gustavo Barrios | BG81: Emiliano Rodrigo Perez | BN81: Carlos Maximiliano Lopez Nuñez | BP81: Alberto Fausto Cillo | BS81: Hernan Martin D'Avanzo | BU81: Fabricio Damian Fernandez Lattianzi | BW81: Cristian Jorge Miranda | BZ81: Juan Carlos Gimenez | CH81: Hector Daniel Techeira | CK81: Pablo Ceferino Gonzalez | CN81: Patricia Lorena Correa | CO81: Gonzalo Matias Enrique Ruiz | CP81: Carla Lorena Coll | DI81: Alexis Jose Brito Vizcaino
A82: 45784 | B82: Carlos Gustavo Zabala | C82: Alexis Jose Brito Vizcaino | D82: Yeferson Angel Gay | E82: Cesar Nixon Velasco Zerpa | F82: Angel Daniel Castillo | G82: Diego Jose Garcia Garcia | H82: Luis Raul Marquez Araujo | J82: Vanina Leonor Lezcano | K82: Carlos Elias Guevara Garanton | L82: Diego German Rodriguez | M82: Carlos Villanueva | N82: Miguel Antonio Akouri Samra | O82: Sergio Luis Prado | P82: Daniel Oscar Aguirre | Q82: Fabricio Sebastian Castillo | R82: Claudio Omar Cobas | S82: Sebastian Leandro Toconas | T82: Eduardo Gabriel Olea | U82: Anibal Rafael Cabrera Paredes | V82: Matias Alejandro Romero | W82: Selso Sanchez | X82: Diego Marcelo Diaz | Y82: Daniel Eduardo FuentesTovar | AA82: Gilberto Miguel Federico Aguirre Viloria | AB82: Aquilino Romero Velazquez | AC82: Yovertt Daniel Herrera Zamora | AD82: Abel Mario Martinez | AE82: Derek Daniel Almeida Santander | AF82: Henry Alexander Robles Molina | AG82: Julio David Muñoz Garcia | AH82: Fernando Di Pietro | AI82: Luis Miguel Prato Ceballo | AJ82: Esteban Del Barco | AK82: qh Carlos Alberto Gonzalez | AL82: Victor Emanuel Piris | AM82: Fernando Ariel Lopez | AN82: Dionicio Ruiz Diaz | AO82: Damian Jorge Abalo Prelat | AP82: Jose Miguel Camacho Fernandez | AQ82: Ezequiel Adrian Marelli | AR82: Mauro Gabriel Allosa | AS82: Luis Eduardo Anselmi | AU82: Jackson Jose Sosa Garcia | AV82: Rommer Leandro Cordero Hernandez | AW82: Lautaro Ezequiel Scarpitti | AX82: GIAMA | AY82: Sergio Gustavo Barrios | BB82: Juan Pablo Allende | BG82: Emiliano Rodrigo Perez | BH82: Osvaldo Daniel Villafañe | BN82: Carlos Maximiliano Lopez Nuñez | BP82: Alberto Fausto Cillo | BS82: Hernan Martin D'Avanzo | BU82: Fabricio Damian Fernandez Lattianzi | BW82: Cristian Jorge Miranda | BY82: Miguel Andres garro | BZ82: Juan Carlos Gimenez | CA82: Norma Graciela Stoppello | CH82: Hector Daniel Techeira | CK82: Pablo Ceferino Gonzalez | CN82: Patricia Lorena Correa | CO82: Gonzalo Matias Enrique Ruiz | CP82: Carla Lorena Coll | CR82: Alejandro Cesar Forin | DI82: Alexis Jose Brito Vizcaino
A83: 45785 | B83: Carlos Gustavo Zabala | C83: Alexis Jose Brito Vizcaino | D83: Yeferson Angel Gay | E83: Cesar Nixon Velasco Zerpa | F83: Angel Daniel Castillo | G83: Diego Jose Garcia Garcia | H83: Luis Raul Marquez Araujo | J83: Vanina Leonor Lezcano | K83: Carlos Elias Guevara Garanton | L83: Diego German Rodriguez | M83: Carlos Villanueva | N83: Miguel Antonio Akouri Samra | O83: Sergio Luis Prado | P83: Daniel Oscar Aguirre | Q83: Fabricio Sebastian Castillo | R83: Claudio Omar Cobas | S83: Sebastian Leandro Toconas | T83: Eduardo Gabriel Olea | U83: Anibal Rafael Cabrera Paredes | V83: Matias Alejandro Romero | W83: Selso Sanchez | X83: Diego Marcelo Diaz | Y83: Daniel Eduardo FuentesTovar | AA83: Gilberto Miguel Federico Aguirre Viloria | AB83: Aquilino Romero Velazquez | AC83: Yovertt Daniel Herrera Zamora | AD83: Abel Mario Martinez | AE83: Derek Daniel Almeida Santander | AF83: Henry Alexander Robles Molina | AG83: Julio David Muñoz Garcia | AH83: Fernando Di Pietro | AI83: Luis Miguel Prato Ceballo | AJ83: Esteban Del Barco | AK83: qh Carlos Alberto Gonzalez | AL83: Victor Emanuel Piris | AM83: Fernando Ariel Lopez | AN83: Dionicio Ruiz Diaz | AO83: Damian Jorge Abalo Prelat | AP83: Jose Miguel Camacho Fernandez | AQ83: Ezequiel Adrian Marelli | AR83: Mauro Gabriel Allosa | AS83: Luis Eduardo Anselmi | AU83: Jackson Jose Sosa Garcia | AV83: Rommer Leandro Cordero Hernandez | AW83: Lautaro Ezequiel Scarpitti | AY83: Sergio Gustavo Barrios | AZ83: Margarita Angelica Luis | BB83: Juan Pablo Allende | BG83: Emiliano Rodrigo Perez | BH83: Osvaldo Daniel Villafañe | BN83: Carlos Maximiliano Lopez Nuñez | BP83: Alberto Fausto Cillo | BR83: Nestor Espindola | BS83: Hernan Martin D'Avanzo | BU83: Fabricio Damian Fernandez Lattianzi | BW83: Cristian Jorge Miranda | BY83: Miguel Andres garro | BZ83: Juan Carlos Gimenez | CA83: Norma Graciela Stoppello | CH83: Hector Daniel Techeira | CK83: Pablo Ceferino Gonzalez | CN83: Patricia Lorena Correa | CO83: Gonzalo Matias Enrique Ruiz | CP83: Carla Lorena Coll | CR83: Alejandro Cesar Forin | DI83: Alexis Jose Brito Vizcaino
A84: 45786 | B84: Carlos Gustavo Zabala | C84: Alexis Jose Brito Vizcaino | D84: Yeferson Angel Gay | E84: Cesar Nixon Velasco Zerpa | F84: Angel Daniel Castillo | G84: Diego Jose Garcia Garcia | H84: Luis Raul Marquez Araujo | J84: Vanina Leonor Lezcano | K84: Carlos Elias Guevara Garanton | L84: Diego German Rodriguez | M84: Carlos Villanueva | N84: Miguel Antonio Akouri Samra | O84: Sergio Luis Prado | P84: Daniel Oscar Aguirre | Q84: Fabricio Sebastian Castillo | R84: Claudio Omar Cobas | S84: Sebastian Leandro Toconas | T84: Eduardo Gabriel Olea | U84: Anibal Rafael Cabrera Paredes | V84: Matias Alejandro Romero | W84: Selso Sanchez | X84: Diego Marcelo Diaz | Y84: Daniel Eduardo FuentesTovar | AA84: Gilberto Miguel Federico Aguirre Viloria | AB84: Aquilino Romero Velazquez | AC84: Yovertt Daniel Herrera Zamora | AD84: Abel Mario Martinez | AE84: Derek Daniel Almeida Santander | AF84: Henry Alexander Robles Molina | AG84: Julio David Muñoz Garcia | AH84: Fernando Di Pietro | AI84: Luis Miguel Prato Ceballo | AJ84: Esteban Del Barco | AK84: qh Carlos Alberto Gonzalez | AL84: Victor Emanuel Piris | AM84: Fernando Ariel Lopez | AN84: Dionicio Ruiz Diaz | AO84: Damian Jorge Abalo Prelat | AP84: Jose Miguel Camacho Fernandez | AQ84: Ezequiel Adrian Marelli | AR84: Mauro Gabriel Allosa | AS84: Luis Eduardo Anselmi | AU84: Jackson Jose Sosa Garcia | AV84: Rommer Leandro Cordero Hernandez | AW84: Lautaro Ezequiel Scarpitti | AY84: Sergio Gustavo Barrios | AZ84: Margarita Angelica Luis | BB84: Juan Pablo Allende | BG84: Emiliano Rodrigo Perez | BH84: Osvaldo Daniel Villafañe | BN84: Carlos Maximiliano Lopez Nuñez | BO84: Fernando Ariel Barrientos | BP84: Alberto Fausto Cillo | BR84: Nestor Espindola | BS84: Hernan Martin D'Avanzo | BU84: Fabricio Damian Fernandez Lattianzi | BW84: Cristian Jorge Miranda | BY84: Miguel Andres garro | CA84: Norma Graciela Stoppello | CH84: Hector Daniel Techeira | CK84: Pablo Ceferino Gonzalez | CN84: Patricia Lorena Correa | CO84: Gonzalo Matias Enrique Ruiz | CP84: Carla Lorena Coll | CR84: Alejandro Cesar Forin | DI84: Alexis Jose Brito Vizcaino
A85: 45787 | B85: Carlos Gustavo Zabala | C85: Alexis Jose Brito Vizcaino | D85: Yeferson Angel Gay | E85: Cesar Nixon Velasco Zerpa | F85: Angel Daniel Castillo | G85: Diego Jose Garcia Garcia | H85: Luis Raul Marquez Araujo | J85: Vanina Leonor Lezcano | K85: Carlos Elias Guevara Garanton | L85: Diego German Rodriguez | M85: Carlos Villanueva | N85: Miguel Antonio Akouri Samra | O85: Sergio Luis Prado | P85: Daniel Oscar Aguirre | Q85: Fabricio Sebastian Castillo | R85: Claudio Omar Cobas | S85: Sebastian Leandro Toconas | T85: Eduardo Gabriel Olea | U85: Anibal Rafael Cabrera Paredes | V85: Matias Alejandro Romero | W85: Selso Sanchez | X85: Diego Marcelo Diaz | Y85: Daniel Eduardo FuentesTovar | AA85: Gilberto Miguel Federico Aguirre Viloria | AB85: Aquilino Romero Velazquez | AC85: Yovertt Daniel Herrera Zamora | AD85: Abel Mario Martinez | AE85: Derek Daniel Almeida Santander | AF85: Henry Alexander Robles Molina | AG85: Julio David Muñoz Garcia | AH85: Fernando Di Pietro | AI85: Luis Miguel Prato Ceballo | AJ85: Esteban Del Barco | AK85: qh Carlos Alberto Gonzalez | AL85: Victor Emanuel Piris | AM85: Fernando Ariel Lopez | AN85: Dionicio Ruiz Diaz | AO85: Damian Jorge Abalo Prelat | AP85: Jose Miguel Camacho Fernandez | AQ85: Ezequiel Adrian Marelli | AR85: Mauro Gabriel Allosa | AS85: Luis Eduardo Anselmi | AU85: Jackson Jose Sosa Garcia | AV85: Rommer Leandro Cordero Hernandez | AW85: Lautaro Ezequiel Scarpitti | AY85: Sergio Gustavo Barrios | AZ85: Margarita Angelica Luis | BB85: Juan Pablo Allende | BG85: Emiliano Rodrigo Perez | BH85: Osvaldo Daniel Villafañe | BN85: Carlos Maximiliano Lopez Nuñez | BO85: Fernando Ariel Barrientos | BP85: Alberto Fausto Cillo | BR85: Nestor Espindola | BS85: Hernan Martin D'Avanzo | BU85: Fabricio Damian Fernandez Lattianzi | BW85: Cristian Jorge Miranda | BY85: Miguel Andres garro | CA85: Norma Graciela Stoppello | CH85: Hector Daniel Techeira | CI85: Cesar Daniel Burgos | CK85: Pablo Ceferino Gonzalez | CN85: Patricia Lorena Correa | CO85: Gonzalo Matias Enrique Ruiz | CP85: Carla Lorena Coll | CR85: Alejandro Cesar Forin | DI85: Alexis Jose Brito Vizcaino
A86: 45788 | B86: Carlos Gustavo Zabala | C86: Alexis Jose Brito Vizcaino | D86: Yeferson Angel Gay | E86: Cesar Nixon Velasco Zerpa | F86: Angel Daniel Castillo | G86: Diego Jose Garcia Garcia | H86: Luis Raul Marquez Araujo | J86: Vanina Leonor Lezcano | K86: Carlos Elias Guevara Garanton | L86: Diego German Rodriguez | M86: Carlos Villanueva | N86: Miguel Antonio Akouri Samra | O86: Sergio Luis Prado | P86: Daniel Oscar Aguirre | Q86: Fabricio Sebastian Castillo | R86: Claudio Omar Cobas | S86: Sebastian Leandro Toconas | T86: Eduardo Gabriel Olea | U86: Anibal Rafael Cabrera Paredes | V86: Matias Alejandro Romero | W86: Selso Sanchez | X86: Diego Marcelo Diaz | Y86: Daniel Eduardo FuentesTovar | AA86: Gilberto Miguel Federico Aguirre Viloria | AB86: Aquilino Romero Velazquez | AC86: Yovertt Daniel Herrera Zamora | AD86: Abel Mario Martinez | AE86: Derek Daniel Almeida Santander | AF86: Henry Alexander Robles Molina | AG86: Julio David Muñoz Garcia | AH86: Fernando Di Pietro | AI86: Luis Miguel Prato Ceballo | AJ86: Esteban Del Barco | AK86: qh Carlos Alberto Gonzalez | AL86: Victor Emanuel Piris | AM86: Fernando Ariel Lopez | AN86: Dionicio Ruiz Diaz | AO86: Damian Jorge Abalo Prelat | AP86: Jose Miguel Camacho Fernandez | AQ86: Ezequiel Adrian Marelli | AR86: Mauro Gabriel Allosa | AS86: Luis Eduardo Anselmi | AU86: Jackson Jose Sosa Garcia | AV86: Rommer Leandro Cordero Hernandez | AW86: Lautaro Ezequiel Scarpitti | AY86: Sergio Gustavo Barrios | AZ86: Margarita Angelica Luis | BB86: Juan Pablo Allende | BG86: Emiliano Rodrigo Perez | BH86: Osvaldo Daniel Villafañe | BN86: Carlos Maximiliano Lopez Nuñez | BO86: Fernando Ariel Barrientos | BP86: Alberto Fausto Cillo | BR86: Nestor Espindola | BS86: Hernan Martin D'Avanzo | BU86: Fabricio Damian Fernandez Lattianzi | BW86: Cristian Jorge Miranda | BY86: Miguel Andres garro | CA86: Norma Graciela Stoppello | CH86: Hector Daniel Techeira | CI86: Cesar Daniel Burgos | CK86: Pablo Ceferino Gonzalez | CN86: Patricia Lorena Correa | CO86: Gonzalo Matias Enrique Ruiz | CP86: Carla Lorena Coll | CR86: Alejandro Cesar Forin | DI86: Alexis Jose Brito Vizcaino
A87: 45789 | B87: Carlos Gustavo Zabala | C87: Alexis Jose Brito Vizcaino | D87: Yeferson Angel Gay | E87: Cesar Nixon Velasco Zerpa | F87: Angel Daniel Castillo | G87: Diego Jose Garcia Garcia | H87: Luis Raul Marquez Araujo | J87: Vanina Leonor Lezcano | K87: Carlos Elias Guevara Garanton | L87: Diego German Rodriguez | M87: Carlos Villanueva | N87: Miguel Antonio Akouri Samra | O87: Sergio Luis Prado | P87: Daniel Oscar Aguirre | Q87: Fabricio Sebastian Castillo | R87: Claudio Omar Cobas | S87: Sebastian Leandro Toconas | T87: Eduardo Gabriel Olea | U87: Anibal Rafael Cabrera Paredes | V87: Matias Alejandro Romero | W87: Selso Sanchez | X87: Diego Marcelo Diaz | Y87: Daniel Eduardo FuentesTovar | AA87: Gilberto Miguel Federico Aguirre Viloria | AB87: Aquilino Romero Velazquez | AC87: Yovertt Daniel Herrera Zamora | AD87: Abel Mario Martinez | AE87: Derek Daniel Almeida Santander | AF87: Henry Alexander Robles Molina | AG87: Julio David Muñoz Garcia | AH87: Fernando Di Pietro | AI87: Luis Miguel Prato Ceballo | AJ87: Esteban Del Barco | AK87: qh Carlos Alberto Gonzalez | AL87: Victor Emanuel Piris | AM87: Fernando Ariel Lopez | AN87: Dionicio Ruiz Diaz | AO87: Damian Jorge Abalo Prelat | AP87: Jose Miguel Camacho Fernandez | AQ87: Ezequiel Adrian Marelli | AR87: Mauro Gabriel Allosa | AS87: Luis Eduardo Anselmi | AU87: Jackson Jose Sosa Garcia | AV87: Rommer Leandro Cordero Hernandez | AW87: Lautaro Ezequiel Scarpitti | AY87: Sergio Gustavo Barrios | AZ87: Margarita Angelica Luis | BB87: Juan Pablo Allende | BG87: Emiliano Rodrigo Perez | BH87: Osvaldo Daniel Villafañe | BN87: Carlos Maximiliano Lopez Nuñez | BO87: Fernando Ariel Barrientos | BP87: Alberto Fausto Cillo | BR87: Nestor Espindola | BS87: Hernan Martin D'Avanzo | BU87: Fabricio Damian Fernandez Lattianzi | BW87: Cristian Jorge Miranda | BY87: Miguel Andres garro | CA87: Norma Graciela Stoppello | CH87: Hector Daniel Techeira | CI87: Cesar Daniel Burgos | CK87: Pablo Ceferino Gonzalez | CN87: Patricia Lorena Correa | CO87: Gonzalo Matias Enrique Ruiz | CP87: Carla Lorena Coll | CR87: Alejandro Cesar Forin | DI87: Alexis Jose Brito Vizcaino
A88: 45790 | B88: Carlos Gustavo Zabala | C88: Alexis Jose Brito Vizcaino | D88: Yeferson Angel Gay | E88: Cesar Nixon Velasco Zerpa | F88: Angel Daniel Castillo | G88: Diego Jose Garcia Garcia | H88: Luis Raul Marquez Araujo | J88: Vanina Leonor Lezcano | K88: Carlos Elias Guevara Garanton | L88: Diego German Rodriguez | M88: Carlos Villanueva | N88: Miguel Antonio Akouri Samra | O88: Sergio Luis Prado | P88: Daniel Oscar Aguirre | Q88: Fabricio Sebastian Castillo | R88: Claudio Omar Cobas | S88: Sebastian Leandro Toconas | T88: Eduardo Gabriel Olea | U88: Anibal Rafael Cabrera Paredes | V88: Matias Alejandro Romero | W88: Selso Sanchez | X88: Diego Marcelo Diaz | Y88: Daniel Eduardo FuentesTovar | AA88: Gilberto Miguel Federico Aguirre Viloria | AB88: Aquilino Romero Velazquez | AC88: Yovertt Daniel Herrera Zamora | AD88: Abel Mario Martinez | AE88: Derek Daniel Almeida Santander | AF88: Henry Alexander Robles Molina | AG88: Julio David Muñoz Garcia | AH88: Fernando Di Pietro | AI88: Luis Miguel Prato Ceballo | AJ88: Esteban Del Barco | AK88: qh Carlos Alberto Gonzalez | AL88: Victor Emanuel Piris | AM88: Fernando Ariel Lopez | AN88: Dionicio Ruiz Diaz | AO88: Damian Jorge Abalo Prelat | AP88: Jose Miguel Camacho Fernandez | AQ88: Ezequiel Adrian Marelli | AR88: Mauro Gabriel Allosa | AS88: Luis Eduardo Anselmi | AU88: Jackson Jose Sosa Garcia | AV88: Rommer Leandro Cordero Hernandez | AW88: Lautaro Ezequiel Scarpitti | AY88: Sergio Gustavo Barrios | AZ88: Margarita Angelica Luis | BA88: Jonathan Jesus Colman | BB88: Juan Pablo Allende | BG88: Emiliano Rodrigo Perez | BH88: Osvaldo Daniel Villafañe | BN88: Carlos Maximiliano Lopez Nuñez | BO88: Fernando Ariel Barrientos | BP88: Alberto Fausto Cillo | BR88: Nestor Espindola | BS88: Hernan Martin D'Avanzo | BU88: Fabricio Damian Fernandez Lattianzi | BW88: Cristian Jorge Miranda | BX88: tg Carlos Alberto Gonzalez | BY88: Miguel Andres garro | CA88: Norma Graciela Stoppello | CH88: Hector Daniel Techeira | CI88: Cesar Daniel Burgos | CK88: Pablo Ceferino Gonzalez | CN88: Patricia Lorena Correa | CO88: Gonzalo Matias Enrique Ruiz | CP88: Carla Lorena Coll | CR88: Alejandro Cesar Forin | DI88: Alexis Jose Brito Vizcaino
A89: 45791 | B89: Carlos Gustavo Zabala | C89: Alexis Jose Brito Vizcaino | D89: Yeferson Angel Gay | E89: Cesar Nixon Velasco Zerpa | F89: Angel Daniel Castillo | G89: Diego Jose Garcia Garcia | H89: Luis Raul Marquez Araujo | J89: Vanina Leonor Lezcano | K89: Carlos Elias Guevara Garanton | L89: Diego German Rodriguez | M89: Carlos Villanueva | N89: Miguel Antonio Akouri Samra | O89: Sergio Luis Prado | P89: Daniel Oscar Aguirre | Q89: Fabricio Sebastian Castillo | R89: Claudio Omar Cobas | S89: Sebastian Leandro Toconas | T89: Eduardo Gabriel Olea | U89: Anibal Rafael Cabrera Paredes | V89: Matias Alejandro Romero | W89: Selso Sanchez | X89: Diego Marcelo Diaz | Y89: Daniel Eduardo FuentesTovar | AA89: Gilberto Miguel Federico Aguirre Viloria | AB89: Aquilino Romero Velazquez | AC89: Yovertt Daniel Herrera Zamora | AD89: Abel Mario Martinez | AE89: Derek Daniel Almeida Santander | AF89: Henry Alexander Robles Molina | AG89: Julio David Muñoz Garcia | AH89: Fernando Di Pietro | AI89: Luis Miguel Prato Ceballo | AJ89: Esteban Del Barco | AK89: qh Carlos Alberto Gonzalez | AL89: Victor Emanuel Piris | AM89: Fernando Ariel Lopez | AN89: Dionicio Ruiz Diaz | AO89: Damian Jorge Abalo Prelat | AP89: Jose Miguel Camacho Fernandez | AQ89: Ezequiel Adrian Marelli | AR89: Mauro Gabriel Allosa | AS89: Luis Eduardo Anselmi | AU89: Jackson Jose Sosa Garcia | AV89: Rommer Leandro Cordero Hernandez | AW89: Lautaro Ezequiel Scarpitti | AY89: Sergio Gustavo Barrios | AZ89: Margarita Angelica Luis | BA89: Jonathan Jesus Colman | BB89: Juan Pablo Allende | BC89: Fernando Rodriguez Carrillo | BG89: Emiliano Rodrigo Perez | BH89: Osvaldo Daniel Villafañe | BN89: Carlos Maximiliano Lopez Nuñez | BO89: Fernando Ariel Barrientos | BP89: Alberto Fausto Cillo | BQ89: Alberto Enrique Meneses | BR89: Nestor Espindola | BS89: Hernan Martin D'Avanzo | BU89: Fabricio Damian Fernandez Lattianzi | BW89: Cristian Jorge Miranda | BX89: tg Carlos Alberto Gonzalez | BY89: Miguel Andres garro | CA89: Norma Graciela Stoppello | CH89: Hector Daniel Techeira | CI89: Cesar Daniel Burgos | CK89: Pablo Ceferino Gonzalez | CN89: Patricia Lorena Correa | CO89: Gonzalo Matias Enrique Ruiz | CP89: Carla Lorena Coll | CR89: Alejandro Cesar Forin | DI89: Alexis Jose Brito Vizcaino
A90: 45792 | B90: Carlos Gustavo Zabala | C90: Alexis Jose Brito Vizcaino | D90: Yeferson Angel Gay | E90: Cesar Nixon Velasco Zerpa | F90: Angel Daniel Castillo | G90: Diego Jose Garcia Garcia | H90: Luis Raul Marquez Araujo | J90: Vanina Leonor Lezcano | K90: Carlos Elias Guevara Garanton | L90: Diego German Rodriguez | M90: Carlos Villanueva | N90: Miguel Antonio Akouri Samra | O90: Sergio Luis Prado | P90: Daniel Oscar Aguirre | Q90: Fabricio Sebastian Castillo | R90: Claudio Omar Cobas | S90: Sebastian Leandro Toconas | T90: Eduardo Gabriel Olea | U90: Anibal Rafael Cabrera Paredes | V90: Matias Alejandro Romero | W90: Selso Sanchez | X90: Diego Marcelo Diaz | Y90: Daniel Eduardo FuentesTovar | AA90: Gilberto Miguel Federico Aguirre Viloria | AB90: Aquilino Romero Velazquez | AC90: Yovertt Daniel Herrera Zamora | AD90: Abel Mario Martinez | AE90: Derek Daniel Almeida Santander | AF90: Henry Alexander Robles Molina | AG90: Julio David Muñoz Garcia | AH90: Fernando Di Pietro | AI90: Luis Miguel Prato Ceballo | AJ90: Esteban Del Barco | AK90: qh Carlos Alberto Gonzalez | AL90: Victor Emanuel Piris | AM90: Fernando Ariel Lopez | AN90: Dionicio Ruiz Diaz | AO90: Damian Jorge Abalo Prelat | AP90: Jose Miguel Camacho Fernandez | AQ90: Ezequiel Adrian Marelli | AR90: Mauro Gabriel Allosa | AS90: Luis Eduardo Anselmi | AU90: Jackson Jose Sosa Garcia | AV90: Rommer Leandro Cordero Hernandez | AW90: Lautaro Ezequiel Scarpitti | AY90: Sergio Gustavo Barrios | AZ90: Margarita Angelica Luis | BA90: Jonathan Jesus Colman | BB90: Juan Pablo Allende | BC90: Fernando Rodriguez Carrillo | BG90: Emiliano Rodrigo Perez | BH90: Osvaldo Daniel Villafañe | BN90: Carlos Maximiliano Lopez Nuñez | BO90: Fernando Ariel Barrientos | BP90: Alberto Fausto Cillo | BQ90: Alberto Enrique Meneses | BR90: Nestor Espindola | BS90: Hernan Martin D'Avanzo | BU90: Fabricio Damian Fernandez Lattianzi | BW90: Cristian Jorge Miranda | BX90: tg Carlos Alberto Gonzalez | BY90: Miguel Andres garro | CA90: Norma Graciela Stoppello | CH90: Hector Daniel Techeira | CI90: Cesar Daniel Burgos | CK90: Pablo Ceferino Gonzalez | CM90: Leandro Gabriel Gerez | CN90: Patricia Lorena Correa | CO90: Gonzalo Matias Enrique Ruiz | CP90: Carla Lorena Coll | CQ90: Gabriel Rodolfo Almeda | CR90: Alejandro Cesar Forin | DI90: Alexis Jose Brito Vizcaino
A91: 45793 | B91: Carlos Gustavo Zabala | C91: Alexis Jose Brito Vizcaino | D91: Yeferson Angel Gay | E91: Cesar Nixon Velasco Zerpa | F91: Angel Daniel Castillo | G91: Diego Jose Garcia Garcia | H91: Luis Raul Marquez Araujo | J91: Vanina Leonor Lezcano | K91: Carlos Elias Guevara Garanton | L91: Diego German Rodriguez | M91: Carlos Villanueva | N91: Miguel Antonio Akouri Samra | O91: Sergio Luis Prado | P91: Daniel Oscar Aguirre | Q91: Fabricio Sebastian Castillo | R91: Claudio Omar Cobas | S91: Sebastian Leandro Toconas | T91: Eduardo Gabriel Olea | U91: Anibal Rafael Cabrera Paredes | V91: Matias Alejandro Romero | W91: Selso Sanchez | X91: Diego Marcelo Diaz | Y91: Daniel Eduardo FuentesTovar | AA91: Hugo Cesar Fernandez Britez | AB91: Aquilino Romero Velazquez | AC91: Yovertt Daniel Herrera Zamora | AD91: Abel Mario Martinez | AE91: GIAMA | AF91: Henry Alexander Robles Molina | AG91: Julio David Muñoz Garcia | AH91: Fernando Di Pietro | AI91: Luis Miguel Prato Ceballo | AJ91: Esteban Del Barco | AK91: qh Carlos Alberto Gonzalez | AL91: Victor Emanuel Piris | AM91: Fernando Ariel Lopez | AN91: Dionicio Ruiz Diaz | AO91: Damian Jorge Abalo Prelat | AP91: Jose Miguel Camacho Fernandez | AQ91: Ezequiel Adrian Marelli | AR91: Mauro Gabriel Allosa | AS91: Luis Eduardo Anselmi | AU91: Jackson Jose Sosa Garcia | AV91: Rommer Leandro Cordero Hernandez | AW91: Lautaro Ezequiel Scarpitti | AY91: Sergio Gustavo Barrios | AZ91: Margarita Angelica Luis | BA91: Jonathan Jesus Colman | BB91: Juan Pablo Allende | BC91: Fernando Rodriguez Carrillo | BG91: Emiliano Rodrigo Perez | BH91: Osvaldo Daniel Villafañe | BN91: Carlos Maximiliano Lopez Nuñez | BO91: Fernando Ariel Barrientos | BP91: Alberto Fausto Cillo | BQ91: Alberto Enrique Meneses | BR91: Nestor Espindola | BS91: Hernan Martin D'Avanzo | BU91: Fabricio Damian Fernandez Lattianzi | BW91: Cristian Jorge Miranda | BX91: tg Carlos Alberto Gonzalez | BY91: Miguel Andres garro | CA91: Norma Graciela Stoppello | CH91: Hector Daniel Techeira | CI91: Cesar Daniel Burgos | CK91: Pablo Ceferino Gonzalez | CM91: Leandro Gabriel Gerez | CN91: Patricia Lorena Correa | CO91: Gonzalo Matias Enrique Ruiz | CP91: Carla Lorena Coll | CQ91: Gabriel Rodolfo Almeda | CR91: Alejandro Cesar Forin | DI91: Alexis Jose Brito Vizcaino
A92: 45794 | B92: Carlos Gustavo Zabala | C92: Alexis Jose Brito Vizcaino | D92: Yeferson Angel Gay | E92: Cesar Nixon Velasco Zerpa | F92: Angel Daniel Castillo | G92: Diego Jose Garcia Garcia | H92: Luis Raul Marquez Araujo | J92: Vanina Leonor Lezcano | K92: Carlos Elias Guevara Garanton | L92: Diego German Rodriguez | M92: Carlos Villanueva | N92: Miguel Antonio Akouri Samra | O92: Sergio Luis Prado | P92: Daniel Oscar Aguirre | Q92: Fabricio Sebastian Castillo | R92: Claudio Omar Cobas | S92: Sebastian Leandro Toconas | T92: Eduardo Gabriel Olea | U92: Anibal Rafael Cabrera Paredes | V92: Matias Alejandro Romero | W92: Selso Sanchez | X92: Diego Marcelo Diaz | Y92: Daniel Eduardo FuentesTovar | AA92: Hugo Cesar Fernandez Britez | AB92: Aquilino Romero Velazquez | AC92: Yovertt Daniel Herrera Zamora | AD92: Abel Mario Martinez | AF92: Henry Alexander Robles Molina | AG92: Julio David Muñoz Garcia | AH92: Fernando Di Pietro | AI92: Luis Miguel Prato Ceballo | AJ92: Esteban Del Barco | AK92: qh Carlos Alberto Gonzalez | AL92: Angel Gabriel Godan | AM92: Fernando Ariel Lopez | AN92: Dionicio Ruiz Diaz | AO92: Damian Jorge Abalo Prelat | AP92: Jose Miguel Camacho Fernandez | AQ92: Ezequiel Adrian Marelli | AR92: Mauro Gabriel Allosa | AS92: Luis Eduardo Anselmi | AU92: Jackson Jose Sosa Garcia | AV92: Rommer Leandro Cordero Hernandez | AW92: Lautaro Ezequiel Scarpitti | AY92: Sergio Gustavo Barrios | AZ92: Margarita Angelica Luis | BA92: Jonathan Jesus Colman | BB92: Juan Pablo Allende | BC92: Fernando Rodriguez Carrillo | BG92: Emiliano Rodrigo Perez | BH92: Osvaldo Daniel Villafañe | BN92: Carlos Maximiliano Lopez Nuñez | BO92: Fernando Ariel Barrientos | BP92: Alberto Fausto Cillo | BQ92: Alberto Enrique Meneses | BR92: Nestor Espindola | BS92: Hernan Martin D'Avanzo | BU92: Fabricio Damian Fernandez Lattianzi | BW92: Cristian Jorge Miranda | BX92: tg Carlos Alberto Gonzalez | BY92: Miguel Andres garro | CA92: Norma Graciela Stoppello | CH92: Hector Daniel Techeira | CI92: Cesar Daniel Burgos | CK92: Pablo Ceferino Gonzalez | CM92: Leandro Gabriel Gerez | CN92: Patricia Lorena Correa | CO92: Gonzalo Matias Enrique Ruiz | CP92: Carla Lorena Coll | CQ92: Gabriel Rodolfo Almeda | CR92: Alejandro Cesar Forin | DI92: Alexis Jose Brito Vizcaino
A93: 45795 | B93: Carlos Gustavo Zabala | C93: Alexis Jose Brito Vizcaino | D93: Yeferson Angel Gay | E93: Cesar Nixon Velasco Zerpa | F93: Angel Daniel Castillo | G93: Diego Jose Garcia Garcia | H93: Luis Raul Marquez Araujo | J93: Vanina Leonor Lezcano | K93: Carlos Elias Guevara Garanton | L93: Diego German Rodriguez | M93: Carlos Villanueva | N93: Miguel Antonio Akouri Samra | O93: Sergio Luis Prado | P93: Daniel Oscar Aguirre | Q93: Fabricio Sebastian Castillo | R93: Claudio Omar Cobas | S93: Sebastian Leandro Toconas | T93: Eduardo Gabriel Olea | U93: Anibal Rafael Cabrera Paredes | V93: Matias Alejandro Romero | W93: Selso Sanchez | X93: Diego Marcelo Diaz | Y93: Daniel Eduardo FuentesTovar | AA93: Hugo Cesar Fernandez Britez | AB93: Aquilino Romero Velazquez | AC93: Yovertt Daniel Herrera Zamora | AD93: Abel Mario Martinez | AF93: Henry Alexander Robles Molina | AG93: Julio David Muñoz Garcia | AH93: Fernando Di Pietro | AI93: Luis Miguel Prato Ceballo | AJ93: Esteban Del Barco | AK93: qh Carlos Alberto Gonzalez | AL93: Angel Gabriel Godan | AM93: Fernando Ariel Lopez | AN93: Dionicio Ruiz Diaz | AO93: Damian Jorge Abalo Prelat | AP93: Jose Miguel Camacho Fernandez | AQ93: Ezequiel Adrian Marelli | AR93: Mauro Gabriel Allosa | AS93: Luis Eduardo Anselmi | AU93: Jackson Jose Sosa Garcia | AV93: Rommer Leandro Cordero Hernandez | AW93: Lautaro Ezequiel Scarpitti | AY93: Sergio Gustavo Barrios | AZ93: Margarita Angelica Luis | BA93: Jonathan Jesus Colman | BB93: Juan Pablo Allende | BC93: Fernando Rodriguez Carrillo | BG93: Emiliano Rodrigo Perez | BH93: Osvaldo Daniel Villafañe | BN93: Carlos Maximiliano Lopez Nuñez | BO93: Fernando Ariel Barrientos | BP93: Alberto Fausto Cillo | BQ93: Alberto Enrique Meneses | BR93: Nestor Espindola | BS93: Hernan Martin D'Avanzo | BU93: Fabricio Damian Fernandez Lattianzi | BW93: Cristian Jorge Miranda | BX93: tg Carlos Alberto Gonzalez | BY93: Miguel Andres garro | CA93: Norma Graciela Stoppello | CH93: Hector Daniel Techeira | CI93: Cesar Daniel Burgos | CK93: Pablo Ceferino Gonzalez | CM93: Leandro Gabriel Gerez | CN93: Patricia Lorena Correa | CO93: Gonzalo Matias Enrique Ruiz | CP93: Carla Lorena Coll | CQ93: Gabriel Rodolfo Almeda | CR93: Alejandro Cesar Forin | DI93: Alexis Jose Brito Vizcaino
A94: 45796 | B94: Carlos Gustavo Zabala | C94: Alexis Jose Brito Vizcaino | D94: Yeferson Angel Gay | E94: Cesar Nixon Velasco Zerpa | F94: Angel Daniel Castillo | G94: Diego Jose Garcia Garcia | H94: Luis Raul Marquez Araujo | J94: Vanina Leonor Lezcano | K94: Carlos Elias Guevara Garanton | L94: Diego German Rodriguez | M94: Carlos Villanueva | N94: Miguel Antonio Akouri Samra | O94: Sergio Luis Prado | P94: Daniel Oscar Aguirre | Q94: Fabricio Sebastian Castillo | R94: Claudio Omar Cobas | S94: Sebastian Leandro Toconas | T94: Eduardo Gabriel Olea | U94: Anibal Rafael Cabrera Paredes | V94: Matias Alejandro Romero | W94: Selso Sanchez | X94: Diego Marcelo Diaz | Y94: Daniel Eduardo FuentesTovar | AA94: Hugo Cesar Fernandez Britez | AB94: Aquilino Romero Velazquez | AC94: Yovertt Daniel Herrera Zamora | AD94: Abel Mario Martinez | AE94: Anibal Rafael Cabrera Paredes | AF94: Henry Alexander Robles Molina | AG94: Julio David Muñoz Garcia | AH94: Fernando Di Pietro | AI94: Luis Miguel Prato Ceballo | AJ94: Esteban Del Barco | AK94: qh Carlos Alberto Gonzalez | AL94: Angel Gabriel Godan | AM94: Fernando Ariel Lopez | AN94: Dionicio Ruiz Diaz | AO94: Damian Jorge Abalo Prelat | AP94: Jose Miguel Camacho Fernandez | AQ94: Ezequiel Adrian Marelli | AR94: Mauro Gabriel Allosa | AS94: Luis Eduardo Anselmi | AU94: Jackson Jose Sosa Garcia | AV94: Rommer Leandro Cordero Hernandez | AW94: Lautaro Ezequiel Scarpitti | AY94: Sergio Gustavo Barrios | AZ94: Margarita Angelica Luis | BA94: Jonathan Jesus Colman | BB94: Juan Pablo Allende | BC94: Fernando Rodriguez Carrillo | BF94: Francisco Javier Niño Canino | BG94: Emiliano Rodrigo Perez | BH94: Osvaldo Daniel Villafañe | BN94: Carlos Maximiliano Lopez Nuñez | BO94: Fernando Ariel Barrientos | BP94: Alberto Fausto Cillo | BQ94: Alberto Enrique Meneses | BR94: Nestor Espindola | BS94: Hernan Martin D'Avanzo | BU94: Fabricio Damian Fernandez Lattianzi | BW94: Cristian Jorge Miranda | BX94: tg Carlos Alberto Gonzalez | BY94: Miguel Andres garro | CA94: Norma Graciela Stoppello | CH94: Hector Daniel Techeira | CI94: Cesar Daniel Burgos | CK94: Pablo Ceferino Gonzalez | CM94: Leandro Gabriel Gerez | CN94: Patricia Lorena Correa | CO94: Gonzalo Matias Enrique Ruiz | CP94: Carla Lorena Coll | CQ94: Gabriel Rodolfo Almeda | CR94: Alejandro Cesar Forin | CS94: Rosana Leonor Arrua | DI94: Alexis Jose Brito Vizcaino
A95: 45797 | B95: Carlos Gustavo Zabala | C95: Alexis Jose Brito Vizcaino | D95: Yeferson Angel Gay | E95: Cesar Nixon Velasco Zerpa | F95: Angel Daniel Castillo | G95: Diego Jose Garcia Garcia | H95: Luis Raul Marquez Araujo | J95: Vanina Leonor Lezcano | K95: Carlos Elias Guevara Garanton | L95: Diego German Rodriguez | M95: Carlos Villanueva | N95: Miguel Antonio Akouri Samra | O95: Sergio Luis Prado | P95: Daniel Oscar Aguirre | Q95: Fabricio Sebastian Castillo | R95: Claudio Omar Cobas | S95: Sebastian Leandro Toconas | T95: Eduardo Gabriel Olea | V95: Matias Alejandro Romero | W95: Selso Sanchez | X95: Diego Marcelo Diaz | Y95: Daniel Eduardo FuentesTovar | AA95: Hugo Cesar Fernandez Britez | AB95: Aquilino Romero Velazquez | AC95: Yovertt Daniel Herrera Zamora | AD95: Abel Mario Martinez | AE95: Anibal Rafael Cabrera Paredes | AF95: Henry Alexander Robles Molina | AG95: Julio David Muñoz Garcia | AH95: Fernando Di Pietro | AI95: Luis Miguel Prato Ceballo | AJ95: Esteban Del Barco | AK95: qh Carlos Alberto Gonzalez | AL95: Angel Gabriel Godan | AM95: Fernando Ariel Lopez | AN95: Dionicio Ruiz Diaz | AO95: Damian Jorge Abalo Prelat | AP95: Jose Miguel Camacho Fernandez | AQ95: Ezequiel Adrian Marelli | AR95: Mauro Gabriel Allosa | AS95: Luis Eduardo Anselmi | AU95: Jackson Jose Sosa Garcia | AV95: Rommer Leandro Cordero Hernandez | AW95: Lautaro Ezequiel Scarpitti | AY95: Sergio Gustavo Barrios | AZ95: Margarita Angelica Luis | BA95: Jonathan Jesus Colman | BB95: Juan Pablo Allende | BC95: Fernando Rodriguez Carrillo | BF95: Francisco Javier Niño Canino | BG95: Emiliano Rodrigo Perez | BH95: Osvaldo Daniel Villafañe | BL95: Victor Hugo Liendro | BN95: Carlos Maximiliano Lopez Nuñez | BO95: Fernando Ariel Barrientos | BP95: Alberto Fausto Cillo | BQ95: Alberto Enrique Meneses | BR95: Nestor Espindola | BS95: Hernan Martin D'Avanzo | BU95: Fabricio Damian Fernandez Lattianzi | BW95: Cristian Jorge Miranda | BX95: tg Carlos Alberto Gonzalez | BY95: Miguel Andres garro | CA95: Norma Graciela Stoppello | CH95: Hector Daniel Techeira | CI95: Cesar Daniel Burgos | CK95: Pablo Ceferino Gonzalez | CM95: Leandro Gabriel Gerez | CN95: Patricia Lorena Correa | CO95: Gonzalo Matias Enrique Ruiz | CP95: Carla Lorena Coll | CQ95: Gabriel Rodolfo Almeda | CR95: Alejandro Cesar Forin | CS95: Rosana Leonor Arrua | DI95: Alexis Jose Brito Vizcaino
A96: 45798 | B96: Carlos Gustavo Zabala | C96: Alexis Jose Brito Vizcaino | D96: Yeferson Angel Gay | E96: Cesar Nixon Velasco Zerpa | F96: Angel Daniel Castillo | G96: Diego Jose Garcia Garcia | H96: Luis Raul Marquez Araujo | J96: Vanina Leonor Lezcano | K96: Carlos Elias Guevara Garanton | L96: Diego German Rodriguez | M96: Carlos Villanueva | N96: Miguel Antonio Akouri Samra | O96: Sergio Luis Prado | P96: Daniel Oscar Aguirre | Q96: Fabricio Sebastian Castillo | R96: Claudio Omar Cobas | S96: Sebastian Leandro Toconas | T96: Eduardo Gabriel Olea | V96: Matias Alejandro Romero | W96: Selso Sanchez | X96: Diego Marcelo Diaz | Y96: Daniel Eduardo FuentesTovar | AA96: Hugo Cesar Fernandez Britez | AB96: Aquilino Romero Velazquez | AC96: Yovertt Daniel Herrera Zamora | AD96: Abel Mario Martinez | AE96: Anibal Rafael Cabrera Paredes | AF96: Henry Alexander Robles Molina | AG96: Julio David Muñoz Garcia | AH96: Fernando Di Pietro | AI96: Luis Miguel Prato Ceballo | AJ96: Esteban Del Barco | AK96: qh Carlos Alberto Gonzalez | AL96: Angel Gabriel Godan | AM96: Fernando Ariel Lopez | AN96: Dionicio Ruiz Diaz | AO96: Damian Jorge Abalo Prelat | AP96: Jose Miguel Camacho Fernandez | AQ96: Ezequiel Adrian Marelli | AR96: Mauro Gabriel Allosa | AS96: Luis Eduardo Anselmi | AT96: Cesar Gabriel Muzzopappa | AU96: Jackson Jose Sosa Garcia | AV96: Rommer Leandro Cordero Hernandez | AW96: Lautaro Ezequiel Scarpitti | AY96: Sergio Gustavo Barrios | AZ96: Margarita Angelica Luis | BA96: Jonathan Jesus Colman | BB96: Juan Pablo Allende | BC96: Fernando Rodriguez Carrillo | BF96: Francisco Javier Niño Canino | BG96: Emiliano Rodrigo Perez | BH96: Osvaldo Daniel Villafañe | BI96: Mauro Elias Arguello | BK96: Yeshid Eddy Espejo Pilco | BL96: Victor Hugo Liendro | BN96: Carlos Maximiliano Lopez Nuñez | BO96: Fernando Ariel Barrientos | BP96: Alberto Fausto Cillo | BQ96: Alberto Enrique Meneses | BR96: Nestor Espindola | BS96: Hernan Martin D'Avanzo | BU96: Fabricio Damian Fernandez Lattianzi | BW96: Cristian Jorge Miranda | BX96: tg Carlos Alberto Gonzalez | BY96: Miguel Andres garro | CA96: Norma Graciela Stoppello | CE96: Paola Gabriela Garces Barres | CH96: Hector Daniel Techeira | CI96: Cesar Daniel Burgos | CK96: Pablo Ceferino Gonzalez | CM96: Leandro Gabriel Gerez | CN96: Patricia Lorena Correa | CO96: Gonzalo Matias Enrique Ruiz | CP96: Carla Lorena Coll | CQ96: Gabriel Rodolfo Almeda | CR96: Alejandro Cesar Forin | CS96: Rosana Leonor Arrua | DI96: Alexis Jose Brito Vizcaino
A97: 45799 | B97: Carlos Gustavo Zabala | C97: Alexis Jose Brito Vizcaino | D97: Yeferson Angel Gay | E97: Cesar Nixon Velasco Zerpa | F97: Angel Daniel Castillo | G97: Diego Jose Garcia Garcia | H97: Luis Raul Marquez Araujo | J97: Vanina Leonor Lezcano | K97: Carlos Elias Guevara Garanton | L97: Diego German Rodriguez | M97: Carlos Villanueva | N97: Miguel Antonio Akouri Samra | O97: Juan Pablo Vergez | P97: Daniel Oscar Aguirre | Q97: Fabricio Sebastian Castillo | R97: Claudio Omar Cobas | S97: Sebastian Leandro Toconas | T97: Eduardo Gabriel Olea | V97: Matias Alejandro Romero | W97: Selso Sanchez | X97: Diego Marcelo Diaz | Y97: Daniel Eduardo FuentesTovar | AA97: Hugo Cesar Fernandez Britez | AB97: Aquilino Romero Velazquez | AC97: Yovertt Daniel Herrera Zamora | AD97: Abel Mario Martinez | AE97: Anibal Rafael Cabrera Paredes | AF97: Henry Alexander Robles Molina | AG97: Julio David Muñoz Garcia | AH97: Fernando Di Pietro | AI97: Luis Miguel Prato Ceballo | AJ97: Esteban Del Barco | AK97: qh Carlos Alberto Gonzalez | AL97: Angel Gabriel Godan | AM97: Fernando Ariel Lopez | AN97: Dionicio Ruiz Diaz | AO97: Damian Jorge Abalo Prelat | AP97: Jose Miguel Camacho Fernandez | AQ97: Ezequiel Adrian Marelli | AR97: Mauro Gabriel Allosa | AS97: Luis Eduardo Anselmi | AT97: Cesar Gabriel Muzzopappa | AU97: Jackson Jose Sosa Garcia | AV97: Rommer Leandro Cordero Hernandez | AW97: Lautaro Ezequiel Scarpitti | AY97: Sergio Gustavo Barrios | AZ97: Margarita Angelica Luis | BA97: Jonathan Jesus Colman | BB97: Juan Pablo Allende | BC97: Fernando Rodriguez Carrillo | BF97: Francisco Javier Niño Canino | BG97: Emiliano Rodrigo Perez | BH97: Osvaldo Daniel Villafañe | BI97: Mauro Elias Arguello | BK97: Yeshid Eddy Espejo Pilco | BL97: Victor Hugo Liendro | BN97: Carlos Maximiliano Lopez Nuñez | BO97: Fernando Ariel Barrientos | BP97: Alberto Fausto Cillo | BQ97: Alberto Enrique Meneses | BS97: Hernan Martin D'Avanzo | BU97: Fabricio Damian Fernandez Lattianzi | BW97: Cristian Jorge Miranda | BX97: tg Carlos Alberto Gonzalez | BY97: Miguel Andres garro | BZ97: Nestor Espindola | CA97: Norma Graciela Stoppello | CE97: Paola Gabriela Garces Barres | CH97: Hector Daniel Techeira | CI97: Cesar Daniel Burgos | CK97: Pablo Ceferino Gonzalez | CM97: Leandro Gabriel Gerez | CN97: Patricia Lorena Correa | CO97: Gonzalo Matias Enrique Ruiz | CP97: Carla Lorena Coll | CQ97: Gabriel Rodolfo Almeda | CR97: Alejandro Cesar Forin | CS97: Rosana Leonor Arrua | DI97: Alexis Jose Brito Vizcaino
A98: 45800 | B98: Carlos Gustavo Zabala | C98: Alexis Jose Brito Vizcaino | D98: Yeferson Angel Gay | E98: Cesar Nixon Velasco Zerpa | F98: Angel Daniel Castillo | G98: Diego Jose Garcia Garcia | H98: Luis Raul Marquez Araujo | J98: Vanina Leonor Lezcano | K98: Carlos Elias Guevara Garanton | L98: Diego German Rodriguez | M98: Carlos Villanueva | N98: Miguel Antonio Akouri Samra | O98: Juan Pablo Vergez | P98: Daniel Oscar Aguirre | Q98: Fabricio Sebastian Castillo | R98: Claudio Omar Cobas | S98: Sebastian Leandro Toconas | T98: Eduardo Gabriel Olea | V98: Matias Alejandro Romero | W98: Selso Sanchez | X98: Diego Marcelo Diaz | Y98: Daniel Eduardo FuentesTovar | AA98: Hugo Cesar Fernandez Britez | AB98: Aquilino Romero Velazquez | AC98: Yovertt Daniel Herrera Zamora | AD98: Abel Mario Martinez | AE98: Anibal Rafael Cabrera Paredes | AF98: Henry Alexander Robles Molina | AG98: Julio David Muñoz Garcia | AH98: Fernando Di Pietro | AI98: Luis Miguel Prato Ceballo | AJ98: Esteban Del Barco | AK98: qh Carlos Alberto Gonzalez | AL98: Angel Gabriel Godan | AM98: Fernando Ariel Lopez | AN98: Dionicio Ruiz Diaz | AO98: Damian Jorge Abalo Prelat | AP98: Jose Miguel Camacho Fernandez | AQ98: Ezequiel Adrian Marelli | AR98: Mauro Gabriel Allosa | AS98: Luis Eduardo Anselmi | AT98: Cesar Gabriel Muzzopappa | AU98: Jackson Jose Sosa Garcia | AV98: Rommer Leandro Cordero Hernandez | AW98: Lautaro Ezequiel Scarpitti | AY98: Sergio Gustavo Barrios | AZ98: Margarita Angelica Luis | BA98: Jonathan Jesus Colman | BB98: Juan Pablo Allende | BC98: Fernando Rodriguez Carrillo | BF98: Francisco Javier Niño Canino | BG98: Emiliano Rodrigo Perez | BH98: Osvaldo Daniel Villafañe | BI98: Mauro Elias Arguello | BJ98: Lorena Graciela Palacios Elias | BK98: Yeshid Eddy Espejo Pilco | BL98: Victor Hugo Liendro | BN98: Carlos Maximiliano Lopez Nuñez | BO98: Fernando Ariel Barrientos | BP98: Alberto Fausto Cillo | BQ98: Alberto Enrique Meneses | BS98: Hernan Martin D'Avanzo | BU98: Fabricio Damian Fernandez Lattianzi | BW98: Cristian Jorge Miranda | BX98: tg Carlos Alberto Gonzalez | BY98: Miguel Andres garro | BZ98: Nestor Espindola | CA98: Norma Graciela Stoppello | CE98: Paola Gabriela Garces Barres | CG98: Ricardo Javier Coria | CH98: Hector Daniel Techeira | CI98: Cesar Daniel Burgos | CK98: Pablo Ceferino Gonzalez | CM98: Leandro Gabriel Gerez | CN98: Patricia Lorena Correa | CO98: Gonzalo Matias Enrique Ruiz | CP98: Carla Lorena Coll | CQ98: Gabriel Rodolfo Almeda | CR98: Alejandro Cesar Forin | CS98: Rosana Leonor Arrua | CU98: Gustavo Ariel Duarte | CV98: Martin Ismael Drago | DI98: Alexis Jose Brito Vizcaino
A99: 45801 | B99: Carlos Gustavo Zabala | C99: Alexis Jose Brito Vizcaino | D99: Yeferson Angel Gay | E99: Cesar Nixon Velasco Zerpa | F99: Angel Daniel Castillo | G99: Diego Jose Garcia Garcia | J99: Vanina Leonor Lezcano | K99: Carlos Elias Guevara Garanton | L99: Diego German Rodriguez | M99: Carlos Villanueva | N99: Miguel Antonio Akouri Samra | O99: Juan Pablo Vergez | P99: Daniel Oscar Aguirre | Q99: Fabricio Sebastian Castillo | R99: Claudio Omar Cobas | S99: Sebastian Leandro Toconas | T99: Eduardo Gabriel Olea | V99: Matias Alejandro Romero | W99: Selso Sanchez | X99: Diego Marcelo Diaz | Y99: Daniel Eduardo FuentesTovar | AA99: Hugo Cesar Fernandez Britez | AB99: Aquilino Romero Velazquez | AC99: Yovertt Daniel Herrera Zamora | AD99: Abel Mario Martinez | AE99: Anibal Rafael Cabrera Paredes | AF99: Henry Alexander Robles Molina | AG99: Julio David Muñoz Garcia | AH99: Fernando Di Pietro | AI99: Luis Miguel Prato Ceballo | AJ99: Esteban Del Barco | AK99: qh Carlos Alberto Gonzalez | AL99: Angel Gabriel Godan | AM99: Fernando Ariel Lopez | AN99: Dionicio Ruiz Diaz | AO99: Damian Jorge Abalo Prelat | AP99: Jose Miguel Camacho Fernandez | AQ99: Ezequiel Adrian Marelli | AR99: Mauro Gabriel Allosa | AS99: Luis Eduardo Anselmi | AT99: Cesar Gabriel Muzzopappa | AU99: Jackson Jose Sosa Garcia | AV99: Rommer Leandro Cordero Hernandez | AW99: Lautaro Ezequiel Scarpitti | AY99: Sergio Gustavo Barrios | AZ99: Margarita Angelica Luis | BA99: Jonathan Jesus Colman | BB99: Juan Pablo Allende | BC99: Fernando Rodriguez Carrillo | BF99: Francisco Javier Niño Canino | BG99: Emiliano Rodrigo Perez | BH99: Osvaldo Daniel Villafañe | BI99: Mauro Elias Arguello | BJ99: Lorena Graciela Palacios Elias | BK99: Yeshid Eddy Espejo Pilco | BL99: Victor Hugo Liendro | BN99: Carlos Maximiliano Lopez Nuñez | BO99: Fernando Ariel Barrientos | BP99: Alberto Fausto Cillo | BQ99: Alberto Enrique Meneses | BS99: Hernan Martin D'Avanzo | BU99: Fabricio Damian Fernandez Lattianzi | BW99: Cristian Jorge Miranda | BX99: tg Carlos Alberto Gonzalez | BY99: Miguel Andres garro | BZ99: Nestor Espindola | CA99: Norma Graciela Stoppello | CE99: Paola Gabriela Garces Barres | CG99: Ricardo Javier Coria | CH99: Hector Daniel Techeira | CI99: Cesar Daniel Burgos | CK99: Pablo Ceferino Gonzalez | CM99: Leandro Gabriel Gerez | CN99: Patricia Lorena Correa | CO99: Gonzalo Matias Enrique Ruiz | CP99: Carla Lorena Coll | CQ99: Gabriel Rodolfo Almeda | CR99: Alejandro Cesar Forin | CS99: Rosana Leonor Arrua | CU99: Gustavo Ariel Duarte | CV99: Martin Ismael Drago | DI99: Alexis Jose Brito Vizcaino
A100: 45802 | B100: Carlos Gustavo Zabala | C100: Alexis Jose Brito Vizcaino | D100: Yeferson Angel Gay | E100: Cesar Nixon Velasco Zerpa | F100: Angel Daniel Castillo | G100: Diego Jose Garcia Garcia | J100: Vanina Leonor Lezcano | K100: Carlos Elias Guevara Garanton | L100: Diego German Rodriguez | M100: Carlos Villanueva | N100: Miguel Antonio Akouri Samra | O100: Juan Pablo Vergez | P100: Daniel Oscar Aguirre | Q100: Fabricio Sebastian Castillo | R100: Claudio Omar Cobas | S100: Sebastian Leandro Toconas | T100: Eduardo Gabriel Olea | V100: Matias Alejandro Romero | W100: Selso Sanchez | X100: Diego Marcelo Diaz | Y100: Daniel Eduardo FuentesTovar | AA100: Hugo Cesar Fernandez Britez | AB100: Aquilino Romero Velazquez | AC100: Yovertt Daniel Herrera Zamora | AD100: Abel Mario Martinez | AE100: Anibal Rafael Cabrera Paredes | AF100: Henry Alexander Robles Molina | AG100: Julio David Muñoz Garcia | AH100: Fernando Di Pietro | AI100: Luis Miguel Prato Ceballo | AJ100: Esteban Del Barco | AK100: qh Carlos Alberto Gonzalez | AL100: Angel Gabriel Godan | AM100: Fernando Ariel Lopez | AN100: Dionicio Ruiz Diaz | AO100: Damian Jorge Abalo Prelat | AP100: Jose Miguel Camacho Fernandez | AQ100: Ezequiel Adrian Marelli | AR100: Mauro Gabriel Allosa | AS100: Luis Eduardo Anselmi | AT100: Cesar Gabriel Muzzopappa | AU100: Jackson Jose Sosa Garcia | AV100: Rommer Leandro Cordero Hernandez | AW100: Lautaro Ezequiel Scarpitti | AY100: Sergio Gustavo Barrios | AZ100: Margarita Angelica Luis | BA100: Jonathan Jesus Colman | BB100: Juan Pablo Allende | BC100: Fernando Rodriguez Carrillo | BF100: Francisco Javier Niño Canino | BG100: Emiliano Rodrigo Perez | BH100: Osvaldo Daniel Villafañe | BI100: Mauro Elias Arguello | BJ100: Lorena Graciela Palacios Elias | BK100: Yeshid Eddy Espejo Pilco | BL100: Victor Hugo Liendro | BN100: Carlos Maximiliano Lopez Nuñez | BO100: Fernando Ariel Barrientos | BP100: Alberto Fausto Cillo | BQ100: Alberto Enrique Meneses | BS100: Hernan Martin D'Avanzo | BU100: Fabricio Damian Fernandez Lattianzi | BW100: Cristian Jorge Miranda | BX100: tg Carlos Alberto Gonzalez | BY100: Miguel Andres garro | BZ100: Nestor Espindola | CA100: Norma Graciela Stoppello | CE100: Paola Gabriela Garces Barres | CG100: Ricardo Javier Coria | CH100: Hector Daniel Techeira | CI100: Cesar Daniel Burgos | CJ100: Luis Raul Marquez Araujo | CK100: Pablo Ceferino Gonzalez | CM100: Leandro Gabriel Gerez | CN100: Patricia Lorena Correa | CO100: Gonzalo Matias Enrique Ruiz | CP100: Carla Lorena Coll | CQ100: Gabriel Rodolfo Almeda | CR100: Alejandro Cesar Forin | CS100: Rosana Leonor Arrua | CU100: Gustavo Ariel Duarte | CV100: Martin Ismael Drago | DI100: Alexis Jose Brito Vizcaino
A101: 45803 | B101: Carlos Gustavo Zabala | C101: Alexis Jose Brito Vizcaino | D101: Yeferson Angel Gay | E101: Cesar Nixon Velasco Zerpa | F101: Angel Daniel Castillo | G101: Diego Jose Garcia Garcia | J101: Vanina Leonor Lezcano | K101: Carlos Elias Guevara Garanton | L101: Diego German Rodriguez | M101: Carlos Villanueva | N101: Miguel Antonio Akouri Samra | O101: Juan Pablo Vergez | P101: Daniel Oscar Aguirre | Q101: Fabricio Sebastian Castillo | R101: Claudio Omar Cobas | S101: Sebastian Leandro Toconas | T101: Eduardo Gabriel Olea | V101: Matias Alejandro Romero | W101: Selso Sanchez | X101: Diego Marcelo Diaz | Y101: Daniel Eduardo FuentesTovar | AA101: Hugo Cesar Fernandez Britez | AB101: Aquilino Romero Velazquez | AC101: Yovertt Daniel Herrera Zamora | AD101: Abel Mario Martinez | AE101: Anibal Rafael Cabrera Paredes | AF101: Henry Alexander Robles Molina | AG101: Julio David Muñoz Garcia | AH101: Fernando Di Pietro | AI101: Luis Miguel Prato Ceballo | AJ101: Esteban Del Barco | AK101: qh Carlos Alberto Gonzalez | AL101: Angel Gabriel Godan | AM101: Fernando Ariel Lopez | AN101: Dionicio Ruiz Diaz | AO101: Damian Jorge Abalo Prelat | AP101: Jose Miguel Camacho Fernandez | AQ101: Ezequiel Adrian Marelli | AR101: Mauro Gabriel Allosa | AS101: Luis Eduardo Anselmi | AT101: Cesar Gabriel Muzzopappa | AU101: Jackson Jose Sosa Garcia | AV101: Rommer Leandro Cordero Hernandez | AW101: Lautaro Ezequiel Scarpitti | AY101: Sergio Gustavo Barrios | AZ101: Margarita Angelica Luis | BA101: Jonathan Jesus Colman | BB101: Juan Pablo Allende | BC101: Fernando Rodriguez Carrillo | BF101: Francisco Javier Niño Canino | BG101: Emiliano Rodrigo Perez | BH101: Osvaldo Daniel Villafañe | BI101: Mauro Elias Arguello | BJ101: Lorena Graciela Palacios Elias | BK101: Yeshid Eddy Espejo Pilco | BL101: Victor Hugo Liendro | BN101: Carlos Maximiliano Lopez Nuñez | BO101: Fernando Ariel Barrientos | BP101: Alberto Fausto Cillo | BQ101: Alberto Enrique Meneses | BS101: Hernan Martin D'Avanzo | BU101: Fabricio Damian Fernandez Lattianzi | BW101: Cristian Jorge Miranda | BX101: tg Carlos Alberto Gonzalez | BY101: Miguel Andres garro | BZ101: Nestor Espindola | CA101: Norma Graciela Stoppello | CE101: Paola Gabriela Garces Barres | CG101: Ricardo Javier Coria | CH101: Hector Daniel Techeira | CI101: Cesar Daniel Burgos | CJ101: Luis Raul Marquez Araujo | CK101: Pablo Ceferino Gonzalez | CM101: Leandro Gabriel Gerez | CN101: Patricia Lorena Correa | CO101: Gonzalo Matias Enrique Ruiz | CP101: Carla Lorena Coll | CQ101: Gabriel Rodolfo Almeda | CR101: Alejandro Cesar Forin | CS101: Rosana Leonor Arrua | CT101: Jhon Jaime Rangel Botina | CU101: Gustavo Ariel Duarte | CV101: Martin Ismael Drago | DI101: Alexis Jose Brito Vizcaino
A102: 45804 | B102: Carlos Gustavo Zabala | C102: Alexis Jose Brito Vizcaino | D102: Yeferson Angel Gay | E102: Cesar Nixon Velasco Zerpa | F102: Angel Daniel Castillo | G102: Diego Jose Garcia Garcia | J102: Vanina Leonor Lezcano | K102: Carlos Elias Guevara Garanton | L102: Diego German Rodriguez | M102: Carlos Villanueva | N102: Miguel Antonio Akouri Samra | O102: Juan Pablo Vergez | P102: Daniel Oscar Aguirre | Q102: Fabricio Sebastian Castillo | R102: Claudio Omar Cobas | S102: Sebastian Leandro Toconas | T102: Eduardo Gabriel Olea | V102: Matias Alejandro Romero | W102: Selso Sanchez | X102: Diego Marcelo Diaz | Y102: Daniel Eduardo FuentesTovar | AA102: Hugo Cesar Fernandez Britez | AB102: Aquilino Romero Velazquez | AC102: Yovertt Daniel Herrera Zamora | AD102: Abel Mario Martinez | AE102: Anibal Rafael Cabrera Paredes | AF102: Henry Alexander Robles Molina | AG102: Julio David Muñoz Garcia | AH102: Fernando Di Pietro | AI102: Luis Miguel Prato Ceballo | AJ102: Esteban Del Barco | AK102: qh Carlos Alberto Gonzalez | AL102: Angel Gabriel Godan | AM102: Fernando Ariel Lopez | AN102: Dionicio Ruiz Diaz | AO102: Damian Jorge Abalo Prelat | AP102: Jose Miguel Camacho Fernandez | AQ102: Ezequiel Adrian Marelli | AR102: Mauro Gabriel Allosa | AS102: Luis Eduardo Anselmi | AT102: Cesar Gabriel Muzzopappa | AU102: Jackson Jose Sosa Garcia | AV102: Rommer Leandro Cordero Hernandez | AW102: Lautaro Ezequiel Scarpitti | AY102: Sergio Gustavo Barrios | AZ102: Margarita Angelica Luis | BA102: Jonathan Jesus Colman | BB102: Juan Pablo Allende | BC102: Fernando Rodriguez Carrillo | BF102: Francisco Javier Niño Canino | BG102: Emiliano Rodrigo Perez | BH102: Santiago Joel Balderrama | BI102: Mauro Elias Arguello | BJ102: Lorena Graciela Palacios Elias | BL102: Victor Hugo Liendro | BN102: Carlos Maximiliano Lopez Nuñez | BO102: Fernando Ariel Barrientos | BP102: Alberto Fausto Cillo | BQ102: Alberto Enrique Meneses | BS102: Hernan Martin D'Avanzo | BU102: Fabricio Damian Fernandez Lattianzi | BW102: Cristian Jorge Miranda | BX102: tg Carlos Alberto Gonzalez | BY102: Miguel Andres garro | BZ102: Nestor Espindola | CA102: Norma Graciela Stoppello | CE102: Paola Gabriela Garces Barres | CG102: Ricardo Javier Coria | CH102: Hector Daniel Techeira | CI102: Cesar Daniel Burgos | CJ102: Luis Raul Marquez Araujo | CK102: Pablo Ceferino Gonzalez | CM102: Leandro Gabriel Gerez | CN102: Patricia Lorena Correa | CO102: Gonzalo Matias Enrique Ruiz | CP102: Carla Lorena Coll | CQ102: Gabriel Rodolfo Almeda | CR102: Alejandro Cesar Forin | CS102: Rosana Leonor Arrua | CT102: Jhon Jaime Rangel Botina | CU102: Gustavo Ariel Duarte | CV102: Martin Ismael Drago | DI102: Alexis Jose Brito Vizcaino
A103: 45805 | B103: Carlos Gustavo Zabala | C103: Alexis Jose Brito Vizcaino | D103: Yeferson Angel Gay | E103: Cesar Nixon Velasco Zerpa | F103: Angel Daniel Castillo | G103: Diego Jose Garcia Garcia | J103: Vanina Leonor Lezcano | K103: Carlos Elias Guevara Garanton | L103: Diego German Rodriguez | M103: Carlos Villanueva | N103: Miguel Antonio Akouri Samra | O103: Juan Pablo Vergez | P103: Daniel Oscar Aguirre | Q103: Fabricio Sebastian Castillo | R103: Claudio Omar Cobas | S103: Sebastian Leandro Toconas | T103: Eduardo Gabriel Olea | V103: Matias Alejandro Romero | W103: Selso Sanchez | X103: Diego Marcelo Diaz | Y103: Daniel Eduardo FuentesTovar | AA103: Hugo Cesar Fernandez Britez | AB103: Aquilino Romero Velazquez | AC103: Yovertt Daniel Herrera Zamora | AD103: Abel Mario Martinez | AE103: Anibal Rafael Cabrera Paredes | AF103: Henry Alexander Robles Molina | AG103: Julio David Muñoz Garcia | AH103: Fernando Di Pietro | AI103: Luis Miguel Prato Ceballo | AJ103: Esteban Del Barco | AK103: qh Carlos Alberto Gonzalez | AL103: Angel Gabriel Godan | AM103: Fernando Ariel Lopez | AN103: Leonardo Enrique Rosillo Loyo | AO103: Damian Jorge Abalo Prelat | AP103: Jose Miguel Camacho Fernandez | AQ103: Ezequiel Adrian Marelli | AR103: Mauro Gabriel Allosa | AS103: Luis Eduardo Anselmi | AT103: Cesar Gabriel Muzzopappa | AU103: Jackson Jose Sosa Garcia | AV103: Rommer Leandro Cordero Hernandez | AW103: Lautaro Ezequiel Scarpitti | AY103: Sergio Gustavo Barrios | AZ103: Margarita Angelica Luis | BA103: Jonathan Jesus Colman | BB103: Juan Pablo Allende | BC103: Fernando Rodriguez Carrillo | BF103: Francisco Javier Niño Canino | BG103: Emiliano Rodrigo Perez | BH103: Santiago Joel Balderrama | BI103: Mauro Elias Arguello | BJ103: Lorena Graciela Palacios Elias | BL103: Victor Hugo Liendro | BN103: Carlos Maximiliano Lopez Nuñez | BO103: Fernando Ariel Barrientos | BP103: Alberto Fausto Cillo | BQ103: Alberto Enrique Meneses | BS103: Hernan Martin D'Avanzo | BU103: Fabricio Damian Fernandez Lattianzi | BW103: Cristian Jorge Miranda | BX103: tg Carlos Alberto Gonzalez | BY103: Miguel Andres garro | BZ103: Nestor Espindola | CA103: Norma Graciela Stoppello | CE103: Paola Gabriela Garces Barres | CG103: Ricardo Javier Coria | CH103: Hector Daniel Techeira | CI103: Cesar Daniel Burgos | CJ103: Luis Raul Marquez Araujo | CK103: Pablo Ceferino Gonzalez | CM103: Leandro Gabriel Gerez | CN103: Patricia Lorena Correa | CO103: Gonzalo Matias Enrique Ruiz | CP103: Carla Lorena Coll | CQ103: Gabriel Rodolfo Almeda | CR103: Alejandro Cesar Forin | CS103: Rosana Leonor Arrua | CT103: Jhon Jaime Rangel Botina | CU103: Gustavo Ariel Duarte | CV103: Martin Ismael Drago | DI103: Alexis Jose Brito Vizcaino
...

Sheet Fc x Alq
A1: Fecha | B1: N° Asiento | C1: Debe | D1: Haber | E1: Saldo | F1: Concepto | G1: T. Comprobante | H1: Comprobante N°
A2: Cuenta: 410101 - Ingreso por alquileres
A3: 46099 | B3: 16270 | C3: 0 | D3: 371900.83 | E3: -1.1811231e+09 | F3: Factura B Nº 00002-00001336 - mauro leonardo gonzalez | H3: 0000200001336
A4: 46106 | B4: 16581 | C4: 0 | D4: 53128.93 | E4: -1.2106522e+09 | F4: Factura B Nº 00002-00001368 - SERGIO ARIEL LAZO | H4: 0000200001368
A5: 46106 | B5: 16575 | C5: 0 | D5: 371900.83 | E5: -1.2105991e+09 | F5: Factura B Nº 00002-00001367 - Ricardo Javier Coria | H5: 0000200001367
A6: 46106 | B6: 16571 | C6: 0 | D6: 106257.85 | E6: -1.2102272e+09 | F6: Factura B Nº 00002-00001366 - Eduardo David Baez | H6: 0000200001366
A7: 46106 | B7: 16474 | C7: 0 | D7: 371900.83 | E7: -1.2100678e+09 | F7: Factura B Nº 00002-00001365 - Walter Lujan Testori | H7: 0000200001365
A8: 46106 | B8: 16464 | C8: 0 | D8: 371900.83 | E8: -1.2089521e+09 | F8: Factura B Nº 00002-00001364 - Hector Marcelo Rodriguez | H8: 0000200001364
A9: 46106 | B9: 16462 | C9: 0 | D9: 371900.83 | E9: -1.2085802e+09 | F9: Factura B Nº 00002-00001363 - Sergio Omar Romero | H9: 0000200001363
A10: 46106 | B10: 16460 | C10: 0 | D10: 371900.83 | E10: -1.2082083e+09 | F10: Factura B Nº 00002-00001362 - Juan Pablo Vergez | H10: 0000200001362
A11: 46106 | B11: 16458 | C11: 0 | D11: 371900.83 | E11: -1.2078364e+09 | F11: Factura B Nº 00002-00001361 - carina sandra pastorino | H11: 0000200001361
A12: 46106 | B12: 16456 | C12: 0 | D12: 371900.83 | E12: -1.2074645e+09 | F12: Factura B Nº 00002-00001360 - Vanina Leonor Lezcano | H12: 0000200001360
A13: 46106 | B13: 16452 | C13: 0 | D13: 371900.83 | E13: -1.2067207e+09 | F13: Factura B Nº 00002-00001359 - Jorge Eduardo Sayavedra | H13: 0000200001359
A14: 46106 | B14: 16450 | C14: 0 | D14: 371900.83 | E14: -1.2063488e+09 | F14: Factura B Nº 00002-00001358 - Diego Rafael Minuet | H14: 0000200001358
... A87: 46106 | B87: 16307 | C87: 0 | D87: 371900.83 | E87: -1.1825471e+09 | F87: Factura A Nº 00002-00002022 - Mariana Elizabeth Tolosa | H87: 0000200002022
A88: 46106 | B88: 16391 | C88: 0 | D88: 371900.83 | E88: -1.1966793e+09 | F88: Alquiler - BALCAZA - desde: 25/03/2026 hasta: 31/03/2026 Dominio: AH252TE CUIT/CUIL: 20302024821 - FACTURA: 3710
A89: 46107 | B89: 16612 | C89: 0 | D89: 319008.26 | E89: -1.2082682e+09 | F89: Factura A Nº 00002-00002081 - Luis Raul Dionisio Laureano | H89: 0000200002081
A90: 46107 | B90: 16520 | C90: 371900.83 | D90: 0 | E90: -1.2079492e+09 | F90: Anulación de factura 3710 | G90: ASD | H90: 0000000016520
A91: 46113 | B91: 17406 | C91: 314049.59 | D91: 0 | E91: -1.239136e+09 | F91: N. Crédito B Nº 00002-00000056 - Florencia Carbone | G91: ASD | H91: 0000200000056
A92: 46113 | B92: 17366 | C92: 371900.83 | D92: 0 | E92: -1.2391312e+09 | F92: N. Crédito B Nº 00002-00000054 - Alexis Jose Brito Vizcaino | G92: ASD | H92: 0000200000054
A93: 46113 | B93: 17697 | C93: 371900.83 | D93: 0 | E93: -1.2390781e+09 | F93: N. Crédito A Nº 00002-00000097 - walter ismael castillo | G93: ASD | H93: 0000200000097
A94: 46113 | B94: 17380 | C94: 371900.83 | D94: 0 | E94: -1.2390781e+09 | F94: N. Crédito A Nº 00002-00000095 - Martin Nacher | G94: ASD | H94: 0000200000095
A95: 46113 | B95: 17407 | C95: 0 | D95: 314049.59 | E95: -1.23945e+09 | F95: Factura B Nº 00002-00001401 - Florencia Carbone | H95: 0000200001401
A96: 46113 | B96: 17367 | C96: 0 | D96: 318771.9 | E96: -1.23945e+09 | F96: Factura B Nº 00002-00001398 - Alexis Jose Brito Vizcaino | H96: 0000200001398
A97: 46113 | B97: 17004 | C97: 0 | D97: 314049.59 | E97: -1.2383343e+09 | F97: Factura B Nº 00002-00001397 - Florencia Carbone | H97: 0000200001397
A98: 46113 | B98: 16991 | C98: 0 | D98: 371900.83 | E98: -1.2376484e+09 | F98: Factura B Nº 00002-00001396 - Maximiliano Alberto Videla | H98: 0000200001396
A99: 46113 | B99: 16979 | C99: 0 | D99: 371900.83 | E99: -1.2361608e+09 | F99: Factura B Nº 00002-00001395 - Hector Marcelo Rodriguez | H99: 0000200001395
A100: 46113 | B100: 16977 | C100: 0 | D100: 371900.83 | E100: -1.2357889e+09 | F100: Factura B Nº 00002-00001394 - Sergio Omar Romero | H100: 0000200001394
A101: 46113 | B101: 16975 | C101: 0 | D101: 371900.83 | E101: -1.235417e+09 | F101: Factura B Nº 00002-00001393 - Juan Pablo Vergez | H101: 0000200001393
A102: 46113 | B102: 16972 | C102: 0 | D102: 371900.83 | E102: -1.2350451e+09 | F102: Factura B Nº 00002-00001392 - Vanina Leonor Lezcano | H102: 0000200001392
A103: 46113 | B103: 16966 | C103: 0 | D103: 371900.83 | E103: -1.2343013e+09 | F103: Factura B Nº 00002-00001391 - Jorge Eduardo Sayavedra | H103: 0000200001391
A104: 46113 | B104: 16964 | C104: 0 | D104: 371900.83 | E104: -1.2339294e+09 | F104: Factura B Nº 00002-00001390 - Diego Rafael Minuet | H104: 0000200001390
A105: 46113 | B105: 16946 | C105: 0 | D105: 371900.83 | E105: -1.2313261e+09 | F105: Factura B Nº 00002-00001389 - CRISTIAN ALBERTO RUS | H105: 0000200001389
A106: 46113 | B106: 16942 | C106: 0 | D106: 371900.83 | E106: -1.2305822e+09 | F106: Factura B Nº 00002-00001388 - Alexis Jose Brito Vizcaino | H106: 0000200001388
... A177: 46113 | B177: 16818 | C177: 0 | D177: 371900.83 | E177: -1.2112434e+09 | F177: Factura A Nº 00002-00002096 - Mariana Elizabeth Tolosa | H177: 0000200002096
A178: 46113 | B178: 16853 | C178: 0 | D178: 371900.83 | E178: -1.2171938e+09 | F178: Alquiler - CANO DE LEON - desde: 01/04/2026 hasta: 07/04/2026 Dominio: AH087VS CUIT/CUIL: 20962637311 - FACTURA: 3806
A179: 46113 | B179: 17724 | C179: 0 | D179: 1925000 | E179: -1.2410031e+09 | F179: Alquiler - - desde: 01/04/2026 hasta: 30/04/2026 Dominio: AH991GB CUIT/CUIL: 30718086228 - FACTURA: 3973
A180: 46118 | B180: 17378 | C180: 0 | D180: 265642.98 | E180: -1.2412156e+09 | F180: Factura A Nº 00002-00002157 - SEBASTIAN FORTI | H180: 0000200002157
A181: 46118 | B181: 17171 | C181: 371900.83 | D181: 0 | E181: -1.2406312e+09 | F181: Anulación de factura 3806 | G181: ASD | H181: 0000000017171
A182: 46118 | B182: 17200 | C182: 0 | D182: 318771.9 | E182: -1.24095e+09 | F182: Alquiler - FORTI - desde: 02-04-2026 hasta: 07-04-2026 CUIT/CUIL: 20270837981- ASIENTO: 17200
A183: 46120 | B183: 17762 | C183: 371900.83 | D183: 0 | E183: -1.2676205e+09 | F183: N. Crédito A Nº 00002-00000098 - Roberto cesar Pagliuca valeria | G183: ASD | H183: 0000200000098
A184: 46120 | B184: 17592 | C184: 0 | D184: 371900.83 | E184: -1.2660266e+09 | F184: Factura B Nº 00002-00001426 - Hector Marcelo Rodriguez | H184: 0000200001426
A185: 46120 | B185: 17590 | C185: 0 | D185: 371900.83 | E185: -1.2656547e+09 | F185: Factura B Nº 00002-00001425 - Sergio Omar Romero | H185: 0000200001425
A186: 46120 | B186: 17586 | C186: 0 | D186: 371900.83 | E186: -1.2652828e+09 | F186: Factura B Nº 00002-00001424 - Juan Pablo Vergez | H186: 0000200001424
A187: 46120 | B187: 17584 | C187: 0 | D187: 371900.83 | E187: -1.2649109e+09 | F187: Factura B Nº 00002-00001423 - Vanina Leonor Lezcano | H187: 0000200001423
A188: 46120 | B188: 17578 | C188: 0 | D188: 371900.83 | E188: -1.2637952e+09 | F188: Factura B Nº 00002-00001422 - Jorge Eduardo Sayavedra | H188: 0000200001422
A189: 46120 | B189: 17576 | C189: 0 | D189: 371900.83 | E189: -1.2634233e+09 | F189: Factura B Nº 00002-00001421 - Diego Rafael Minuet | H189: 0000200001421
A190: 46120 | B190: 17568 | C190: 0 | D190: 371900.83 | E190: -1.2619357e+09 | F190: Factura B Nº 00002-00001420 - Miguel Antonio Castro Aponte | H190: 0000200001420
A191: 46120 | B191: 17559 | C191: 0 | D191: 371900.83 | E191: -1.2604481e+09 | F191: Factura B Nº 00002-00001419 - CRISTIAN ALBERTO RUS | H191: 0000200001419
A192: 46120 | B192: 17551 | C192: 0 | D192: 371900.83 | E192: -1.2597043e+09 | F192: Factura B Nº 00002-00001418 - Fernando Augusto Carlos Zacarias Fernandez | H192: 0000200001418
A193: 46120 | B193: 17549 | C193: 0 | D193: 371900.83 | E193: -1.2593324e+09 | F193: Factura B Nº 00002-00001417 - Eduardo Javier Escobar | H193: 0000200001417
A194: 46120 | B194: 17547 | C194: 0 | D194: 371900.83 | E194: -1.2589605e+09 | F194: Factura B Nº 00002-00001416 - Walter Lujan Testori | H194: 0000200001416
A195: 46120 | B195: 17545 | C195: 0 | D195: 371900.83 | E195: -1.2585886e+09 | F195: Factura B Nº 00002-00001415 - Ramon jaimes jaimes | H195: 0000200001415
... A259: 46120 | B259: 17416 | C259: 0 | D259: 371900.83 | E259: -1.2412688e+09 | F259: Factura A Nº 00002-00002160 - Rodrigo Roberto Cussi Rueda | H259: 0000200002160
A260: 46120 | B260: 17377 | C260: 318771.9 | D260: 0 | E260: -1.2408969e+09 | F260: Anulación de factura 3872 | G260: ASD | H260: 0000000017377
A261: 46120 | B261: 17529 | C261: 0 | D261: 212396.69 | E261: -1.257101e+09 | F261: Alquiler - Ramirez - desde: 08/04/2026 hasta: 12/04/2026 Dominio: AH502KD CUIT/CUIL: 20370846813 - FACTURA: 3937
A262: 46121 | B262: 17531 | C262: 212396.69 | D262: 0 | E262: -1.2674081e+09 | F262: Anulación de factura 3937 | G262: ASD | H262: 0000000017531
A263: 46121 | B263: 17495 | C263: 371900.83 | D263: 0 | E263: -1.2676205e+09 | F263: Anulación de factura 3920 | G263: ASD | H263: 0000000017495
A264: 46121 | B264: 17493 | C264: 0 | D264: 371900.83 | E264: -1.2679924e+09 | F264: Alquiler - Pereyra - desde: 08/04/2026 hasta: 14/04/2026 Dominio: AH252TE CUIT/CUIL: 20254352889 - FACTURA: 3920
A265: 46122 | B265: 17764 | C265: 0 | D265: 159385.95 | E265: -1.2678331e+09 | F265: Factura A Nº 00002-00002215 - Roberto cesar Pagliuca valeria | H265: 0000200002215
A266: 46122 | B266: 17714 | C266: 0 | D266: 265642.98 | E266: -1267673719 | F266: Factura A Nº 00002-00002214 - Rolando Antonio Bustos Cavieres | H266: 0000200002214
A267: 46122 | B267: 17726 | C267: 1925000 | D267: 0 | E267: -1265748719 | F267: Anulación de factura 3973 | G267: ASD | H267: 0000000017726
A268: 46125 | B268: 17770 | C268: 0 | D268: 371900.83 | E268: -1.268205e+09 | F268: Factura A Nº 00002-00002216 - FLORENCIA MAILEN RUIZ | H268: 0000200002216
A269: 46126 | B269: 17802 | C269: 0 | D269: 371900.83 | E269: -1.2685769e+09 | F269: Factura A Nº 00002-00002217 - EZEQUIEL SOUZA REY | H269: 0000200002217
A270: 46127 | B270: 18112 | C270: 371900.83 | D270: 0 | E270: -1.2949819e+09 | F270: N. Crédito A Nº 00002-00000099 - Martin Nacher | G270: ASD | H270: 0000200000099
A271: 46127 | B271: 18013 | C271: 0 | D271: 319008.26 | E271: -1.2953538e+09 | F271: Factura B Nº 00002-00001450 - Sergio Omar Romero | H271: 0000200001450
A272: 46127 | B272: 17968 | C272: 0 | D272: 371900.83 | E272: -1.2932281e+09 | F272: Factura B Nº 00002-00001449 - Hector Marcelo Rodriguez | H272: 0000200001449
A273: 46127 | B273: 17965 | C273: 0 | D273: 52892.56 | E273: -1.2928562e+09 | F273: Factura B Nº 00002-00001448 - Sergio Omar Romero | H273: 0000200001448
A274: 46127 | B274: 17963 | C274: 0 | D274: 371900.83 | E274: -1.2928034e+09 | F274: Factura B Nº 00002-00001447 - Juan Pablo Vergez | H274: 0000200001447
A275: 46127 | B275: 17961 | C275: 0 | D275: 371900.83 | E275: -1.2924315e+09 | F275: Factura B Nº 00002-00001446 - Vanina Leonor Lezcano | H275: 0000200001446
A276: 46127 | B276: 17952 | C276: 0 | D276: 319008.26 | E276: -1.2913157e+09 | F276: Factura B Nº 00002-00001445 - Jorge Eduardo Sayavedra | H276: 0000200001445
A277: 46127 | B277: 17950 | C277: 0 | D277: 52892.56 | E277: -1.2909967e+09 | F277: Factura B Nº 00002-00001444 - Jorge Eduardo Sayavedra | H277: 0000200001444
A278: 46127 | B278: 17948 | C278: 0 | D278: 371900.83 | E278: -1.2909438e+09 | F278: Factura B Nº 00002-00001443 - Diego Rafael Minuet | H278: 0000200001443
A279: 46127 | B279: 17940 | C279: 0 | D279: 371900.83 | E279: -1.2894562e+09 | F279: Factura B Nº 00002-00001442 - Miguel Antonio Castro Aponte | H279: 0000200001442
A280: 46127 | B280: 17931 | C280: 0 | D280: 371900.83 | E280: -1.2879686e+09 | F280: Factura B Nº 00002-00001441 - CRISTIAN ALBERTO RUS | H280: 0000200001441
A281: 46127 | B281: 17927 | C281: 0 | D281: 371900.83 | E281: -1.2872248e+09 | F281: Factura B Nº 00002-00001440 - Fernando Augusto Carlos Zacarias Fernandez | H281: 0000200001440
A282: 46127 | B282: 17925 | C282: 0 | D282: 371900.83 | E282: -1.2868529e+09 | F282: Factura B Nº 00002-00001439 - Eduardo Javier Escobar | H282: 0000200001439
... A353: 46132 | B353: 18216 | C353: 0 | D353: 371900.83 | E353: -1.2960421e+09 | F353: Factura A Nº 00002-00002276 - jhonatan miguel vega mendez | H353: 0000200002276
A354: 46134 | B354: 18682 | C354: 371900.83 | D354: 0 | E354: -1.3242003e+09 | F354: N. Crédito B Nº 00002-00000058 - Maximiliano Alberto Videla | G354: ASD | H354: 0000200000058
A355: 46134 | B355: 18743 | C355: 371900.83 | D355: 0 | E355: -1.3236155e+09 | F355: N. Crédito A Nº 00002-00000102 - Juan Jose Concepción | G355: ASD | H355: 0000200000102
A356: 46134 | B356: 18740 | C356: 371900.83 | D356: 0 | E356: -1.3237221e+09 | F356: N. Crédito A Nº 00002-00000101 - Juan Jose Concepción | G356: ASD | H356: 0000200000101
A357: 46134 | B357: 18737 | C357: 371900.83 | D357: 0 | E357: -1.3239346e+09 | F357: N. Crédito A Nº 00002-00000100 - Marcelo Sergio Fidalgo | G357: ASD | H357: 0000200000100
A358: 46134 | B358: 18683 | C358: 0 | D358: 106257.02 | E358: -1.3243065e+09 | F358: Factura B Nº 00002-00001477 - Maximiliano Alberto Videla | H358: 0000200001477
A359: 46134 | B359: 18475 | C359: 0 | D359: 371900.83 | E359: -1.3229252e+09 | F359: Factura B Nº 00002-00001476 - Hector Marcelo Rodriguez | H359: 0000200001476
A360: 46134 | B360: 18472 | C360: 0 | D360: 371900.83 | E360: -1.3225533e+09 | F360: Factura B Nº 00002-00001475 - Sergio Omar Romero | H360: 0000200001475
A361: 46134 | B361: 18470 | C361: 0 | D361: 371900.83 | E361: -1.3221814e+09 | F361: Factura B Nº 00002-00001474 - Juan Pablo Vergez | H361: 0000200001474
A362: 46134 | B362: 18468 | C362: 0 | D362: 371900.83 | E362: -1.3218095e+09 | F362: Factura B Nº 00002-00001473 - Vanina Leonor Lezcano | H362: 0000200001473
A363: 46134 | B363: 18462 | C363: 0 | D363: 371900.83 | E363: -1.3206938e+09 | F363: Factura B Nº 00002-00001472 - Jorge Eduardo Sayavedra | H363: 0000200001472
A364: 46134 | B364: 18460 | C364: 0 | D364: 371900.83 | E364: -1.3203219e+09 | F364: Factura B Nº 00002-00001471 - Diego Rafael Minuet | H364: 0000200001471
A365: 46134 | B365: 18453 | C365: 0 | D365: 371900.83 | E365: -1.3192062e+09 | F365: Factura B Nº 00002-00001470 - Miguel Antonio Castro Aponte | H365: 0000200001470
A366: 46134 | B366: 18434 | C366: 0 | D366: 371900.83 | E366: -1.3169748e+09 | F366: Factura B Nº 00002-00001469 - CRISTIAN ALBERTO RUS | H366: 0000200001469
A367: 46134 | B367: 18427 | C367: 0 | D367: 371900.83 | E367: -1.3158591e+09 | F367: Factura B Nº 00002-00001468 - Javier Alejandro Diaz | H367: 0000200001468
A368: 46134 | B368: 18425 | C368: 0 | D368: 371900.83 | E368: -1.3154872e+09 | F368: Factura B Nº 00002-00001467 - Fernando Augusto Carlos Zacarias Fernandez | H368: 0000200001467
A369: 46134 | B369: 18423 | C369: 0 | D369: 371900.83 | E369: -1.3151153e+09 | F369: Factura B Nº 00002-00001466 - Eduardo Javier Escobar | H369: 0000200001466
... A441: 46134 | B441: 18311 | C441: 0 | D441: 371900.83 | E441: -1.2968921e+09 | F441: Factura A Nº 00002-00002280 - Marcelo Alfredo Marchese | H441: 0000200002280
A442: 46134 | B442: 18451 | C442: 0 | D442: 371900.83 | E442: -1.3188343e+09 | F442: Alquiler - RUIZ - desde: 22/04/2026 hasta: 28/04/2026 Dominio: AH448TS CUIT/CUIL: 27425664137 - FACTURA: 4137
A443: 46134 | B443: 18753 | C443: 0 | D443: 265289.26 | E443: -1.3241461e+09 | F443: Alquiler - Concepción - desde: 24-04-2026 hasta: 28-04-2026 CUIT/CUIL: 20385101814- ASIENTO: 18753
A444: 46134 | B444: 18748 | C444: 0 | D444: 52892.56 | E444: -1.323775e+09 | F444: Alquiler - Concepción - desde: 22/04/2026 hasta: 22/04/2026 Dominio: AH191LK CUIT/CUIL: 20385101814 - FACTURA: 4171
A445: 46135 | B445: 18784 | C445: 371900.83 | D445: 0 | E445: -1.3240403e+09 | F445: N. Crédito A Nº 00002-00000103 - JAVIER LUCIO ALDEA MEDRANO | G445: ASD | H445: 0000200000103
A446: 46135 | B446: 18594 | C446: 0 | D446: 371900.83 | E446: -1.3244122e+09 | F446: Factura A Nº 00002-00002343 - JAVIER LUCIO ALDEA MEDRANO | H446: 0000200002343
...
